Workbook

Sheet Industry
A1: Timestamp | B1: Email | C1: Last Name | D1: First Name | E1: Industry | F1: Accommodation and Food Services | G1: Food and Beverage Services Group | H1: Cafes, Restaurants and Takeaway Food Services | I1: Administrative and Support Services | J1: Administrative Services Group | K1: Employment Services | L1: Other Administrative Services | M1: Building Cleaning, Pest Control and Other Support Services Group | N1: Building Cleaning, Pest Control and Gardening Services | O1: Agriculture, Forestry and Fishing | P1: Agriculture Group | Q1: Fruit and Tree Nut Growing | R1: Mushroom and Vegetable Growing | S1: Nursery and Floriculture Production | T1: Poultry Farming | U1: Sheep, Beef Cattle and Grain Farming | V1: Other Crop Growing | W1: Other Livestock Farming | X1: Agriculture, Forestry and Fishing Support Services Group | Y1: Agriculture and Fishing Support Services | Z1: Aquaculture | AA1: Fishing, Hunting and Trapping Group | AB1: Fishing | AC1: Forestry and Logging | AD1: Arts and Recreation Services | AE1: Creative and Performing Arts Activities | AF1: Gambling Activities | AG1: Heritage Activities | AH1: Parks and Gardens Operations | AI1: Sports and Recreation Activities | AJ1: Amusement and Other Recreation Activities | AK1: Horse and Dog Racing Activities | AL1: Sports and Physical Recreation Activities | AM1: Construction | AN1: Building Construction | AO1: Residential Building Construction | AP1: Construction Services | AQ1: Building Completion Services | AR1: Building Installation Services | AS1: Building Structure Services | AT1: Land Development and Site Preparation Services | AU1: Other Construction Services | AV1: Heavy and Civil Engineering Construction | AW1: Education and Training | AX1: Adult, Community and Other Education | AY1: Adult, Community and Other Education | AZ1: Preschool and School Education | BA1: School Education | BB1: Tertiary Education | BC1: Electricity Supply | BD1: Electricity Distribution | BE1: Electricity Generation | BF1: Waste Collection, Treatment and Disposal Services | BG1: Waste Collection Services | BH1: Waste Treatment, Disposal and Remediation Services | BI1: Water Supply, Sewerage and Drainage Services | BJ1: Financial and Insurance Services | BK1: Auxiliary Finance and Insurance Services | BL1: Auxiliary Finance and Investment Services | BM1: Finance | BN1: Depository Financial Intermediation | BO1: Insurance and Superannuation Funds | BP1: Health and General Insurance | BQ1: Health Care and Social Assistance | BR1: Hospitals | BS1: Medical and Other Health Care Services | BT1: Allied Health Services | BU1: Medical Services | BV1: Other Health Care Services | BW1: Residential Care Services | BX1: Social Assistance Services | BY1: Information Media and Telecommunications | BZ1: Broadcasting (except Internet) | CA1: Television Broadcasting | CB1: Internet Service Providers, Web Search Portals and Data Processing Services | CC1: Data Processing, Web Hosting and Electronic Information Storage Services | CD1: Library and Other Information Services | CE1: Motion Picture and Sound Recording Activities | CF1: Motion Picture and Video Activities | CG1: Sound Recording and Music Publishing | CH1: Publishing (except Internet and Music Publishing) | CI1: Newspaper, Periodical, Book and Directory Publishing | CJ1: Manufacturing | CK1: Basic Chemical and Chemical Product Manufacturing | CL1: Basic Chemical Manufacturing | CM1: Basic Polymer Manufacturing | CN1: Cleaning Compound and Toiletry Preparation Manufacturing | CO1: Fertiliser and Pesticide Manufacturing | CP1: Pharmaceutical and Medicinal Product Manufacturing | CQ1: Other Basic Chemical Product Manufacturing | CR1: Beverage and Tobacco Product Manufacturing | CS1: Beverage Manufacturing | CT1: Fabricated Metal Product Manufacturing | CU1: Metal Container Manufacturing | CV1: Structural Metal Product Manufacturing | CW1: Other Fabricated Metal Product Manufacturing | CX1: Food Product Manufacturing | CY1: Bakery Product Manufacturing | CZ1: Dairy Product Manufacturing | DA1: Grain Mill and Cereal Product Manufacturing | DB1: Meat and Meat Product Manufacturing | DC1: Sugar and Confectionery Manufacturing | DD1: Other Food Product Manufacturing | DE1: Furniture and Other Manufacturing | DF1: Furniture Manufacturing | DG1: Other Manufacturing | DH1: Machinery and Equipment Manufacturing | DI1: Computer and Electronic Equipment Manufacturing | DJ1: Domestic Appliance Manufacturing | DK1: Electrical Equipment Manufacturing | DL1: Professional and Scientific Equipment Manufacturing | DM1: Pump, Compressor, Heating and Ventilation Equipment Manufacturing | DN1: Specialised Machinery and Equipment Manufacturing | DO1: Other Machinery and Equipment Manufacturing | DP1: Non-Metallic Mineral Product Manufacturing | DQ1: Cement, Lime, Plaster and Concrete Product Manufacturing | DR1: Ceramic Product Manufacturing | DS1: Petroleum and Coal Product Manufacturing | DT1: Polymer Product and Rubber Product Manufacturing | DU1: Polymer Product Manufacturing | DV1: Primary Metal and Metal Product Manufacturing | DW1: Basic Ferrous Metal Manufacturing | DX1: Basic Ferrous Metal Product Manufacturing | DY1: Basic Non-Ferrous Metal Manufacturing | DZ1: Basic Non-Ferrous Metal Product Manufacturing | EA1: Printing (including the Reproduction of Recorded Media) | EB1: Printing and Printing Support Services | EC1: Pulp, Paper and Converted Paper Product Manufacturing | ED1: Converted Paper Product Manufacturing | EE1: Textile, Leather, Clothing and Footwear Manufacturing | EF1: Clothing and Footwear Manufacturing | EG1: Textile Manufacturing | EH1: Textile Product Manufacturing | EI1: Transport Equipment Manufacturing | EJ1: Motor Vehicle and Motor Vehicle Part Manufacturing | EK1: Other Transport Equipment Manufacturing | EL1: Wood Product Manufacturing | EM1: Log Sawmilling and Timber Dressing | EN1: Other Wood Product Manufacturing | EO1: Mining | EP1: Exploration and Other Mining Support Services | EQ1: Exploration | ER1: Metal Ore Mining | ES1: Non-Metallic Mineral Mining and Quarrying | ET1: Construction Material Mining | EU1: Professional, Scientific and Technical Services | EV1: Professional, Scientific and Technical Services (Except Computer System Design and Related Services) | EW1: Architectural, Engineering and Technical Services | EX1: Legal and Accounting Services | EY1: Management and Related Consulting Services | EZ1: Other Professional, Scientific and Technical Services | FA1: Public Administration and Safety | FB1: Public Administration | FC1: Government Representation | FD1: Public Order, Safety and Regulatory Services | FE1: Public Order and Safety Services | FF1: Rental Hiring and Real Estate Services | FG1: Property Operators and Real Estate Services | FH1: Property Operators | FI1: Rental and Hiring Services (except Real Estate) | FJ1: Motor Vehicle and Transport Equipment Rental and Hiring | FK1: Other Goods and Equipment Rental and Hiring | FL1: Retail Trade | FM1: Food Retailing | FN1: Specialised Food Retailing | FO1: Motor Vehicle and Motor Vehicle Parts Retailing | FP1: Motor Vehicle Parts and Tyre Retailing | FQ1: Motor Vehicle Retailing | FR1: Non-Store Retailing and Retail Commission Based Buying and/or Selling | FS1: Other Store-Based Retailing | FT1: Clothing, Footwear and Personal Accessory Retailing | FU1: Electrical and Electronic Goods Retailing | FV1: Furniture, Floor Coverings, Houseware and Textile Goods Retailing | FW1: Hardware, Building and Garden Supplies Retailing | FX1: Pharmaceutical and Other Store-Based Retailing | FY1: Recreational Goods Retailing | FZ1: Transport, Postal and Warehousing | GA1: Postal and Courier Pick-up and Delivery Services | GB1: Rail Transport | GC1: Road Transport | GD1: Road Passenger Transport | GE1: Transport Support Services | GF1: Other Transport Support Services | GG1: Water Transport Support Services | GH1: Warehousing and Storage Services | GI1: Water Transport | GJ1: Other Transport | GK1: Pipeline and Other Transport | GL1: Wholesale Trade | GM1: Basic Material Wholesaling | GN1: Agricultural Product Wholesaling | GO1: Mineral, Metal and Chemical Wholesaling | GP1: Timber and Hardware Goods Wholesaling | GQ1: Grocery, Liquor and Tobacco Product Wholesaling | GR1: Machinery and Equipment Wholesaling | GS1: Specialised Industrial Machinery and Equipment Wholesaling | GT1: Other Machinery and Equipment Wholesaling | GU1: Motor Vehicle and Motor Vehicle Parts Wholesaling | GV1: Other Goods Wholesaling | GW1: Furniture, Floor Covering and Other Goods Wholesaling | GX1: Textile, Clothing and Footwear Wholesaling | GY1: Other Services | GZ1: Personal and Other Services | HA1: Civic Professional and Other Interest Group Services | HB1: Personal Care Services | HC1: Other Personal Services | HD1: Private Households Employing Staff and Undifferentiated Goods- and Service-Producing Activities of Households for Own Use | HE1: Repair and Maintenance | HF1: Automotive Repair and Maintenance | HG1: Machinery and Equipment Repair and Maintenance | HH1: Other Repair and Maintenance | HI1: Accommodation | HJ1: Contact persons email: | HK1: Accommodation

Sheet Industry Acronyms
A1: =Industry!A1 -> Timestamp | B1: =Industry!B1 -> Email | C1: =Industry!C1 -> Last Name | D1: =Industry!D1 -> First Name | E1: =Industry!E1 -> Industry | F1: =Industry!F1 -> Accommodation and Food Services | G1: =Industry!G1 -> Food and Beverage Services Group | H1: =Industry!H1 -> Cafes, Restaurants and Takeaway Food Services | ... HH1: =Industry!HH1 -> Other Repair and Maintenance | HI1: Accommodation | HJ1: Cafes, Restaurants and Takeaway Food Services | HK1: Clubs (Hospitality) | HL1: Pubs, Taverns and Bars | HM1: Employment Services | HN1: Travel Agency and Tour Arrangement Services | HO1: Other Administrative Services | HP1: Building Cleaning, Pest Control and Gardening Services | HQ1: Packaging Services | HR1: Dairy Cattle Farming | HS1: Deer Farming | HT1: Fruit and Tree Nut Growing | HU1: Mushroom and Vegetable Growing | HV1: Nursery and Floriculture Production | HW1: Poultry Farming | HX1: Sheep, Beef Cattle and Grain Farming | HY1: Other Crop Growing | HZ1: Other Livestock Farming | IA1: Agriculture and Fishing Support Services | IB1: Forestry Support Services | IC1: Aquaculture | ID1: Fishing | IE1: Hunting and Trapping | IF1: Forestry and Logging | IG1: Creative and Performing Arts Activities | IH1: Gambling Activities | II1: Museum Operation | IJ1: Parks and Gardens Operations | IK1: Amusement and Other Recreation Activities | IL1: Horse and Dog Racing Activities | IM1: Sports and Physical Recreation Activities | IN1: Residential Building Construction | IO1: Non-Residential Building Construction | IP1: Building Completion Services | IQ1: Building Installation Services | IR1: Building Structure Services | IS1: Land Development and Site Preparation Services | IT1: Other Construction Services | IU1: Road and Bridge Construction | IV1: Other Heavy and Civil Engineering Construction | IW1: Adult, Community and Other Education | IX1: Educational Support Services | IY1: Preschool Education | IZ1: School Education | JA1: Higher Education | JB1: Technical and Vocational Education and Training | JC1: Electricity Distribution | JD1: Electricity Generation | JE1: Electricity Transmission | JF1: On Selling Electricity and Electricity Market Operation | JG1: Gas Supply | JH1: Waste Collection Services | JI1: Waste Treatment, Disposal and Remediation Services | JJ1: Sewerage and Drainage Services | JK1: Water Supply | JL1: Auxiliary Finance and Investment Services | JM1: Auxiliary Insurance Services | JN1: Central Banking | JO1: Depository Financial Intermediation | JP1: Financial Asset Investing | JQ1: Non-Depository Financing | JR1: Health and General Insurance | JS1: Life Insurance | JT1: Superannuation Funds | JU1: Hospitals | JV1: Medical Services | JW1: Pathology and Diagnostic Imaging Services | JX1: Allied Health Services | JY1: Other Health Care Services | JZ1: Aged Care Residential Services | KA1: Other Residential Care Services | KB1: Child Care Services | KC1: Other Social Assistance Services | KD1: Radio Broadcasting | KE1: Television Broadcasting | KF1: Internet Publishing and Broadcasting | KG1: Data Processing, Web Hosting and Electronic Information Storage Services | KH1: Internet Service Providers and Web Search Portals | KI1: Libraries and Archives | KJ1: Other Information Services | KK1: Motion Picture and Video Activities | KL1: Sound Recording and Music Publishing | KM1: Newspaper, Periodical, Book and Directory Publishing | KN1: Software Publishing | KO1: Telecommunications Services | KP1: Basic Chemical Manufacturing | KQ1: Basic Polymer Manufacturing | KR1: Cleaning Compound and Toiletry Preparation Manufacturing | KS1: Fertiliser and Pesticide Manufacturing | KT1: Pharmaceutical and Medicinal Product Manufacturing | KU1: Other Basic Chemical Product Manufacturing | KV1: Beverage Manufacturing | KW1: Cigarette and Tobacco Product Manufacturing | KX1: Iron and Steel Forging | KY1: Metal Container Manufacturing | KZ1: Sheet Metal Product Manufacturing (except Metal Structural and Container Products) | LA1: Structural Metal Product Manufacturing | LB1: Other Fabricated Metal Product Manufacturing | LC1: Bakery Product Manufacturing | LD1: Dairy Product Manufacturing | LE1: Fruit and Vegetable Processing | LF1: Grain Mill and Cereal Product Manufacturing | LG1: Meat and Meat Product Manufacturing | LH1: Oil and Fat Manufacturing | LI1: Seafood Processing | LJ1: Sugar and Confectionery Manufacturing | LK1: Other Food Product Manufacturing | LL1: Furniture Manufacturing | LM1: Other Manufacturing | LN1: Computer and Electronic Equipment Manufacturing | LO1: Domestic Appliance Manufacturing | LP1: Electrical Equipment Manufacturing | LQ1: Professional and Scientific Equipment Manufacturing | LR1: Pump, Compressor, Heating and Ventilation Equipment Manufacturing | LS1: Specialised Machinery and Equipment Manufacturing | LT1: Other Machinery and Equipment Manufacturing | LU1: Cement, Lime, Plaster and Concrete Product Manufacturing | LV1: Ceramic Product Manufacturing | LW1: Glass and Glass Product Manufacturing | LX1: Other Non-Metallic Mineral Product Manufacturing | LY1: Petroleum Refining and Petroleum Fuel Manufacturing | LZ1: Other Petroleum and Coal Product Manufacturing | MA1: Natural Rubber Product Manufacturing | MB1: Polymer Product Manufacturing | MC1: Basic Ferrous Metal Manufacturing | MD1: Basic Ferrous Metal Product Manufacturing | ME1: Basic Non-Ferrous Metal Manufacturing | MF1: Basic Non-Ferrous Metal Product Manufacturing | MG1: Printing and Printing Support Services | MH1: Reproduction of Recorded Media | MI1: Converted Paper Product Manufacturing | MJ1: Pulp, Paper and Paperboard Manufacturing | MK1: Clothing and Footwear Manufacturing | ML1: Knitted Product Manufacturing | MM1: Leather Tanning, Fur Dressing and Leather Product Manufacturing | MN1: Textile Manufacturing | MO1: Textile Product Manufacturing | MP1: Motor Vehicle and Motor Vehicle Part Manufacturing | MQ1: Other Transport Equipment Manufacturing | MR1: Log Sawmilling and Timber Dressing | MS1: Other Wood Product Manufacturing | MT1: Coal Mining | MU1: Exploration | MV1: Other Mining Support Services | MW1: Metal Ore Mining | MX1: Construction Material Mining | MY1: Oil and Gas Extraction | MZ1: Other Non-Metallic Mineral Mining and Quarrying | NA1: Computer System Design and Related Services | NB1: Advertising Services | NC1: Architectural, Engineering and Technical Services | ND1: Legal and Accounting Services | NE1: Management and Related Consulting Services | NF1: Market Research and Statistical Services | NG1: Scientific Research Services | NH1: Veterinary Services | NI1: Other Professional, Scientific and Technical Services | NJ1: Central Government Administration | NK1: State Government Administration | NL1: Local Government Administration | NM1: Justice | NN1: Government Representation | NO1: Defence | NP1: Public Order and Safety Services | NQ1: Regulatory Services | NR1: Property Operators | NS1: Real Estate Services | NT1: Farm Animal and Bloodstock Leasing | NU1: Motor Vehicle and Transport Equipment Rental and Hiring | NV1: Non-Financial Intangible Assets (Except Copyrights) Leasing | NW1: Other Goods and Equipment Rental and Hiring | NX1: Supermarket and Grocery Stores | NY1: Specialised Food Retailing | NZ1: Fuel Retailing | OA1: Motor Vehicle Parts and Tyre Retailing | OB1: Motor Vehicle Retailing | OC1: Non-Store Retailing | OD1: Retail Commission-Based Buying and/or Selling | OE1: Clothing, Footwear and Personal Accessory Retailing | OF1: Department Stores | OG1: Electrical and Electronic Goods Retailing | OH1: Furniture, Floor Coverings, Houseware and Textile Goods Retailing | OI1: Hardware, Building and Garden Supplies Retailing | OJ1: Pharmaceutical and Other Store-Based Retailing | OK1: Recreational Goods Retailing | OL1: Air and Space Transport | OM1: Postal and Courier Pick-up and Delivery Services | ON1: Rail Freight Transport | OO1: Rail Passenger Transport | OP1: Road Freight Transport | OQ1: Road Passenger Transport | OR1: Airport Operations and Other Air Transport Support Services | OS1: Water Transport Support Services | OT1: Other Transport Support Services | OU1: Warehousing and Storage Services | OV1: Water Freight Transport | OW1: Water Passenger Transport | OX1: Pipeline and Other Transport | OY1: Scenic and Sightseeing Transport | OZ1: Agricultural Product Wholesaling | PA1: Mineral, Metal and Chemical Wholesaling | PB1: Timber and Hardware Goods Wholesaling | PC1: Commission-Based Wholesaling | PD1: Grocery, Liquor and Tobacco Product Wholesaling | PE1: Specialised Industrial Machinery and Equipment Wholesaling | PF1: Other Machinery and Equipment Wholesaling | PG1: Motor Vehicle and Motor Vehicle Parts Wholesaling | PH1: Textile, Clothing and Footwear Wholesaling | PI1: Furniture, Floor Covering and Other Goods Wholesaling | PJ1: Pharmaceutical and Toiletry Goods Wholesaling | PK1: Civic, Professional and Other Interest Group Services | PL1: Funeral, Crematorium and Cemetery Services | PM1: Personal Care Services | PN1: Religious Services | PO1: Other Personal Services | PP1: Private Households Employing Staff and Undifferentiated Goods- and Service-Producing Activities of Households for Own Use | PQ1: Automotive Repair and Maintenance | PR1: Machinery and Equipment Repair and Maintenance | PS1: Other Repair and Maintenance
HI2: =if(ISERROR(SEARCH("Accommodation",F2)),"","440") | HJ2: =if(ISERROR(SEARCH("Cafes, Restaurants and Takeaway Food Services",G2)),"","450") | HK2: =if(ISERROR(SEARCH("Clubs (Hospitality)",G2)),"","453") | HL2: =if(ISERROR(SEARCH("Pubs, Taverns and Bars",G2)),"","452") | HM2: =if(ISERROR(SEARCH("Employment Services",J2)),"","721") | HN2: =if(ISERROR(SEARCH("Travel Agency and Tour Arrangement Services",J2)),"","722") | HO2: =if(ISERROR(SEARCH("Other Administrative Services",J2)),"","729") | HP2: =if(ISERROR(SEARCH("Building Cleaning, Pest Control and Gardening Servicess",M2)),"","731") | HQ2: =if(ISERROR(SEARCH("Packaging Services",M2)),"","732") | HR2: =if(ISERROR(SEARCH("Dairy Cattle Farming",P2)),"","016") | HS2: =if(ISERROR(SEARCH("Deer Farming",P2)),"","018") | HT2: =if(ISERROR(SEARCH("Fruit and Tree Nut Growing",P2)),"","013") | HU2: =if(ISERROR(SEARCH("Mushroom and Vegetable Growing",P2)),"","012") | HV2: =if(ISERROR(SEARCH("Nursery and Floriculture Production",P2)),"","011") | HW2: =if(ISERROR(SEARCH("Poultry Farming",P2)),"","017") | HX2: =if(ISERROR(SEARCH("Sheep, Beef Cattle and Grain Farming",P2)),"","014") | HY2: =if(ISERROR(SEARCH("Other Crop Growing",P2)),"","015") | HZ2: =if(ISERROR(SEARCH("Other Livestock Farming",P2)),"","019") | IA2: =if(ISERROR(SEARCH("Agriculture and Fishing Support Services",X2)),"","052") | IB2: =if(ISERROR(SEARCH("Forestry Support Services",X2)),"","051") | IC2: =if(ISERROR(SEARCH("Aquaculture",Z2)),"","020") | ID2: =if(ISERROR(SEARCH("Fishing",AA2)),"","041") | IE2: =if(ISERROR(SEARCH("Hunting and Trapping",AA2)),"","042") | IF2: =if(ISERROR(SEARCH("Forestry and Logging",AB2)),"","030") | IG2: =if(ISERROR(SEARCH("Creative and Performing Arts Activities",AD2)),"","900") | IH2: =if(ISERROR(SEARCH("Gambling Activities",AD2)),"","920") | II2: =if(ISERROR(SEARCH("Museum Operation",AG2)),"","891") | IJ2: =if(ISERROR(SEARCH("Parks and Gardens Operations",AG2)),"","892") | IK2: =if(ISERROR(SEARCH("Amusement and Other Recreation Activities",AI2)),"","913") | IL2: =if(ISERROR(SEARCH("Horse and Dog Racing Activities",AI2)),"","912") | IM2: =if(ISERROR(SEARCH("Sports and Physical Recreation Activities",AI2)),"","911") | IN2: =if(ISERROR(SEARCH("Residential Building Construction",AN2)),"","301") | IO2: =if(ISERROR(SEARCH("Non-Residential Building Construction",AN2)),"","302") | IP2: =if(ISERROR(SEARCH("Building Completion Services",AP2)),"","324") | IQ2: =if(ISERROR(SEARCH("Building Installation Servicess",AP2)),"","323") | IR2: =if(ISERROR(SEARCH("Building Structure Services",AP2)),"","322") | IS2: =if(ISERROR(SEARCH("Land Development and Site Preparation Services",AP2)),"","321") | IT2: =if(ISERROR(SEARCH("Other Construction Services",AP2)),"","329") | IU2: =if(ISERROR(SEARCH("Road and Bridge Construction",AV2)),"","310") | IV2: =if(ISERROR(SEARCH("Other Heavy and Civil Engineering Construction",AV2)),"","310") | IW2: =if(ISERROR(SEARCH("Adult, Community and Other Education",AX2)),"","821") | IX2: =if(ISERROR(SEARCH("Educational Support Services",AX2)),"","822") | IY2: =if(ISERROR(SEARCH("Preschool Education",AZ2)),"","801") | IZ2: =if(ISERROR(SEARCH("School Education",AZ2)),"","802") | JA2: =if(ISERROR(SEARCH("Higher Education",BB2)),"","810") | JB2: =if(ISERROR(SEARCH("Higher Education",BC2)),"","810") | JC2: =if(ISERROR(SEARCH("Electricity Distribution",BC2)),"","263") | JD2: =if(ISERROR(SEARCH("Electricity Generation",BC2)),"","261") | JE2: =if(ISERROR(SEARCH("Electricity Transmission",BC2)),"","262") | JF2: =if(ISERROR(SEARCH("On Selling Electricity and Electricity Market Operation",BC2)),"","264") | JG2: =if(ISERROR(SEARCH("Gas Supply",BC2)),"","270") | JH2: =if(ISERROR(SEARCH("Waste Collection Services",BF2)),"","291") | JI2: =if(ISERROR(SEARCH("Waste Treatment, Disposal and Remediation Services",BF2)),"","292") | JJ2: =if(ISERROR(SEARCH("Sewerage and Drainage Services",BI2)),"","281") | JK2: =if(ISERROR(SEARCH("Water Supply",BI2)),"","281") | JL2: =if(ISERROR(SEARCH("Auxiliary Finance and Investment Services",BK2)),"","641") | JM2: =if(ISERROR(SEARCH("Auxiliary Insurance Services",BK2)),"","642") | JN2: =if(ISERROR(SEARCH("Central Banking",BM2)),"","621") | JO2: =if(ISERROR(SEARCH("Depository Financial Intermediation",BM2)),"","622") | JP2: =if(ISERROR(SEARCH("Financial Asset Investing",BM2)),"","624") | JQ2: =if(ISERROR(SEARCH("Non-Depository Financing",BM2)),"","623") | JR2: =if(ISERROR(SEARCH("Health and General Insurance",BO2)),"","632") | JS2: =if(ISERROR(SEARCH("Life Insurance",BO2)),"","631") | JT2: =if(ISERROR(SEARCH("Superannuation Funds",BO2)),"","633") | JU2: =if(ISERROR(SEARCH("Hospitals",BQ2)),"","840") | JV2: =if(ISERROR(SEARCH("Medical Services",BS2)),"","851") | JW2: =if(ISERROR(SEARCH("Pathology and Diagnostic Imaging Services",BS2)),"","852") | JX2: =if(ISERROR(SEARCH("Allied Health Services",BS2)),"","853") | JY2: =if(ISERROR(SEARCH("Other Health Care Services",BS2)),"","859") | JZ2: =if(ISERROR(SEARCH("Aged Care Residential Services",BW2)),"","860") | KA2: =if(ISERROR(SEARCH("Other Residential Care Services",BW2)),"","860") | KB2: =if(ISERROR(SEARCH("Child Care Services",BX2)),"","871") | KC2: =if(ISERROR(SEARCH("Other Social Assistance Services",BX2)),"","879") | KD2: =if(ISERROR(SEARCH("Radio Broadcasting",BZ2)),"","561") | KE2: =if(ISERROR(SEARCH("Television Broadcasting",BZ2)),"","562") | KF2: =if(ISERROR(SEARCH("Internet Publishing and Broadcasting",BY2)),"","570") | KG2: =if(ISERROR(SEARCH("Data Processing, Web Hosting and Electronic Information Storage Services",CB2)),"","592") | KH2: =if(ISERROR(SEARCH("Internet Service Providers and Web Search Portals",CB2)),"","591") | KI2: =if(ISERROR(SEARCH("Libraries and Archives",CD2)),"","601") | KJ2: =if(ISERROR(SEARCH("Other Information Services",CD2)),"","602") | KK2: =if(ISERROR(SEARCH("Motion Picture and Video Activities",CE2)),"","551") | KL2: =if(ISERROR(SEARCH("Sound Recording and Music Publishing",CE2)),"","552") | KM2: =if(ISERROR(SEARCH("Newspaper, Periodical, Book and Directory Publishing",CH2)),"","541") | KN2: =if(ISERROR(SEARCH("Software Publishing",CH2)),"","542") | KO2: =if(ISERROR(SEARCH("Telecommunications Services",BY2)),"","580") | KP2: =if(ISERROR(SEARCH("Basic Chemical Manufacturing",CK2)),"","181") | KQ2: =if(ISERROR(SEARCH("Basic Polymer Manufacturing",CK2)),"","182") | KR2: =if(ISERROR(SEARCH("Cleaning Compound and Toiletry Preparation Manufacturing",CK2)),"","185") | KS2: =if(ISERROR(SEARCH("Fertiliser and Pesticide Manufacturing",CK2)),"","183") | KT2: =if(ISERROR(SEARCH("Pharmaceutical and Medicinal Product Manufacturing",CK2)),"","184") | KU2: =if(ISERROR(SEARCH("Other Basic Chemical Product Manufacturing",CK2)),"","189") | KV2: =if(ISERROR(SEARCH("Beverage Manufacturing",CR2)),"","121") | KW2: =if(ISERROR(SEARCH("Cigarette and Tobacco Product Manufacturing",CR2)),"","122") | KX2: =if(ISERROR(SEARCH("Iron and Steel Forging",CT2)),"","221") | KY2: =if(ISERROR(SEARCH("Metal Container Manufacturing",CT2)),"","223") | KZ2: =if(ISERROR(SEARCH("Sheet Metal Product Manufacturing (except Metal Structural and Container Products)",CT2)),"","224") | LA2: =if(ISERROR(SEARCH("Structural Metal Product Manufacturing",CT2)),"","222") | LB2: =if(ISERROR(SEARCH("Other Fabricated Metal Product Manufacturing",CT2)),"","229") | LC2: =if(ISERROR(SEARCH("Bakery Product Manufacturing",CX2)),"","117") | LD2: =if(ISERROR(SEARCH("Dairy Product Manufacturing",CX2)),"","113") | LE2: =if(ISERROR(SEARCH("Fruit and Vegetable Processing",CX2)),"","114") | LF2: =if(ISERROR(SEARCH("Grain Mill and Cereal Product Manufacturing",CX2)),"","116") | LG2: =if(ISERROR(SEARCH("Meat and Meat Product Manufacturing",CX2)),"","111") | LH2: =if(ISERROR(SEARCH("Oil and Fat Manufacturing",CX2)),"","115") | LI2: =if(ISERROR(SEARCH("Seafood Processing",CX2)),"","112") | LJ2: =if(ISERROR(SEARCH("Sugar and Confectionery Manufacturing",CX2)),"","118") | LK2: =if(ISERROR(SEARCH("Other Food Product Manufacturing",CX2)),"","119") | LL2: =if(ISERROR(SEARCH("Furniture Manufacturing",DE2)),"","251") | LM2: =if(ISERROR(SEARCH("Other Manufacturing",DE2)),"","259") | LN2: =if(ISERROR(SEARCH("Computer and Electronic Equipment Manufacturing",DH2)),"","242") | LO2: =if(ISERROR(SEARCH("Domestic Appliance Manufacturing",DH2)),"","244") | LP2: =if(ISERROR(SEARCH("Electrical Equipment Manufacturing",DH2)),"","243") | LQ2: =if(ISERROR(SEARCH("Professional and Scientific Equipment Manufacturing",DH2)),"","241") | LR2: =if(ISERROR(SEARCH("Pump, Compressor, Heating and Ventilation Equipment Manufacturing",DH2)),"","245") | LS2: =if(ISERROR(SEARCH("Specialised Machinery and Equipment Manufacturing",DH2)),"","246") | LT2: =if(ISERROR(SEARCH("Other Machinery and Equipment Manufacturing",DH2)),"","249") | LU2: =if(ISERROR(SEARCH("Cement, Lime, Plaster and Concrete Product Manufacturing",DP2)),"","203") | LV2: =if(ISERROR(SEARCH("Ceramic Product Manufacturing",DP2)),"","202") | LW2: =if(ISERROR(SEARCH("Glass and Glass Product Manufacturing",DP2)),"","201") | LX2: =if(ISERROR(SEARCH("Other Non-Metallic Mineral Product Manufacturing",DP2)),"","209") | LY2: =if(ISERROR(SEARCH("Petroleum Refining and Petroleum Fuel Manufacturing",DS2)),"","170") | LZ2: =if(ISERROR(SEARCH("Other Petroleum and Coal Product Manufacturing",DS2)),"","170") | MA2: =if(ISERROR(SEARCH("Natural Rubber Product Manufacturing",DT2)),"","192") | MB2: =if(ISERROR(SEARCH("Polymer Product Manufacturing",DT2)),"","191") | MC2: =if(ISERROR(SEARCH("Basic Ferrous Metal Manufacturing",DV2)),"","211") | MD2: =if(ISERROR(SEARCH("Basic Ferrous Metal Product Manufacturing",DV2)),"","212") | ME2: =if(ISERROR(SEARCH("Basic Non-Ferrous Metal Manufacturing",DV2)),"","213") | MF2: =if(ISERROR(SEARCH("Basic Non-Ferrous Metal Product Manufacturing",DV2)),"","214") | MG2: =if(ISERROR(SEARCH("Printing and Printing Support Services",EA2)),"","161") | MH2: =if(ISERROR(SEARCH("Reproduction of Recorded Media",EA2)),"","162") | MI2: =if(ISERROR(SEARCH("Converted Paper Product Manufacturing",EC2)),"","152") | MJ2: =if(ISERROR(SEARCH("Pulp, Paper and Paperboard Manufacturing",EC2)),"","151") | MK2: =if(ISERROR(SEARCH("Clothing and Footwear Manufacturing",EE2)),"","135") | ML2: =if(ISERROR(SEARCH("Knitted Product Manufacturing",EE2)),"","134") | MM2: =if(ISERROR(SEARCH("Leather Tanning, Fur Dressing and Leather Product Manufacturing",EE2)),"","132") | MN2: =if(ISERROR(SEARCH("Textile Manufacturing",EE2)),"","131") | MO2: =if(ISERROR(SEARCH("Textile Product Manufacturing",EE2)),"","133") | MP2: =if(ISERROR(SEARCH("Motor Vehicle and Motor Vehicle Part Manufacturing",EI2)),"","231") | MQ2: =if(ISERROR(SEARCH("Other Transport Equipment Manufacturing",EI2)),"","239") | MR2: =if(ISERROR(SEARCH("Log Sawmilling and Timber Dressing",EL2)),"","141") | MS2: =if(ISERROR(SEARCH("Other Wood Product Manufacturing",EL2)),"","149") | MT2: =if(ISERROR(SEARCH("Coal Mining",EO2)),"","060") | MU2: =if(ISERROR(SEARCH("Exploration",EP2)),"","101") | MV2: =if(ISERROR(SEARCH("Other Mining Support Services",EP2)),"","109") | MW2: =if(ISERROR(SEARCH("Metal Ore Mining",EO2)),"","080") | MX2: =if(ISERROR(SEARCH("Construction Material Mining",ES2)),"","091") | MY2: =if(ISERROR(SEARCH("Oil and Gas Extraction",EO2)),"","070") | MZ2: =if(ISERROR(SEARCH("Other Non-Metallic Mineral Mining and Quarrying",ES2)),"","099") | NA2: =if(ISERROR(SEARCH("Computer System Design and Related Services",EU2)),"","700") | NB2: =if(ISERROR(SEARCH("Advertising Services",EV2)),"","694") | NC2: =if(ISERROR(SEARCH("Architectural, Engineering and Technical Services",EV2)),"","692") | ND2: =if(ISERROR(SEARCH("Legal and Accounting Services",EV2)),"","693") | NE2: =if(ISERROR(SEARCH("Management and Related Consulting Services",EV2)),"","696") | NF2: =if(ISERROR(SEARCH("Market Research and Statistical Services",EV2)),"","695") | NG2: =if(ISERROR(SEARCH("Scientific Research Services",EV2)),"","691") | NH2: =if(ISERROR(SEARCH("Veterinary Services",EV2)),"","697") | NI2: =if(ISERROR(SEARCH("Other Professional, Scientific and Technical Services",EV2)),"","699") | NJ2: =if(ISERROR(SEARCH("Central Government Administration",FB2)),"","751") | NK2: =if(ISERROR(SEARCH("State Government Administration",FB2)),"","752") | NL2: =if(ISERROR(SEARCH("Local Government Administration",FB2)),"","753") | NM2: =if(ISERROR(SEARCH("Justice",FB2)),"","754") | NN2: =if(ISERROR(SEARCH("Government Representation",FB2)),"","755") | NO2: =if(ISERROR(SEARCH("Defence",FA2)),"","760") | NP2: =if(ISERROR(SEARCH("Public Order and Safety Services",FD2)),"","771") | NQ2: =if(ISERROR(SEARCH("Regulatory Services",FD2)),"","772") | NR2: =if(ISERROR(SEARCH("Property Operators",FG2)),"","671") | NS2: =if(ISERROR(SEARCH("Real Estate Services",FG2)),"","672") | NT2: =if(ISERROR(SEARCH("Farm Animal and Bloodstock Leasing",FI2)),"","662") | NU2: =if(ISERROR(SEARCH("Motor Vehicle and Transport Equipment Rental and Hiring",FI2)),"","661") | NV2: =if(ISERROR(SEARCH("Non-Financial Intangible Assets (Except Copyrights) Leasing",FI2)),"","664") | NW2: =if(ISERROR(SEARCH("Other Goods and Equipment Rental and Hiring",FI2)),"","663") | NX2: =if(ISERROR(SEARCH("Supermarket and Grocery Stores",FM2)),"","411") | NY2: =if(ISERROR(SEARCH("Specialised Food Retailing",FM2)),"","412") | NZ2: =if(ISERROR(SEARCH("Fuel Retailing",FL2)),"","400") | OA2: =if(ISERROR(SEARCH("Motor Vehicle Parts and Tyre Retailing",FO2)),"","392") | OB2: =if(ISERROR(SEARCH("Motor Vehicle Retailing",FO2)),"","391") | OC2: =if(ISERROR(SEARCH("Non-Store Retailing",FR2)),"","431") | OD2: =if(ISERROR(SEARCH("Retail Commission-Based Buying and/or Selling",FR2)),"","432") | OE2: =if(ISERROR(SEARCH("Clothing, Footwear and Personal Accessory Retailing",FS2)),"","425") | OF2: =if(ISERROR(SEARCH("Department Stores",FS2)),"","426") | OG2: =if(ISERROR(SEARCH("Electrical and Electronic Goods Retailing",FS2)),"","422") | OH2: =if(ISERROR(SEARCH("Furniture, Floor Coverings, Houseware and Textile Goods Retailing",FS2)),"","421") | OI2: =if(ISERROR(SEARCH("Hardware, Building and Garden Supplies Retailing",FS2)),"","423") | OJ2: =if(ISERROR(SEARCH("Pharmaceutical and Other Store-Based Retailing",FS2)),"","427") | OK2: =if(ISERROR(SEARCH("Recreational Goods Retailing",FS2)),"","424") | OL2: =if(ISERROR(SEARCH("Air and Space Transport",FZ2)),"","490") | OM2: =if(ISERROR(SEARCH("Postal and Courier Pick-up and Delivery Services",FZ2)),"","510") | ON2: =if(ISERROR(SEARCH("Rail Freight Transport",GB2)),"","471") | OO2: =if(ISERROR(SEARCH("Rail Passenger Transport",GB2)),"","472") | OP2: =if(ISERROR(SEARCH("Road Freight Transport",GC2)),"","461") | OQ2: =if(ISERROR(SEARCH("Road Passenger Transport",GC2)),"","462") | OR2: =if(ISERROR(SEARCH("Airport Operations and Other Air Transport Support Services",GE2)),"","522") | OS2: =if(ISERROR(SEARCH("Water Transport Support Services",GE2)),"","521") | OT2: =if(ISERROR(SEARCH("Other Transport Support Services",GE2)),"","529") | OU2: =if(ISERROR(SEARCH("Warehousing and Storage Services",FZ2)),"","530") | OV2: =if(ISERROR(SEARCH("Water Freight Transport",GI2)),"","481") | OW2: =if(ISERROR(SEARCH("Water Freight Transport",GI2)),"","482") | OX2: =if(ISERROR(SEARCH("Pipeline and Other Transport",GJ2)),"","502") | OY2: =if(ISERROR(SEARCH("Scenic and Sightseeing Transport",GJ2)),"","501") | OZ2: =if(ISERROR(SEARCH("Agricultural Product Wholesaling",GM2)),"","331") | PA2: =if(ISERROR(SEARCH("Mineral, Metal and Chemical Wholesaling",GM2)),"","332") | PB2: =if(ISERROR(SEARCH("Timber and Hardware Goods Wholesaling",GM2)),"","333") | PC2: =if(ISERROR(SEARCH("Commission-Based Wholesaling",GL2)),"","380") | PD2: =if(ISERROR(SEARCH("Grocery, Liquor and Tobacco Product Wholesaling",GL2)),"","360") | PE2: =if(ISERROR(SEARCH("Specialised Industrial Machinery and Equipment Wholesaling",GR2)),"","341") | PF2: =if(ISERROR(SEARCH("Other Machinery and Equipment Wholesaling",GR2)),"","349") | PG2: =if(ISERROR(SEARCH("Motor Vehicle and Motor Vehicle Parts Wholesaling",GL2)),"","350") | PH2: =if(ISERROR(SEARCH("Textile, Clothing and Footwear Wholesaling",GV2)),"","371") | PI2: =if(ISERROR(SEARCH("Furniture, Floor Covering and Other Goods Wholesaling",GV2)),"","373") | PJ2: =if(ISERROR(SEARCH("Pharmaceutical and Toiletry Goods Wholesaling",GV2)),"","372") | PK2: =if(ISERROR(SEARCH("Civic, Professional and Other Interest Group Services",GZ2)),"","955") | PL2: =if(ISERROR(SEARCH("Funeral, Crematorium and Cemetery Services",GZ2)),"","952") | PM2: =if(ISERROR(SEARCH("Personal Care Services",GZ2)),"","951") | PN2: =if(ISERROR(SEARCH("Religious Services",GZ2)),"","954") | PO2: =if(ISERROR(SEARCH("Other Personal Services",GZ2)),"","953") | PP2: =if(ISERROR(SEARCH("Private Households Employing Staff and Undifferentiated Goods- and Service-Producing Activities of Households for Own Use",GY2)),"","960") | PQ2: =if(ISERROR(SEARCH("Automotive Repair and Maintenance",HE2)),"","941") | PR2: =if(ISERROR(SEARCH("Machinery and Equipment Repair and Maintenance",HE2)),"","942") | PS2: =if(ISERROR(SEARCH("Other Repair and Maintenance",HE2)),"","949")
HI3: =if(ISERROR(SEARCH("Accommodation",F3)),"","440") | HJ3: =if(ISERROR(SEARCH("Cafes, Restaurants and Takeaway Food Services",G3)),"","450") | HK3: =if(ISERROR(SEARCH("Clubs (Hospitality)",G3)),"","453") | HL3: =if(ISERROR(SEARCH("Pubs, Taverns and Bars",G3)),"","452") | HM3: =if(ISERROR(SEARCH("Employment Services",J3)),"","721") | HN3: =if(ISERROR(SEARCH("Travel Agency and Tour Arrangement Services",J3)),"","722") | HO3: =if(ISERROR(SEARCH("Other Administrative Services",J3)),"","729") | HP3: =if(ISERROR(SEARCH("Building Cleaning, Pest Control and Gardening Servicess",M3)),"","731") | HQ3: =if(ISERROR(SEARCH("Packaging Services",M3)),"","732") | HR3: =if(ISERROR(SEARCH("Dairy Cattle Farming",P3)),"","016") | HS3: =if(ISERROR(SEARCH("Deer Farming",P3)),"","018") | HT3: =if(ISERROR(SEARCH("Fruit and Tree Nut Growing",P3)),"","013") | HU3: =if(ISERROR(SEARCH("Mushroom and Vegetable Growing",P3)),"","012") | HV3: =if(ISERROR(SEARCH("Nursery and Floriculture Production",P3)),"","011") | HW3: =if(ISERROR(SEARCH("Poultry Farming",P3)),"","017") | HX3: =if(ISERROR(SEARCH("Sheep, Beef Cattle and Grain Farming",P3)),"","014") | HY3: =if(ISERROR(SEARCH("Other Crop Growing",P3)),"","015") | HZ3: =if(ISERROR(SEARCH("Other Livestock Farming",P3)),"","019") | IA3: =if(ISERROR(SEARCH("Agriculture and Fishing Support Services",X3)),"","052") | IB3: =if(ISERROR(SEARCH("Forestry Support Services",X3)),"","051") | IC3: =if(ISERROR(SEARCH("Aquaculture",Z3)),"","020") | ID3: =if(ISERROR(SEARCH("Fishing",AA3)),"","041") | IE3: =if(ISERROR(SEARCH("Hunting and Trapping",AA3)),"","042") | IF3: =if(ISERROR(SEARCH("Forestry and Logging",AB3)),"","030") | IG3: =if(ISERROR(SEARCH("Creative and Performing Arts Activities",AD3)),"","900") | IH3: =if(ISERROR(SEARCH("Gambling Activities",AD3)),"","920") | II3: =if(ISERROR(SEARCH("Museum Operation",AG3)),"","891") | IJ3: =if(ISERROR(SEARCH("Parks and Gardens Operations",AG3)),"","892") | IK3: =if(ISERROR(SEARCH("Amusement and Other Recreation Activities",AI3)),"","913") | IL3: =if(ISERROR(SEARCH("Horse and Dog Racing Activities",AI3)),"","912") | IM3: =if(ISERROR(SEARCH("Sports and Physical Recreation Activities",AI3)),"","911") | IN3: =if(ISERROR(SEARCH("Residential Building Construction",AN3)),"","301") | IO3: =if(ISERROR(SEARCH("Non-Residential Building Construction",AN3)),"","302") | IP3: =if(ISERROR(SEARCH("Building Completion Services",AP3)),"","324") | IQ3: =if(ISERROR(SEARCH("Building Installation Servicess",AP3)),"","323") | IR3: =if(ISERROR(SEARCH("Building Structure Services",AP3)),"","322") | IS3: =if(ISERROR(SEARCH("Land Development and Site Preparation Services",AP3)),"","321") | IT3: =if(ISERROR(SEARCH("Other Construction Services",AP3)),"","329") | IU3: =if(ISERROR(SEARCH("Road and Bridge Construction",AV3)),"","310") | IV3: =if(ISERROR(SEARCH("Other Heavy and Civil Engineering Construction",AV3)),"","310") | IW3: =if(ISERROR(SEARCH("Adult, Community and Other Education",AX3)),"","821") | IX3: =if(ISERROR(SEARCH("Educational Support Services",AX3)),"","822") | IY3: =if(ISERROR(SEARCH("Preschool Education",AZ3)),"","801") | IZ3: =if(ISERROR(SEARCH("School Education",AZ3)),"","802") | JA3: =if(ISERROR(SEARCH("Higher Education",BB3)),"","810") | JB3: =if(ISERROR(SEARCH("Higher Education",BC3)),"","810") | JC3: =if(ISERROR(SEARCH("Electricity Distribution",BC3)),"","263") | JD3: =if(ISERROR(SEARCH("Electricity Generation",BC3)),"","261") | JE3: =if(ISERROR(SEARCH("Electricity Transmission",BC3)),"","262") | JF3: =if(ISERROR(SEARCH("On Selling Electricity and Electricity Market Operation",BC3)),"","264") | JG3: =if(ISERROR(SEARCH("Gas Supply",BC3)),"","270") | JH3: =if(ISERROR(SEARCH("Waste Collection Services",BF3)),"","291") | JI3: =if(ISERROR(SEARCH("Waste Treatment, Disposal and Remediation Services",BF3)),"","292") | JJ3: =if(ISERROR(SEARCH("Sewerage and Drainage Services",BI3)),"","281") | JK3: =if(ISERROR(SEARCH("Water Supply",BI3)),"","281") | JL3: =if(ISERROR(SEARCH("Auxiliary Finance and Investment Services",BK3)),"","641") | JM3: =if(ISERROR(SEARCH("Auxiliary Insurance Services",BK3)),"","642") | JN3: =if(ISERROR(SEARCH("Central Banking",BM3)),"","621") | JO3: =if(ISERROR(SEARCH("Depository Financial Intermediation",BM3)),"","622") | JP3: =if(ISERROR(SEARCH("Financial Asset Investing",BM3)),"","624") | JQ3: =if(ISERROR(SEARCH("Non-Depository Financing",BM3)),"","623") | JR3: =if(ISERROR(SEARCH("Health and General Insurance",BO3)),"","632") | JS3: =if(ISERROR(SEARCH("Life Insurance",BO3)),"","631") | JT3: =if(ISERROR(SEARCH("Superannuation Funds",BO3)),"","633") | JU3: =if(ISERROR(SEARCH("Hospitals",BQ3)),"","840") | JV3: =if(ISERROR(SEARCH("Medical Services",BS3)),"","851") | JW3: =if(ISERROR(SEARCH("Pathology and Diagnostic Imaging Services",BS3)),"","852") | JX3: =if(ISERROR(SEARCH("Allied Health Services",BS3)),"","853") | JY3: =if(ISERROR(SEARCH("Other Health Care Services",BS3)),"","859") | JZ3: =if(ISERROR(SEARCH("Aged Care Residential Services",BW3)),"","860") | KA3: =if(ISERROR(SEARCH("Other Residential Care Services",BW3)),"","860") | KB3: =if(ISERROR(SEARCH("Child Care Services",BX3)),"","871") | KC3: =if(ISERROR(SEARCH("Other Social Assistance Services",BX3)),"","879") | KD3: =if(ISERROR(SEARCH("Radio Broadcasting",BZ3)),"","561") | KE3: =if(ISERROR(SEARCH("Television Broadcasting",BZ3)),"","562") | KF3: =if(ISERROR(SEARCH("Internet Publishing and Broadcasting",BY3)),"","570") | KG3: =if(ISERROR(SEARCH("Data Processing, Web Hosting and Electronic Information Storage Services",CB3)),"","592") | KH3: =if(ISERROR(SEARCH("Internet Service Providers and Web Search Portals",CB3)),"","591") | KI3: =if(ISERROR(SEARCH("Libraries and Archives",CD3)),"","601") | KJ3: =if(ISERROR(SEARCH("Other Information Services",CD3)),"","602") | KK3: =if(ISERROR(SEARCH("Motion Picture and Video Activities",CE3)),"","551") | KL3: =if(ISERROR(SEARCH("Sound Recording and Music Publishing",CE3)),"","552") | KM3: =if(ISERROR(SEARCH("Newspaper, Periodical, Book and Directory Publishing",CH3)),"","541") | KN3: =if(ISERROR(SEARCH("Software Publishing",CH3)),"","542") | KO3: =if(ISERROR(SEARCH("Telecommunications Services",BY3)),"","580") | KP3: =if(ISERROR(SEARCH("Basic Chemical Manufacturing",CK3)),"","181") | KQ3: =if(ISERROR(SEARCH("Basic Polymer Manufacturing",CK3)),"","182") | KR3: =if(ISERROR(SEARCH("Cleaning Compound and Toiletry Preparation Manufacturing",CK3)),"","185") | KS3: =if(ISERROR(SEARCH("Fertiliser and Pesticide Manufacturing",CK3)),"","183") | KT3: =if(ISERROR(SEARCH("Pharmaceutical and Medicinal Product Manufacturing",CK3)),"","184") | KU3: =if(ISERROR(SEARCH("Other Basic Chemical Product Manufacturing",CK3)),"","189") | KV3: =if(ISERROR(SEARCH("Beverage Manufacturing",CR3)),"","121") | KW3: =if(ISERROR(SEARCH("Cigarette and Tobacco Product Manufacturing",CR3)),"","122") | KX3: =if(ISERROR(SEARCH("Iron and Steel Forging",CT3)),"","221") | KY3: =if(ISERROR(SEARCH("Metal Container Manufacturing",CT3)),"","223") | KZ3: =if(ISERROR(SEARCH("Sheet Metal Product Manufacturing (except Metal Structural and Container Products)",CT3)),"","224") | LA3: =if(ISERROR(SEARCH("Structural Metal Product Manufacturing",CT3)),"","222") | LB3: =if(ISERROR(SEARCH("Other Fabricated Metal Product Manufacturing",CT3)),"","229") | LC3: =if(ISERROR(SEARCH("Bakery Product Manufacturing",CX3)),"","117") | LD3: =if(ISERROR(SEARCH("Dairy Product Manufacturing",CX3)),"","113") | LE3: =if(ISERROR(SEARCH("Fruit and Vegetable Processing",CX3)),"","114") | LF3: =if(ISERROR(SEARCH("Grain Mill and Cereal Product Manufacturing",CX3)),"","116") | LG3: =if(ISERROR(SEARCH("Meat and Meat Product Manufacturing",CX3)),"","111") | LH3: =if(ISERROR(SEARCH("Oil and Fat Manufacturing",CX3)),"","115") | LI3: =if(ISERROR(SEARCH("Seafood Processing",CX3)),"","112") | LJ3: =if(ISERROR(SEARCH("Sugar and Confectionery Manufacturing",CX3)),"","118") | LK3: =if(ISERROR(SEARCH("Other Food Product Manufacturing",CX3)),"","119") | LL3: =if(ISERROR(SEARCH("Furniture Manufacturing",DE3)),"","251") | LM3: =if(ISERROR(SEARCH("Other Manufacturing",DE3)),"","259") | LN3: =if(ISERROR(SEARCH("Computer and Electronic Equipment Manufacturing",DH3)),"","242") | LO3: =if(ISERROR(SEARCH("Domestic Appliance Manufacturing",DH3)),"","244") | LP3: =if(ISERROR(SEARCH("Electrical Equipment Manufacturing",DH3)),"","243") | LQ3: =if(ISERROR(SEARCH("Professional and Scientific Equipment Manufacturing",DH3)),"","241") | LR3: =if(ISERROR(SEARCH("Pump, Compressor, Heating and Ventilation Equipment Manufacturing",DH3)),"","245") | LS3: =if(ISERROR(SEARCH("Specialised Machinery and Equipment Manufacturing",DH3)),"","246") | LT3: =if(ISERROR(SEARCH("Other Machinery and Equipment Manufacturing",DH3)),"","249") | LU3: =if(ISERROR(SEARCH("Cement, Lime, Plaster and Concrete Product Manufacturing",DP3)),"","203") | LV3: =if(ISERROR(SEARCH("Ceramic Product Manufacturing",DP3)),"","202") | LW3: =if(ISERROR(SEARCH("Glass and Glass Product Manufacturing",DP3)),"","201") | LX3: =if(ISERROR(SEARCH("Other Non-Metallic Mineral Product Manufacturing",DP3)),"","209") | LY3: =if(ISERROR(SEARCH("Petroleum Refining and Petroleum Fuel Manufacturing",DS3)),"","170") | LZ3: =if(ISERROR(SEARCH("Other Petroleum and Coal Product Manufacturing",DS3)),"","170") | MA3: =if(ISERROR(SEARCH("Natural Rubber Product Manufacturing",DT3)),"","192") | MB3: =if(ISERROR(SEARCH("Polymer Product Manufacturing",DT3)),"","191") | MC3: =if(ISERROR(SEARCH("Basic Ferrous Metal Manufacturing",DV3)),"","211") | MD3: =if(ISERROR(SEARCH("Basic Ferrous Metal Product Manufacturing",DV3)),"","212") | ME3: =if(ISERROR(SEARCH("Basic Non-Ferrous Metal Manufacturing",DV3)),"","213") | MF3: =if(ISERROR(SEARCH("Basic Non-Ferrous Metal Product Manufacturing",DV3)),"","214") | MG3: =if(ISERROR(SEARCH("Printing and Printing Support Services",EA3)),"","161") | MH3: =if(ISERROR(SEARCH("Reproduction of Recorded Media",EA3)),"","162") | MI3: =if(ISERROR(SEARCH("Converted Paper Product Manufacturing",EC3)),"","152") | MJ3: =if(ISERROR(SEARCH("Pulp, Paper and Paperboard Manufacturing",EC3)),"","151") | MK3: =if(ISERROR(SEARCH("Clothing and Footwear Manufacturing",EE3)),"","135") | ML3: =if(ISERROR(SEARCH("Knitted Product Manufacturing",EE3)),"","134") | MM3: =if(ISERROR(SEARCH("Leather Tanning, Fur Dressing and Leather Product Manufacturing",EE3)),"","132") | MN3: =if(ISERROR(SEARCH("Textile Manufacturing",EE3)),"","131") | MO3: =if(ISERROR(SEARCH("Textile Product Manufacturing",EE3)),"","133") | MP3: =if(ISERROR(SEARCH("Motor Vehicle and Motor Vehicle Part Manufacturing",EI3)),"","231") | MQ3: =if(ISERROR(SEARCH("Other Transport Equipment Manufacturing",EI3)),"","239") | MR3: =if(ISERROR(SEARCH("Log Sawmilling and Timber Dressing",EL3)),"","141") | MS3: =if(ISERROR(SEARCH("Other Wood Product Manufacturing",EL3)),"","149") | MT3: =if(ISERROR(SEARCH("Coal Mining",EO3)),"","060") | MU3: =if(ISERROR(SEARCH("Exploration",EP3)),"","101") | MV3: =if(ISERROR(SEARCH("Other Mining Support Services",EP3)),"","109") | MW3: =if(ISERROR(SEARCH("Metal Ore Mining",EO3)),"","080") | MX3: =if(ISERROR(SEARCH("Construction Material Mining",ES3)),"","091") | MY3: =if(ISERROR(SEARCH("Oil and Gas Extraction",EO3)),"","070") | MZ3: =if(ISERROR(SEARCH("Other Non-Metallic Mineral Mining and Quarrying",ES3)),"","099") | NA3: =if(ISERROR(SEARCH("Computer System Design and Related Services",EU3)),"","700") | NB3: =if(ISERROR(SEARCH("Advertising Services",EV3)),"","694") | NC3: =if(ISERROR(SEARCH("Architectural, Engineering and Technical Services",EV3)),"","692") | ND3: =if(ISERROR(SEARCH("Legal and Accounting Services",EV3)),"","693") | NE3: =if(ISERROR(SEARCH("Management and Related Consulting Services",EV3)),"","696") | NF3: =if(ISERROR(SEARCH("Market Research and Statistical Services",EV3)),"","695") | NG3: =if(ISERROR(SEARCH("Scientific Research Services",EV3)),"","691") | NH3: =if(ISERROR(SEARCH("Veterinary Services",EV3)),"","697") | NI3: =if(ISERROR(SEARCH("Other Professional, Scientific and Technical Services",EV3)),"","699") | NJ3: =if(ISERROR(SEARCH("Central Government Administration",FB3)),"","751") | NK3: =if(ISERROR(SEARCH("State Government Administration",FB3)),"","752") | NL3: =if(ISERROR(SEARCH("Local Government Administration",FB3)),"","753") | NM3: =if(ISERROR(SEARCH("Justice",FB3)),"","754") | NN3: =if(ISERROR(SEARCH("Government Representation",FB3)),"","755") | NO3: =if(ISERROR(SEARCH("Defence",FA3)),"","760") | NP3: =if(ISERROR(SEARCH("Public Order and Safety Services",FD3)),"","771") | NQ3: =if(ISERROR(SEARCH("Regulatory Services",FD3)),"","772") | NR3: =if(ISERROR(SEARCH("Property Operators",FG3)),"","671") | NS3: =if(ISERROR(SEARCH("Real Estate Services",FG3)),"","672") | NT3: =if(ISERROR(SEARCH("Farm Animal and Bloodstock Leasing",FI3)),"","662") | NU3: =if(ISERROR(SEARCH("Motor Vehicle and Transport Equipment Rental and Hiring",FI3)),"","661") | NV3: =if(ISERROR(SEARCH("Non-Financial Intangible Assets (Except Copyrights) Leasing",FI3)),"","664") | NW3: =if(ISERROR(SEARCH("Other Goods and Equipment Rental and Hiring",FI3)),"","663") | NX3: =if(ISERROR(SEARCH("Supermarket and Grocery Stores",FM3)),"","411") | NY3: =if(ISERROR(SEARCH("Specialised Food Retailing",FM3)),"","412") | NZ3: =if(ISERROR(SEARCH("Fuel Retailing",FL3)),"","400") | OA3: =if(ISERROR(SEARCH("Motor Vehicle Parts and Tyre Retailing",FO3)),"","392") | OB3: =if(ISERROR(SEARCH("Motor Vehicle Retailing",FO3)),"","391") | OC3: =if(ISERROR(SEARCH("Non-Store Retailing",FR3)),"","431") | OD3: =if(ISERROR(SEARCH("Retail Commission-Based Buying and/or Selling",FR3)),"","432") | OE3: =if(ISERROR(SEARCH("Clothing, Footwear and Personal Accessory Retailing",FS3)),"","425") | OF3: =if(ISERROR(SEARCH("Department Stores",FS3)),"","426") | OG3: =if(ISERROR(SEARCH("Electrical and Electronic Goods Retailing",FS3)),"","422") | OH3: =if(ISERROR(SEARCH("Furniture, Floor Coverings, Houseware and Textile Goods Retailing",FS3)),"","421") | OI3: =if(ISERROR(SEARCH("Hardware, Building and Garden Supplies Retailing",FS3)),"","423") | OJ3: =if(ISERROR(SEARCH("Pharmaceutical and Other Store-Based Retailing",FS3)),"","427") | OK3: =if(ISERROR(SEARCH("Recreational Goods Retailing",FS3)),"","424") | OL3: =if(ISERROR(SEARCH("Air and Space Transport",FZ3)),"","490") | OM3: =if(ISERROR(SEARCH("Postal and Courier Pick-up and Delivery Services",FZ3)),"","510") | ON3: =if(ISERROR(SEARCH("Rail Freight Transport",GB3)),"","471") | OO3: =if(ISERROR(SEARCH("Rail Passenger Transport",GB3)),"","472") | OP3: =if(ISERROR(SEARCH("Road Freight Transport",GC3)),"","461") | OQ3: =if(ISERROR(SEARCH("Road Passenger Transport",GC3)),"","462") | OR3: =if(ISERROR(SEARCH("Airport Operations and Other Air Transport Support Services",GE3)),"","522") | OS3: =if(ISERROR(SEARCH("Water Transport Support Services",GE3)),"","521") | OT3: =if(ISERROR(SEARCH("Other Transport Support Services",GE3)),"","529") | OU3: =if(ISERROR(SEARCH("Warehousing and Storage Services",FZ3)),"","530") | OV3: =if(ISERROR(SEARCH("Water Freight Transport",GI3)),"","481") | OW3: =if(ISERROR(SEARCH("Water Freight Transport",GI3)),"","482") | OX3: =if(ISERROR(SEARCH("Pipeline and Other Transport",GJ3)),"","502") | OY3: =if(ISERROR(SEARCH("Scenic and Sightseeing Transport",GJ3)),"","501") | OZ3: =if(ISERROR(SEARCH("Agricultural Product Wholesaling",GM3)),"","331") | PA3: =if(ISERROR(SEARCH("Mineral, Metal and Chemical Wholesaling",GM3)),"","332") | PB3: =if(ISERROR(SEARCH("Timber and Hardware Goods Wholesaling",GM3)),"","333") | PC3: =if(ISERROR(SEARCH("Commission-Based Wholesaling",GL3)),"","380") | PD3: =if(ISERROR(SEARCH("Grocery, Liquor and Tobacco Product Wholesaling",GL3)),"","360") | PE3: =if(ISERROR(SEARCH("Specialised Industrial Machinery and Equipment Wholesaling",GR3)),"","341") | PF3: =if(ISERROR(SEARCH("Other Machinery and Equipment Wholesaling",GR3)),"","349") | PG3: =if(ISERROR(SEARCH("Motor Vehicle and Motor Vehicle Parts Wholesaling",GL3)),"","350") | PH3: =if(ISERROR(SEARCH("Textile, Clothing and Footwear Wholesaling",GV3)),"","371") | PI3: =if(ISERROR(SEARCH("Furniture, Floor Covering and Other Goods Wholesaling",GV3)),"","373") | PJ3: =if(ISERROR(SEARCH("Pharmaceutical and Toiletry Goods Wholesaling",GV3)),"","372") | PK3: =if(ISERROR(SEARCH("Civic, Professional and Other Interest Group Services",GZ3)),"","955") | PL3: =if(ISERROR(SEARCH("Funeral, Crematorium and Cemetery Services",GZ3)),"","952") | PM3: =if(ISERROR(SEARCH("Personal Care Services",GZ3)),"","951") | PN3: =if(ISERROR(SEARCH("Religious Services",GZ3)),"","954") | PO3: =if(ISERROR(SEARCH("Other Personal Services",GZ3)),"","953") | PP3: =if(ISERROR(SEARCH("Private Households Employing Staff and Undifferentiated Goods- and Service-Producing Activities of Households for Own Use",GY3)),"","960") | PQ3: =if(ISERROR(SEARCH("Automotive Repair and Maintenance",HE3)),"","941") | PR3: =if(ISERROR(SEARCH("Machinery and Equipment Repair and Maintenance",HE3)),"","942") | PS3: =if(ISERROR(SEARCH("Other Repair and Maintenance",HE3)),"","949")
HI4: =if(ISERROR(SEARCH("Accommodation",F4)),"","440") | HJ4: =if(ISERROR(SEARCH("Cafes, Restaurants and Takeaway Food Services",G4)),"","450") | HK4: =if(ISERROR(SEARCH("Clubs (Hospitality)",G4)),"","453") | HL4: =if(ISERROR(SEARCH("Pubs, Taverns and Bars",G4)),"","452") | HM4: =if(ISERROR(SEARCH("Employment Services",J4)),"","721") | HN4: =if(ISERROR(SEARCH("Travel Agency and Tour Arrangement Services",J4)),"","722") | HO4: =if(ISERROR(SEARCH("Other Administrative Services",J4)),"","729") | HP4: =if(ISERROR(SEARCH("Building Cleaning, Pest Control and Gardening Servicess",M4)),"","731") | HQ4: =if(ISERROR(SEARCH("Packaging Services",M4)),"","732") | HR4: =if(ISERROR(SEARCH("Dairy Cattle Farming",P4)),"","016") | HS4: =if(ISERROR(SEARCH("Deer Farming",P4)),"","018") | HT4: =if(ISERROR(SEARCH("Fruit and Tree Nut Growing",P4)),"","013") | HU4: =if(ISERROR(SEARCH("Mushroom and Vegetable Growing",P4)),"","012") | HV4: =if(ISERROR(SEARCH("Nursery and Floriculture Production",P4)),"","011") | HW4: =if(ISERROR(SEARCH("Poultry Farming",P4)),"","017") | HX4: =if(ISERROR(SEARCH("Sheep, Beef Cattle and Grain Farming",P4)),"","014") | HY4: =if(ISERROR(SEARCH("Other Crop Growing",P4)),"","015") | HZ4: =if(ISERROR(SEARCH("Other Livestock Farming",P4)),"","019") | IA4: =if(ISERROR(SEARCH("Agriculture and Fishing Support Services",X4)),"","052") | IB4: =if(ISERROR(SEARCH("Forestry Support Services",X4)),"","051") | IC4: =if(ISERROR(SEARCH("Aquaculture",Z4)),"","020") | ID4: =if(ISERROR(SEARCH("Fishing",AA4)),"","041") | IE4: =if(ISERROR(SEARCH("Hunting and Trapping",AA4)),"","042") | IF4: =if(ISERROR(SEARCH("Forestry and Logging",AB4)),"","030") | IG4: =if(ISERROR(SEARCH("Creative and Performing Arts Activities",AD4)),"","900") | IH4: =if(ISERROR(SEARCH("Gambling Activities",AD4)),"","920") | II4: =if(ISERROR(SEARCH("Museum Operation",AG4)),"","891") | IJ4: =if(ISERROR(SEARCH("Parks and Gardens Operations",AG4)),"","892") | IK4: =if(ISERROR(SEARCH("Amusement and Other Recreation Activities",AI4)),"","913") | IL4: =if(ISERROR(SEARCH("Horse and Dog Racing Activities",AI4)),"","912") | IM4: =if(ISERROR(SEARCH("Sports and Physical Recreation Activities",AI4)),"","911") | IN4: =if(ISERROR(SEARCH("Residential Building Construction",AN4)),"","301") | IO4: =if(ISERROR(SEARCH("Non-Residential Building Construction",AN4)),"","302") | IP4: =if(ISERROR(SEARCH("Building Completion Services",AP4)),"","324") | IQ4: =if(ISERROR(SEARCH("Building Installation Servicess",AP4)),"","323") | IR4: =if(ISERROR(SEARCH("Building Structure Services",AP4)),"","322") | IS4: =if(ISERROR(SEARCH("Land Development and Site Preparation Services",AP4)),"","321") | IT4: =if(ISERROR(SEARCH("Other Construction Services",AP4)),"","329") | IU4: =if(ISERROR(SEARCH("Road and Bridge Construction",AV4)),"","310") | IV4: =if(ISERROR(SEARCH("Other Heavy and Civil Engineering Construction",AV4)),"","310") | IW4: =if(ISERROR(SEARCH("Adult, Community and Other Education",AX4)),"","821") | IX4: =if(ISERROR(SEARCH("Educational Support Services",AX4)),"","822") | IY4: =if(ISERROR(SEARCH("Preschool Education",AZ4)),"","801") | IZ4: =if(ISERROR(SEARCH("School Education",AZ4)),"","802") | JA4: =if(ISERROR(SEARCH("Higher Education",BB4)),"","810") | JB4: =if(ISERROR(SEARCH("Higher Education",BC4)),"","810") | JC4: =if(ISERROR(SEARCH("Electricity Distribution",BC4)),"","263") | JD4: =if(ISERROR(SEARCH("Electricity Generation",BC4)),"","261") | JE4: =if(ISERROR(SEARCH("Electricity Transmission",BC4)),"","262") | JF4: =if(ISERROR(SEARCH("On Selling Electricity and Electricity Market Operation",BC4)),"","264") | JG4: =if(ISERROR(SEARCH("Gas Supply",BC4)),"","270") | JH4: =if(ISERROR(SEARCH("Waste Collection Services",BF4)),"","291") | JI4: =if(ISERROR(SEARCH("Waste Treatment, Disposal and Remediation Services",BF4)),"","292") | JJ4: =if(ISERROR(SEARCH("Sewerage and Drainage Services",BI4)),"","281") | JK4: =if(ISERROR(SEARCH("Water Supply",BI4)),"","281") | JL4: =if(ISERROR(SEARCH("Auxiliary Finance and Investment Services",BK4)),"","641") | JM4: =if(ISERROR(SEARCH("Auxiliary Insurance Services",BK4)),"","642") | JN4: =if(ISERROR(SEARCH("Central Banking",BM4)),"","621") | JO4: =if(ISERROR(SEARCH("Depository Financial Intermediation",BM4)),"","622") | JP4: =if(ISERROR(SEARCH("Financial Asset Investing",BM4)),"","624") | JQ4: =if(ISERROR(SEARCH("Non-Depository Financing",BM4)),"","623") | JR4: =if(ISERROR(SEARCH("Health and General Insurance",BO4)),"","632") | JS4: =if(ISERROR(SEARCH("Life Insurance",BO4)),"","631") | JT4: =if(ISERROR(SEARCH("Superannuation Funds",BO4)),"","633") | JU4: =if(ISERROR(SEARCH("Hospitals",BQ4)),"","840") | JV4: =if(ISERROR(SEARCH("Medical Services",BS4)),"","851") | JW4: =if(ISERROR(SEARCH("Pathology and Diagnostic Imaging Services",BS4)),"","852") | JX4: =if(ISERROR(SEARCH("Allied Health Services",BS4)),"","853") | JY4: =if(ISERROR(SEARCH("Other Health Care Services",BS4)),"","859") | JZ4: =if(ISERROR(SEARCH("Aged Care Residential Services",BW4)),"","860") | KA4: =if(ISERROR(SEARCH("Other Residential Care Services",BW4)),"","860") | KB4: =if(ISERROR(SEARCH("Child Care Services",BX4)),"","871") | KC4: =if(ISERROR(SEARCH("Other Social Assistance Services",BX4)),"","879") | KD4: =if(ISERROR(SEARCH("Radio Broadcasting",BZ4)),"","561") | KE4: =if(ISERROR(SEARCH("Television Broadcasting",BZ4)),"","562") | KF4: =if(ISERROR(SEARCH("Internet Publishing and Broadcasting",BY4)),"","570") | KG4: =if(ISERROR(SEARCH("Data Processing, Web Hosting and Electronic Information Storage Services",CB4)),"","592") | KH4: =if(ISERROR(SEARCH("Internet Service Providers and Web Search Portals",CB4)),"","591") | KI4: =if(ISERROR(SEARCH("Libraries and Archives",CD4)),"","601") | KJ4: =if(ISERROR(SEARCH("Other Information Services",CD4)),"","602") | KK4: =if(ISERROR(SEARCH("Motion Picture and Video Activities",CE4)),"","551") | KL4: =if(ISERROR(SEARCH("Sound Recording and Music Publishing",CE4)),"","552") | KM4: =if(ISERROR(SEARCH("Newspaper, Periodical, Book and Directory Publishing",CH4)),"","541") | KN4: =if(ISERROR(SEARCH("Software Publishing",CH4)),"","542") | KO4: =if(ISERROR(SEARCH("Telecommunications Services",BY4)),"","580") | KP4: =if(ISERROR(SEARCH("Basic Chemical Manufacturing",CK4)),"","181") | KQ4: =if(ISERROR(SEARCH("Basic Polymer Manufacturing",CK4)),"","182") | KR4: =if(ISERROR(SEARCH("Cleaning Compound and Toiletry Preparation Manufacturing",CK4)),"","185") | KS4: =if(ISERROR(SEARCH("Fertiliser and Pesticide Manufacturing",CK4)),"","183") | KT4: =if(ISERROR(SEARCH("Pharmaceutical and Medicinal Product Manufacturing",CK4)),"","184") | KU4: =if(ISERROR(SEARCH("Other Basic Chemical Product Manufacturing",CK4)),"","189") | KV4: =if(ISERROR(SEARCH("Beverage Manufacturing",CR4)),"","121") | KW4: =if(ISERROR(SEARCH("Cigarette and Tobacco Product Manufacturing",CR4)),"","122") | KX4: =if(ISERROR(SEARCH("Iron and Steel Forging",CT4)),"","221") | KY4: =if(ISERROR(SEARCH("Metal Container Manufacturing",CT4)),"","223") | KZ4: =if(ISERROR(SEARCH("Sheet Metal Product Manufacturing (except Metal Structural and Container Products)",CT4)),"","224") | LA4: =if(ISERROR(SEARCH("Structural Metal Product Manufacturing",CT4)),"","222") | LB4: =if(ISERROR(SEARCH("Other Fabricated Metal Product Manufacturing",CT4)),"","229") | LC4: =if(ISERROR(SEARCH("Bakery Product Manufacturing",CX4)),"","117") | LD4: =if(ISERROR(SEARCH("Dairy Product Manufacturing",CX4)),"","113") | LE4: =if(ISERROR(SEARCH("Fruit and Vegetable Processing",CX4)),"","114") | LF4: =if(ISERROR(SEARCH("Grain Mill and Cereal Product Manufacturing",CX4)),"","116") | LG4: =if(ISERROR(SEARCH("Meat and Meat Product Manufacturing",CX4)),"","111") | LH4: =if(ISERROR(SEARCH("Oil and Fat Manufacturing",CX4)),"","115") | LI4: =if(ISERROR(SEARCH("Seafood Processing",CX4)),"","112") | LJ4: =if(ISERROR(SEARCH("Sugar and Confectionery Manufacturing",CX4)),"","118") | LK4: =if(ISERROR(SEARCH("Other Food Product Manufacturing",CX4)),"","119") | LL4: =if(ISERROR(SEARCH("Furniture Manufacturing",DE4)),"","251") | LM4: =if(ISERROR(SEARCH("Other Manufacturing",DE4)),"","259") | LN4: =if(ISERROR(SEARCH("Computer and Electronic Equipment Manufacturing",DH4)),"","242") | LO4: =if(ISERROR(SEARCH("Domestic Appliance Manufacturing",DH4)),"","244") | LP4: =if(ISERROR(SEARCH("Electrical Equipment Manufacturing",DH4)),"","243") | LQ4: =if(ISERROR(SEARCH("Professional and Scientific Equipment Manufacturing",DH4)),"","241") | LR4: =if(ISERROR(SEARCH("Pump, Compressor, Heating and Ventilation Equipment Manufacturing",DH4)),"","245") | LS4: =if(ISERROR(SEARCH("Specialised Machinery and Equipment Manufacturing",DH4)),"","246") | LT4: =if(ISERROR(SEARCH("Other Machinery and Equipment Manufacturing",DH4)),"","249") | LU4: =if(ISERROR(SEARCH("Cement, Lime, Plaster and Concrete Product Manufacturing",DP4)),"","203") | LV4: =if(ISERROR(SEARCH("Ceramic Product Manufacturing",DP4)),"","202") | LW4: =if(ISERROR(SEARCH("Glass and Glass Product Manufacturing",DP4)),"","201") | LX4: =if(ISERROR(SEARCH("Other Non-Metallic Mineral Product Manufacturing",DP4)),"","209") | LY4: =if(ISERROR(SEARCH("Petroleum Refining and Petroleum Fuel Manufacturing",DS4)),"","170") | LZ4: =if(ISERROR(SEARCH("Other Petroleum and Coal Product Manufacturing",DS4)),"","170") | MA4: =if(ISERROR(SEARCH("Natural Rubber Product Manufacturing",DT4)),"","192") | MB4: =if(ISERROR(SEARCH("Polymer Product Manufacturing",DT4)),"","191") | MC4: =if(ISERROR(SEARCH("Basic Ferrous Metal Manufacturing",DV4)),"","211") | MD4: =if(ISERROR(SEARCH("Basic Ferrous Metal Product Manufacturing",DV4)),"","212") | ME4: =if(ISERROR(SEARCH("Basic Non-Ferrous Metal Manufacturing",DV4)),"","213") | MF4: =if(ISERROR(SEARCH("Basic Non-Ferrous Metal Product Manufacturing",DV4)),"","214") | MG4: =if(ISERROR(SEARCH("Printing and Printing Support Services",EA4)),"","161") | MH4: =if(ISERROR(SEARCH("Reproduction of Recorded Media",EA4)),"","162") | MI4: =if(ISERROR(SEARCH("Converted Paper Product Manufacturing",EC4)),"","152") | MJ4: =if(ISERROR(SEARCH("Pulp, Paper and Paperboard Manufacturing",EC4)),"","151") | MK4: =if(ISERROR(SEARCH("Clothing and Footwear Manufacturing",EE4)),"","135") | ML4: =if(ISERROR(SEARCH("Knitted Product Manufacturing",EE4)),"","134") | MM4: =if(ISERROR(SEARCH("Leather Tanning, Fur Dressing and Leather Product Manufacturing",EE4)),"","132") | MN4: =if(ISERROR(SEARCH("Textile Manufacturing",EE4)),"","131") | MO4: =if(ISERROR(SEARCH("Textile Product Manufacturing",EE4)),"","133") | MP4: =if(ISERROR(SEARCH("Motor Vehicle and Motor Vehicle Part Manufacturing",EI4)),"","231") | MQ4: =if(ISERROR(SEARCH("Other Transport Equipment Manufacturing",EI4)),"","239") | MR4: =if(ISERROR(SEARCH("Log Sawmilling and Timber Dressing",EL4)),"","141") | MS4: =if(ISERROR(SEARCH("Other Wood Product Manufacturing",EL4)),"","149") | MT4: =if(ISERROR(SEARCH("Coal Mining",EO4)),"","060") | MU4: =if(ISERROR(SEARCH("Exploration",EP4)),"","101") | MV4: =if(ISERROR(SEARCH("Other Mining Support Services",EP4)),"","109") | MW4: =if(ISERROR(SEARCH("Metal Ore Mining",EO4)),"","080") | MX4: =if(ISERROR(SEARCH("Construction Material Mining",ES4)),"","091") | MY4: =if(ISERROR(SEARCH("Oil and Gas Extraction",EO4)),"","070") | MZ4: =if(ISERROR(SEARCH("Other Non-Metallic Mineral Mining and Quarrying",ES4)),"","099") | NA4: =if(ISERROR(SEARCH("Computer System Design and Related Services",EU4)),"","700") | NB4: =if(ISERROR(SEARCH("Advertising Services",EV4)),"","694") | NC4: =if(ISERROR(SEARCH("Architectural, Engineering and Technical Services",EV4)),"","692") | ND4: =if(ISERROR(SEARCH("Legal and Accounting Services",EV4)),"","693") | NE4: =if(ISERROR(SEARCH("Management and Related Consulting Services",EV4)),"","696") | NF4: =if(ISERROR(SEARCH("Market Research and Statistical Services",EV4)),"","695") | NG4: =if(ISERROR(SEARCH("Scientific Research Services",EV4)),"","691") | NH4: =if(ISERROR(SEARCH("Veterinary Services",EV4)),"","697") | NI4: =if(ISERROR(SEARCH("Other Professional, Scientific and Technical Services",EV4)),"","699") | NJ4: =if(ISERROR(SEARCH("Central Government Administration",FB4)),"","751") | NK4: =if(ISERROR(SEARCH("State Government Administration",FB4)),"","752") | NL4: =if(ISERROR(SEARCH("Local Government Administration",FB4)),"","753") | NM4: =if(ISERROR(SEARCH("Justice",FB4)),"","754") | NN4: =if(ISERROR(SEARCH("Government Representation",FB4)),"","755") | NO4: =if(ISERROR(SEARCH("Defence",FA4)),"","760") | NP4: =if(ISERROR(SEARCH("Public Order and Safety Services",FD4)),"","771") | NQ4: =if(ISERROR(SEARCH("Regulatory Services",FD4)),"","772") | NR4: =if(ISERROR(SEARCH("Property Operators",FG4)),"","671") | NS4: =if(ISERROR(SEARCH("Real Estate Services",FG4)),"","672") | NT4: =if(ISERROR(SEARCH("Farm Animal and Bloodstock Leasing",FI4)),"","662") | NU4: =if(ISERROR(SEARCH("Motor Vehicle and Transport Equipment Rental and Hiring",FI4)),"","661") | NV4: =if(ISERROR(SEARCH("Non-Financial Intangible Assets (Except Copyrights) Leasing",FI4)),"","664") | NW4: =if(ISERROR(SEARCH("Other Goods and Equipment Rental and Hiring",FI4)),"","663") | NX4: =if(ISERROR(SEARCH("Supermarket and Grocery Stores",FM4)),"","411") | NY4: =if(ISERROR(SEARCH("Specialised Food Retailing",FM4)),"","412") | NZ4: =if(ISERROR(SEARCH("Fuel Retailing",FL4)),"","400") | OA4: =if(ISERROR(SEARCH("Motor Vehicle Parts and Tyre Retailing",FO4)),"","392") | OB4: =if(ISERROR(SEARCH("Motor Vehicle Retailing",FO4)),"","391") | OC4: =if(ISERROR(SEARCH("Non-Store Retailing",FR4)),"","431") | OD4: =if(ISERROR(SEARCH("Retail Commission-Based Buying and/or Selling",FR4)),"","432") | OE4: =if(ISERROR(SEARCH("Clothing, Footwear and Personal Accessory Retailing",FS4)),"","425") | OF4: =if(ISERROR(SEARCH("Department Stores",FS4)),"","426") | OG4: =if(ISERROR(SEARCH("Electrical and Electronic Goods Retailing",FS4)),"","422") | OH4: =if(ISERROR(SEARCH("Furniture, Floor Coverings, Houseware and Textile Goods Retailing",FS4)),"","421") | OI4: =if(ISERROR(SEARCH("Hardware, Building and Garden Supplies Retailing",FS4)),"","423") | OJ4: =if(ISERROR(SEARCH("Pharmaceutical and Other Store-Based Retailing",FS4)),"","427") | OK4: =if(ISERROR(SEARCH("Recreational Goods Retailing",FS4)),"","424") | OL4: =if(ISERROR(SEARCH("Air and Space Transport",FZ4)),"","490") | OM4: =if(ISERROR(SEARCH("Postal and Courier Pick-up and Delivery Services",FZ4)),"","510") | ON4: =if(ISERROR(SEARCH("Rail Freight Transport",GB4)),"","471") | OO4: =if(ISERROR(SEARCH("Rail Passenger Transport",GB4)),"","472") | OP4: =if(ISERROR(SEARCH("Road Freight Transport",GC4)),"","461") | OQ4: =if(ISERROR(SEARCH("Road Passenger Transport",GC4)),"","462") | OR4: =if(ISERROR(SEARCH("Airport Operations and Other Air Transport Support Services",GE4)),"","522") | OS4: =if(ISERROR(SEARCH("Water Transport Support Services",GE4)),"","521") | OT4: =if(ISERROR(SEARCH("Other Transport Support Services",GE4)),"","529") | OU4: =if(ISERROR(SEARCH("Warehousing and Storage Services",FZ4)),"","530") | OV4: =if(ISERROR(SEARCH("Water Freight Transport",GI4)),"","481") | OW4: =if(ISERROR(SEARCH("Water Freight Transport",GI4)),"","482") | OX4: =if(ISERROR(SEARCH("Pipeline and Other Transport",GJ4)),"","502") | OY4: =if(ISERROR(SEARCH("Scenic and Sightseeing Transport",GJ4)),"","501") | OZ4: =if(ISERROR(SEARCH("Agricultural Product Wholesaling",GM4)),"","331") | PA4: =if(ISERROR(SEARCH("Mineral, Metal and Chemical Wholesaling",GM4)),"","332") | PB4: =if(ISERROR(SEARCH("Timber and Hardware Goods Wholesaling",GM4)),"","333") | PC4: =if(ISERROR(SEARCH("Commission-Based Wholesaling",GL4)),"","380") | PD4: =if(ISERROR(SEARCH("Grocery, Liquor and Tobacco Product Wholesaling",GL4)),"","360") | PE4: =if(ISERROR(SEARCH("Specialised Industrial Machinery and Equipment Wholesaling",GR4)),"","341") | PF4: =if(ISERROR(SEARCH("Other Machinery and Equipment Wholesaling",GR4)),"","349") | PG4: =if(ISERROR(SEARCH("Motor Vehicle and Motor Vehicle Parts Wholesaling",GL4)),"","350") | PH4: =if(ISERROR(SEARCH("Textile, Clothing and Footwear Wholesaling",GV4)),"","371") | PI4: =if(ISERROR(SEARCH("Furniture, Floor Covering and Other Goods Wholesaling",GV4)),"","373") | PJ4: =if(ISERROR(SEARCH("Pharmaceutical and Toiletry Goods Wholesaling",GV4)),"","372") | PK4: =if(ISERROR(SEARCH("Civic, Professional and Other Interest Group Services",GZ4)),"","955") | PL4: =if(ISERROR(SEARCH("Funeral, Crematorium and Cemetery Services",GZ4)),"","952") | PM4: =if(ISERROR(SEARCH("Personal Care Services",GZ4)),"","951") | PN4: =if(ISERROR(SEARCH("Religious Services",GZ4)),"","954") | PO4: =if(ISERROR(SEARCH("Other Personal Services",GZ4)),"","953") | PP4: =if(ISERROR(SEARCH("Private Households Employing Staff and Undifferentiated Goods- and Service-Producing Activities of Households for Own Use",GY4)),"","960") | PQ4: =if(ISERROR(SEARCH("Automotive Repair and Maintenance",HE4)),"","941") | PR4: =if(ISERROR(SEARCH("Machinery and Equipment Repair and Maintenance",HE4)),"","942") | PS4: =if(ISERROR(SEARCH("Other Repair and Maintenance",HE4)),"","949")
HI5: =if(ISERROR(SEARCH("Accommodation",F5)),"","440") | HJ5: =if(ISERROR(SEARCH("Cafes, Restaurants and Takeaway Food Services",G5)),"","450") | HK5: =if(ISERROR(SEARCH("Clubs (Hospitality)",G5)),"","453") | HL5: =if(ISERROR(SEARCH("Pubs, Taverns and Bars",G5)),"","452") | HM5: =if(ISERROR(SEARCH("Employment Services",J5)),"","721") | HN5: =if(ISERROR(SEARCH("Travel Agency and Tour Arrangement Services",J5)),"","722") | HO5: =if(ISERROR(SEARCH("Other Administrative Services",J5)),"","729") | HP5: =if(ISERROR(SEARCH("Building Cleaning, Pest Control and Gardening Servicess",M5)),"","731") | HQ5: =if(ISERROR(SEARCH("Packaging Services",M5)),"","732") | HR5: =if(ISERROR(SEARCH("Dairy Cattle Farming",P5)),"","016") | HS5: =if(ISERROR(SEARCH("Deer Farming",P5)),"","018") | HT5: =if(ISERROR(SEARCH("Fruit and Tree Nut Growing",P5)),"","013") | HU5: =if(ISERROR(SEARCH("Mushroom and Vegetable Growing",P5)),"","012") | HV5: =if(ISERROR(SEARCH("Nursery and Floriculture Production",P5)),"","011") | HW5: =if(ISERROR(SEARCH("Poultry Farming",P5)),"","017") | HX5: =if(ISERROR(SEARCH("Sheep, Beef Cattle and Grain Farming",P5)),"","014") | HY5: =if(ISERROR(SEARCH("Other Crop Growing",P5)),"","015") | HZ5: =if(ISERROR(SEARCH("Other Livestock Farming",P5)),"","019") | IA5: =if(ISERROR(SEARCH("Agriculture and Fishing Support Services",X5)),"","052") | IB5: =if(ISERROR(SEARCH("Forestry Support Services",X5)),"","051") | IC5: =if(ISERROR(SEARCH("Aquaculture",Z5)),"","020") | ID5: =if(ISERROR(SEARCH("Fishing",AA5)),"","041") | IE5: =if(ISERROR(SEARCH("Hunting and Trapping",AA5)),"","042") | IF5: =if(ISERROR(SEARCH("Forestry and Logging",AB5)),"","030") | IG5: =if(ISERROR(SEARCH("Creative and Performing Arts Activities",AD5)),"","900") | IH5: =if(ISERROR(SEARCH("Gambling Activities",AD5)),"","920") | II5: =if(ISERROR(SEARCH("Museum Operation",AG5)),"","891") | IJ5: =if(ISERROR(SEARCH("Parks and Gardens Operations",AG5)),"","892") | IK5: =if(ISERROR(SEARCH("Amusement and Other Recreation Activities",AI5)),"","913") | IL5: =if(ISERROR(SEARCH("Horse and Dog Racing Activities",AI5)),"","912") | IM5: =if(ISERROR(SEARCH("Sports and Physical Recreation Activities",AI5)),"","911") | IN5: =if(ISERROR(SEARCH("Residential Building Construction",AN5)),"","301") | IO5: =if(ISERROR(SEARCH("Non-Residential Building Construction",AN5)),"","302") | IP5: =if(ISERROR(SEARCH("Building Completion Services",AP5)),"","324") | IQ5: =if(ISERROR(SEARCH("Building Installation Servicess",AP5)),"","323") | IR5: =if(ISERROR(SEARCH("Building Structure Services",AP5)),"","322") | IS5: =if(ISERROR(SEARCH("Land Development and Site Preparation Services",AP5)),"","321") | IT5: =if(ISERROR(SEARCH("Other Construction Services",AP5)),"","329") | IU5: =if(ISERROR(SEARCH("Road and Bridge Construction",AV5)),"","310") | IV5: =if(ISERROR(SEARCH("Other Heavy and Civil Engineering Construction",AV5)),"","310") | IW5: =if(ISERROR(SEARCH("Adult, Community and Other Education",AX5)),"","821") | IX5: =if(ISERROR(SEARCH("Educational Support Services",AX5)),"","822") | IY5: =if(ISERROR(SEARCH("Preschool Education",AZ5)),"","801") | IZ5: =if(ISERROR(SEARCH("School Education",AZ5)),"","802") | JA5: =if(ISERROR(SEARCH("Higher Education",BB5)),"","810") | JB5: =if(ISERROR(SEARCH("Higher Education",BC5)),"","810") | JC5: =if(ISERROR(SEARCH("Electricity Distribution",BC5)),"","263") | JD5: =if(ISERROR(SEARCH("Electricity Generation",BC5)),"","261") | JE5: =if(ISERROR(SEARCH("Electricity Transmission",BC5)),"","262") | JF5: =if(ISERROR(SEARCH("On Selling Electricity and Electricity Market Operation",BC5)),"","264") | JG5: =if(ISERROR(SEARCH("Gas Supply",BC5)),"","270") | JH5: =if(ISERROR(SEARCH("Waste Collection Services",BF5)),"","291") | JI5: =if(ISERROR(SEARCH("Waste Treatment, Disposal and Remediation Services",BF5)),"","292") | JJ5: =if(ISERROR(SEARCH("Sewerage and Drainage Services",BI5)),"","281") | JK5: =if(ISERROR(SEARCH("Water Supply",BI5)),"","281") | JL5: =if(ISERROR(SEARCH("Auxiliary Finance and Investment Services",BK5)),"","641") | JM5: =if(ISERROR(SEARCH("Auxiliary Insurance Services",BK5)),"","642") | JN5: =if(ISERROR(SEARCH("Central Banking",BM5)),"","621") | JO5: =if(ISERROR(SEARCH("Depository Financial Intermediation",BM5)),"","622") | JP5: =if(ISERROR(SEARCH("Financial Asset Investing",BM5)),"","624") | JQ5: =if(ISERROR(SEARCH("Non-Depository Financing",BM5)),"","623") | JR5: =if(ISERROR(SEARCH("Health and General Insurance",BO5)),"","632") | JS5: =if(ISERROR(SEARCH("Life Insurance",BO5)),"","631") | JT5: =if(ISERROR(SEARCH("Superannuation Funds",BO5)),"","633") | JU5: =if(ISERROR(SEARCH("Hospitals",BQ5)),"","840") | JV5: =if(ISERROR(SEARCH("Medical Services",BS5)),"","851") | JW5: =if(ISERROR(SEARCH("Pathology and Diagnostic Imaging Services",BS5)),"","852") | JX5: =if(ISERROR(SEARCH("Allied Health Services",BS5)),"","853") | JY5: =if(ISERROR(SEARCH("Other Health Care Services",BS5)),"","859") | JZ5: =if(ISERROR(SEARCH("Aged Care Residential Services",BW5)),"","860") | KA5: =if(ISERROR(SEARCH("Other Residential Care Services",BW5)),"","860") | KB5: =if(ISERROR(SEARCH("Child Care Services",BX5)),"","871") | KC5: =if(ISERROR(SEARCH("Other Social Assistance Services",BX5)),"","879") | KD5: =if(ISERROR(SEARCH("Radio Broadcasting",BZ5)),"","561") | KE5: =if(ISERROR(SEARCH("Television Broadcasting",BZ5)),"","562") | KF5: =if(ISERROR(SEARCH("Internet Publishing and Broadcasting",BY5)),"","570") | KG5: =if(ISERROR(SEARCH("Data Processing, Web Hosting and Electronic Information Storage Services",CB5)),"","592") | KH5: =if(ISERROR(SEARCH("Internet Service Providers and Web Search Portals",CB5)),"","591") | KI5: =if(ISERROR(SEARCH("Libraries and Archives",CD5)),"","601") | KJ5: =if(ISERROR(SEARCH("Other Information Services",CD5)),"","602") | KK5: =if(ISERROR(SEARCH("Motion Picture and Video Activities",CE5)),"","551") | KL5: =if(ISERROR(SEARCH("Sound Recording and Music Publishing",CE5)),"","552") | KM5: =if(ISERROR(SEARCH("Newspaper, Periodical, Book and Directory Publishing",CH5)),"","541") | KN5: =if(ISERROR(SEARCH("Software Publishing",CH5)),"","542") | KO5: =if(ISERROR(SEARCH("Telecommunications Services",BY5)),"","580") | KP5: =if(ISERROR(SEARCH("Basic Chemical Manufacturing",CK5)),"","181") | KQ5: =if(ISERROR(SEARCH("Basic Polymer Manufacturing",CK5)),"","182") | KR5: =if(ISERROR(SEARCH("Cleaning Compound and Toiletry Preparation Manufacturing",CK5)),"","185") | KS5: =if(ISERROR(SEARCH("Fertiliser and Pesticide Manufacturing",CK5)),"","183") | KT5: =if(ISERROR(SEARCH("Pharmaceutical and Medicinal Product Manufacturing",CK5)),"","184") | KU5: =if(ISERROR(SEARCH("Other Basic Chemical Product Manufacturing",CK5)),"","189") | KV5: =if(ISERROR(SEARCH("Beverage Manufacturing",CR5)),"","121") | KW5: =if(ISERROR(SEARCH("Cigarette and Tobacco Product Manufacturing",CR5)),"","122") | KX5: =if(ISERROR(SEARCH("Iron and Steel Forging",CT5)),"","221") | KY5: =if(ISERROR(SEARCH("Metal Container Manufacturing",CT5)),"","223") | KZ5: =if(ISERROR(SEARCH("Sheet Metal Product Manufacturing (except Metal Structural and Container Products)",CT5)),"","224") | LA5: =if(ISERROR(SEARCH("Structural Metal Product Manufacturing",CT5)),"","222") | LB5: =if(ISERROR(SEARCH("Other Fabricated Metal Product Manufacturing",CT5)),"","229") | LC5: =if(ISERROR(SEARCH("Bakery Product Manufacturing",CX5)),"","117") | LD5: =if(ISERROR(SEARCH("Dairy Product Manufacturing",CX5)),"","113") | LE5: =if(ISERROR(SEARCH("Fruit and Vegetable Processing",CX5)),"","114") | LF5: =if(ISERROR(SEARCH("Grain Mill and Cereal Product Manufacturing",CX5)),"","116") | LG5: =if(ISERROR(SEARCH("Meat and Meat Product Manufacturing",CX5)),"","111") | LH5: =if(ISERROR(SEARCH("Oil and Fat Manufacturing",CX5)),"","115") | LI5: =if(ISERROR(SEARCH("Seafood Processing",CX5)),"","112") | LJ5: =if(ISERROR(SEARCH("Sugar and Confectionery Manufacturing",CX5)),"","118") | LK5: =if(ISERROR(SEARCH("Other Food Product Manufacturing",CX5)),"","119") | LL5: =if(ISERROR(SEARCH("Furniture Manufacturing",DE5)),"","251") | LM5: =if(ISERROR(SEARCH("Other Manufacturing",DE5)),"","259") | LN5: =if(ISERROR(SEARCH("Computer and Electronic Equipment Manufacturing",DH5)),"","242") | LO5: =if(ISERROR(SEARCH("Domestic Appliance Manufacturing",DH5)),"","244") | LP5: =if(ISERROR(SEARCH("Electrical Equipment Manufacturing",DH5)),"","243") | LQ5: =if(ISERROR(SEARCH("Professional and Scientific Equipment Manufacturing",DH5)),"","241") | LR5: =if(ISERROR(SEARCH("Pump, Compressor, Heating and Ventilation Equipment Manufacturing",DH5)),"","245") | LS5: =if(ISERROR(SEARCH("Specialised Machinery and Equipment Manufacturing",DH5)),"","246") | LT5: =if(ISERROR(SEARCH("Other Machinery and Equipment Manufacturing",DH5)),"","249") | LU5: =if(ISERROR(SEARCH("Cement, Lime, Plaster and Concrete Product Manufacturing",DP5)),"","203") | LV5: =if(ISERROR(SEARCH("Ceramic Product Manufacturing",DP5)),"","202") | LW5: =if(ISERROR(SEARCH("Glass and Glass Product Manufacturing",DP5)),"","201") | LX5: =if(ISERROR(SEARCH("Other Non-Metallic Mineral Product Manufacturing",DP5)),"","209") | LY5: =if(ISERROR(SEARCH("Petroleum Refining and Petroleum Fuel Manufacturing",DS5)),"","170") | LZ5: =if(ISERROR(SEARCH("Other Petroleum and Coal Product Manufacturing",DS5)),"","170") | MA5: =if(ISERROR(SEARCH("Natural Rubber Product Manufacturing",DT5)),"","192") | MB5: =if(ISERROR(SEARCH("Polymer Product Manufacturing",DT5)),"","191") | MC5: =if(ISERROR(SEARCH("Basic Ferrous Metal Manufacturing",DV5)),"","211") | MD5: =if(ISERROR(SEARCH("Basic Ferrous Metal Product Manufacturing",DV5)),"","212") | ME5: =if(ISERROR(SEARCH("Basic Non-Ferrous Metal Manufacturing",DV5)),"","213") | MF5: =if(ISERROR(SEARCH("Basic Non-Ferrous Metal Product Manufacturing",DV5)),"","214") | MG5: =if(ISERROR(SEARCH("Printing and Printing Support Services",EA5)),"","161") | MH5: =if(ISERROR(SEARCH("Reproduction of Recorded Media",EA5)),"","162") | MI5: =if(ISERROR(SEARCH("Converted Paper Product Manufacturing",EC5)),"","152") | MJ5: =if(ISERROR(SEARCH("Pulp, Paper and Paperboard Manufacturing",EC5)),"","151") | MK5: =if(ISERROR(SEARCH("Clothing and Footwear Manufacturing",EE5)),"","135") | ML5: =if(ISERROR(SEARCH("Knitted Product Manufacturing",EE5)),"","134") | MM5: =if(ISERROR(SEARCH("Leather Tanning, Fur Dressing and Leather Product Manufacturing",EE5)),"","132") | MN5: =if(ISERROR(SEARCH("Textile Manufacturing",EE5)),"","131") | MO5: =if(ISERROR(SEARCH("Textile Product Manufacturing",EE5)),"","133") | MP5: =if(ISERROR(SEARCH("Motor Vehicle and Motor Vehicle Part Manufacturing",EI5)),"","231") | MQ5: =if(ISERROR(SEARCH("Other Transport Equipment Manufacturing",EI5)),"","239") | MR5: =if(ISERROR(SEARCH("Log Sawmilling and Timber Dressing",EL5)),"","141") | MS5: =if(ISERROR(SEARCH("Other Wood Product Manufacturing",EL5)),"","149") | MT5: =if(ISERROR(SEARCH("Coal Mining",EO5)),"","060") | MU5: =if(ISERROR(SEARCH("Exploration",EP5)),"","101") | MV5: =if(ISERROR(SEARCH("Other Mining Support Services",EP5)),"","109") | MW5: =if(ISERROR(SEARCH("Metal Ore Mining",EO5)),"","080") | MX5: =if(ISERROR(SEARCH("Construction Material Mining",ES5)),"","091") | MY5: =if(ISERROR(SEARCH("Oil and Gas Extraction",EO5)),"","070") | MZ5: =if(ISERROR(SEARCH("Other Non-Metallic Mineral Mining and Quarrying",ES5)),"","099") | NA5: =if(ISERROR(SEARCH("Computer System Design and Related Services",EU5)),"","700") | NB5: =if(ISERROR(SEARCH("Advertising Services",EV5)),"","694") | NC5: =if(ISERROR(SEARCH("Architectural, Engineering and Technical Services",EV5)),"","692") | ND5: =if(ISERROR(SEARCH("Legal and Accounting Services",EV5)),"","693") | NE5: =if(ISERROR(SEARCH("Management and Related Consulting Services",EV5)),"","696") | NF5: =if(ISERROR(SEARCH("Market Research and Statistical Services",EV5)),"","695") | NG5: =if(ISERROR(SEARCH("Scientific Research Services",EV5)),"","691") | NH5: =if(ISERROR(SEARCH("Veterinary Services",EV5)),"","697") | NI5: =if(ISERROR(SEARCH("Other Professional, Scientific and Technical Services",EV5)),"","699") | NJ5: =if(ISERROR(SEARCH("Central Government Administration",FB5)),"","751") | NK5: =if(ISERROR(SEARCH("State Government Administration",FB5)),"","752") | NL5: =if(ISERROR(SEARCH("Local Government Administration",FB5)),"","753") | NM5: =if(ISERROR(SEARCH("Justice",FB5)),"","754") | NN5: =if(ISERROR(SEARCH("Government Representation",FB5)),"","755") | NO5: =if(ISERROR(SEARCH("Defence",FA5)),"","760") | NP5: =if(ISERROR(SEARCH("Public Order and Safety Services",FD5)),"","771") | NQ5: =if(ISERROR(SEARCH("Regulatory Services",FD5)),"","772") | NR5: =if(ISERROR(SEARCH("Property Operators",FG5)),"","671") | NS5: =if(ISERROR(SEARCH("Real Estate Services",FG5)),"","672") | NT5: =if(ISERROR(SEARCH("Farm Animal and Bloodstock Leasing",FI5)),"","662") | NU5: =if(ISERROR(SEARCH("Motor Vehicle and Transport Equipment Rental and Hiring",FI5)),"","661") | NV5: =if(ISERROR(SEARCH("Non-Financial Intangible Assets (Except Copyrights) Leasing",FI5)),"","664") | NW5: =if(ISERROR(SEARCH("Other Goods and Equipment Rental and Hiring",FI5)),"","663") | NX5: =if(ISERROR(SEARCH("Supermarket and Grocery Stores",FM5)),"","411") | NY5: =if(ISERROR(SEARCH("Specialised Food Retailing",FM5)),"","412") | NZ5: =if(ISERROR(SEARCH("Fuel Retailing",FL5)),"","400") | OA5: =if(ISERROR(SEARCH("Motor Vehicle Parts and Tyre Retailing",FO5)),"","392") | OB5: =if(ISERROR(SEARCH("Motor Vehicle Retailing",FO5)),"","391") | OC5: =if(ISERROR(SEARCH("Non-Store Retailing",FR5)),"","431") | OD5: =if(ISERROR(SEARCH("Retail Commission-Based Buying and/or Selling",FR5)),"","432") | OE5: =if(ISERROR(SEARCH("Clothing, Footwear and Personal Accessory Retailing",FS5)),"","425") | OF5: =if(ISERROR(SEARCH("Department Stores",FS5)),"","426") | OG5: =if(ISERROR(SEARCH("Electrical and Electronic Goods Retailing",FS5)),"","422") | OH5: =if(ISERROR(SEARCH("Furniture, Floor Coverings, Houseware and Textile Goods Retailing",FS5)),"","421") | OI5: =if(ISERROR(SEARCH("Hardware, Building and Garden Supplies Retailing",FS5)),"","423") | OJ5: =if(ISERROR(SEARCH("Pharmaceutical and Other Store-Based Retailing",FS5)),"","427") | OK5: =if(ISERROR(SEARCH("Recreational Goods Retailing",FS5)),"","424") | OL5: =if(ISERROR(SEARCH("Air and Space Transport",FZ5)),"","490") | OM5: =if(ISERROR(SEARCH("Postal and Courier Pick-up and Delivery Services",FZ5)),"","510") | ON5: =if(ISERROR(SEARCH("Rail Freight Transport",GB5)),"","471") | OO5: =if(ISERROR(SEARCH("Rail Passenger Transport",GB5)),"","472") | OP5: =if(ISERROR(SEARCH("Road Freight Transport",GC5)),"","461") | OQ5: =if(ISERROR(SEARCH("Road Passenger Transport",GC5)),"","462") | OR5: =if(ISERROR(SEARCH("Airport Operations and Other Air Transport Support Services",GE5)),"","522") | OS5: =if(ISERROR(SEARCH("Water Transport Support Services",GE5)),"","521") | OT5: =if(ISERROR(SEARCH("Other Transport Support Services",GE5)),"","529") | OU5: =if(ISERROR(SEARCH("Warehousing and Storage Services",FZ5)),"","530") | OV5: =if(ISERROR(SEARCH("Water Freight Transport",GI5)),"","481") | OW5: =if(ISERROR(SEARCH("Water Freight Transport",GI5)),"","482") | OX5: =if(ISERROR(SEARCH("Pipeline and Other Transport",GJ5)),"","502") | OY5: =if(ISERROR(SEARCH("Scenic and Sightseeing Transport",GJ5)),"","501") | OZ5: =if(ISERROR(SEARCH("Agricultural Product Wholesaling",GM5)),"","331") | PA5: =if(ISERROR(SEARCH("Mineral, Metal and Chemical Wholesaling",GM5)),"","332") | PB5: =if(ISERROR(SEARCH("Timber and Hardware Goods Wholesaling",GM5)),"","333") | PC5: =if(ISERROR(SEARCH("Commission-Based Wholesaling",GL5)),"","380") | PD5: =if(ISERROR(SEARCH("Grocery, Liquor and Tobacco Product Wholesaling",GL5)),"","360") | PE5: =if(ISERROR(SEARCH("Specialised Industrial Machinery and Equipment Wholesaling",GR5)),"","341") | PF5: =if(ISERROR(SEARCH("Other Machinery and Equipment Wholesaling",GR5)),"","349") | PG5: =if(ISERROR(SEARCH("Motor Vehicle and Motor Vehicle Parts Wholesaling",GL5)),"","350") | PH5: =if(ISERROR(SEARCH("Textile, Clothing and Footwear Wholesaling",GV5)),"","371") | PI5: =if(ISERROR(SEARCH("Furniture, Floor Covering and Other Goods Wholesaling",GV5)),"","373") | PJ5: =if(ISERROR(SEARCH("Pharmaceutical and Toiletry Goods Wholesaling",GV5)),"","372") | PK5: =if(ISERROR(SEARCH("Civic, Professional and Other Interest Group Services",GZ5)),"","955") | PL5: =if(ISERROR(SEARCH("Funeral, Crematorium and Cemetery Services",GZ5)),"","952") | PM5: =if(ISERROR(SEARCH("Personal Care Services",GZ5)),"","951") | PN5: =if(ISERROR(SEARCH("Religious Services",GZ5)),"","954") | PO5: =if(ISERROR(SEARCH("Other Personal Services",GZ5)),"","953") | PP5: =if(ISERROR(SEARCH("Private Households Employing Staff and Undifferentiated Goods- and Service-Producing Activities of Households for Own Use",GY5)),"","960") | PQ5: =if(ISERROR(SEARCH("Automotive Repair and Maintenance",HE5)),"","941") | PR5: =if(ISERROR(SEARCH("Machinery and Equipment Repair and Maintenance",HE5)),"","942") | PS5: =if(ISERROR(SEARCH("Other Repair and Maintenance",HE5)),"","949")
HI6: =if(ISERROR(SEARCH("Accommodation",F6)),"","440") | HJ6: =if(ISERROR(SEARCH("Cafes, Restaurants and Takeaway Food Services",G6)),"","450") | HK6: =if(ISERROR(SEARCH("Clubs (Hospitality)",G6)),"","453") | HL6: =if(ISERROR(SEARCH("Pubs, Taverns and Bars",G6)),"","452") | HM6: =if(ISERROR(SEARCH("Employment Services",J6)),"","721") | HN6: =if(ISERROR(SEARCH("Travel Agency and Tour Arrangement Services",J6)),"","722") | HO6: =if(ISERROR(SEARCH("Other Administrative Services",J6)),"","729") | HP6: =if(ISERROR(SEARCH("Building Cleaning, Pest Control and Gardening Servicess",M6)),"","731") | HQ6: =if(ISERROR(SEARCH("Packaging Services",M6)),"","732") | HR6: =if(ISERROR(SEARCH("Dairy Cattle Farming",P6)),"","016") | HS6: =if(ISERROR(SEARCH("Deer Farming",P6)),"","018") | HT6: =if(ISERROR(SEARCH("Fruit and Tree Nut Growing",P6)),"","013") | HU6: =if(ISERROR(SEARCH("Mushroom and Vegetable Growing",P6)),"","012") | HV6: =if(ISERROR(SEARCH("Nursery and Floriculture Production",P6)),"","011") | HW6: =if(ISERROR(SEARCH("Poultry Farming",P6)),"","017") | HX6: =if(ISERROR(SEARCH("Sheep, Beef Cattle and Grain Farming",P6)),"","014") | HY6: =if(ISERROR(SEARCH("Other Crop Growing",P6)),"","015") | HZ6: =if(ISERROR(SEARCH("Other Livestock Farming",P6)),"","019") | IA6: =if(ISERROR(SEARCH("Agriculture and Fishing Support Services",X6)),"","052") | IB6: =if(ISERROR(SEARCH("Forestry Support Services",X6)),"","051") | IC6: =if(ISERROR(SEARCH("Aquaculture",Z6)),"","020") | ID6: =if(ISERROR(SEARCH("Fishing",AA6)),"","041") | IE6: =if(ISERROR(SEARCH("Hunting and Trapping",AA6)),"","042") | IF6: =if(ISERROR(SEARCH("Forestry and Logging",AB6)),"","030") | IG6: =if(ISERROR(SEARCH("Creative and Performing Arts Activities",AD6)),"","900") | IH6: =if(ISERROR(SEARCH("Gambling Activities",AD6)),"","920") | II6: =if(ISERROR(SEARCH("Museum Operation",AG6)),"","891") | IJ6: =if(ISERROR(SEARCH("Parks and Gardens Operations",AG6)),"","892") | IK6: =if(ISERROR(SEARCH("Amusement and Other Recreation Activities",AI6)),"","913") | IL6: =if(ISERROR(SEARCH("Horse and Dog Racing Activities",AI6)),"","912") | IM6: =if(ISERROR(SEARCH("Sports and Physical Recreation Activities",AI6)),"","911") | IN6: =if(ISERROR(SEARCH("Residential Building Construction",AN6)),"","301") | IO6: =if(ISERROR(SEARCH("Non-Residential Building Construction",AN6)),"","302") | IP6: =if(ISERROR(SEARCH("Building Completion Services",AP6)),"","324") | IQ6: =if(ISERROR(SEARCH("Building Installation Servicess",AP6)),"","323") | IR6: =if(ISERROR(SEARCH("Building Structure Services",AP6)),"","322") | IS6: =if(ISERROR(SEARCH("Land Development and Site Preparation Services",AP6)),"","321") | IT6: =if(ISERROR(SEARCH("Other Construction Services",AP6)),"","329") | IU6: =if(ISERROR(SEARCH("Road and Bridge Construction",AV6)),"","310") | IV6: =if(ISERROR(SEARCH("Other Heavy and Civil Engineering Construction",AV6)),"","310") | IW6: =if(ISERROR(SEARCH("Adult, Community and Other Education",AX6)),"","821") | IX6: =if(ISERROR(SEARCH("Educational Support Services",AX6)),"","822") | IY6: =if(ISERROR(SEARCH("Preschool Education",AZ6)),"","801") | IZ6: =if(ISERROR(SEARCH("School Education",AZ6)),"","802") | JA6: =if(ISERROR(SEARCH("Higher Education",BB6)),"","810") | JB6: =if(ISERROR(SEARCH("Higher Education",BC6)),"","810") | JC6: =if(ISERROR(SEARCH("Electricity Distribution",BC6)),"","263") | JD6: =if(ISERROR(SEARCH("Electricity Generation",BC6)),"","261") | JE6: =if(ISERROR(SEARCH("Electricity Transmission",BC6)),"","262") | JF6: =if(ISERROR(SEARCH("On Selling Electricity and Electricity Market Operation",BC6)),"","264") | JG6: =if(ISERROR(SEARCH("Gas Supply",BC6)),"","270") | JH6: =if(ISERROR(SEARCH("Waste Collection Services",BF6)),"","291") | JI6: =if(ISERROR(SEARCH("Waste Treatment, Disposal and Remediation Services",BF6)),"","292") | JJ6: =if(ISERROR(SEARCH("Sewerage and Drainage Services",BI6)),"","281") | JK6: =if(ISERROR(SEARCH("Water Supply",BI6)),"","281") | JL6: =if(ISERROR(SEARCH("Auxiliary Finance and Investment Services",BK6)),"","641") | JM6: =if(ISERROR(SEARCH("Auxiliary Insurance Services",BK6)),"","642") | JN6: =if(ISERROR(SEARCH("Central Banking",BM6)),"","621") | JO6: =if(ISERROR(SEARCH("Depository Financial Intermediation",BM6)),"","622") | JP6: =if(ISERROR(SEARCH("Financial Asset Investing",BM6)),"","624") | JQ6: =if(ISERROR(SEARCH("Non-Depository Financing",BM6)),"","623") | JR6: =if(ISERROR(SEARCH("Health and General Insurance",BO6)),"","632") | JS6: =if(ISERROR(SEARCH("Life Insurance",BO6)),"","631") | JT6: =if(ISERROR(SEARCH("Superannuation Funds",BO6)),"","633") | JU6: =if(ISERROR(SEARCH("Hospitals",BQ6)),"","840") | JV6: =if(ISERROR(SEARCH("Medical Services",BS6)),"","851") | JW6: =if(ISERROR(SEARCH("Pathology and Diagnostic Imaging Services",BS6)),"","852") | JX6: =if(ISERROR(SEARCH("Allied Health Services",BS6)),"","853") | JY6: =if(ISERROR(SEARCH("Other Health Care Services",BS6)),"","859") | JZ6: =if(ISERROR(SEARCH("Aged Care Residential Services",BW6)),"","860") | KA6: =if(ISERROR(SEARCH("Other Residential Care Services",BW6)),"","860") | KB6: =if(ISERROR(SEARCH("Child Care Services",BX6)),"","871") | KC6: =if(ISERROR(SEARCH("Other Social Assistance Services",BX6)),"","879") | KD6: =if(ISERROR(SEARCH("Radio Broadcasting",BZ6)),"","561") | KE6: =if(ISERROR(SEARCH("Television Broadcasting",BZ6)),"","562") | KF6: =if(ISERROR(SEARCH("Internet Publishing and Broadcasting",BY6)),"","570") | KG6: =if(ISERROR(SEARCH("Data Processing, Web Hosting and Electronic Information Storage Services",CB6)),"","592") | KH6: =if(ISERROR(SEARCH("Internet Service Providers and Web Search Portals",CB6)),"","591") | KI6: =if(ISERROR(SEARCH("Libraries and Archives",CD6)),"","601") | KJ6: =if(ISERROR(SEARCH("Other Information Services",CD6)),"","602") | KK6: =if(ISERROR(SEARCH("Motion Picture and Video Activities",CE6)),"","551") | KL6: =if(ISERROR(SEARCH("Sound Recording and Music Publishing",CE6)),"","552") | KM6: =if(ISERROR(SEARCH("Newspaper, Periodical, Book and Directory Publishing",CH6)),"","541") | KN6: =if(ISERROR(SEARCH("Software Publishing",CH6)),"","542") | KO6: =if(ISERROR(SEARCH("Telecommunications Services",BY6)),"","580") | KP6: =if(ISERROR(SEARCH("Basic Chemical Manufacturing",CK6)),"","181") | KQ6: =if(ISERROR(SEARCH("Basic Polymer Manufacturing",CK6)),"","182") | KR6: =if(ISERROR(SEARCH("Cleaning Compound and Toiletry Preparation Manufacturing",CK6)),"","185") | KS6: =if(ISERROR(SEARCH("Fertiliser and Pesticide Manufacturing",CK6)),"","183") | KT6: =if(ISERROR(SEARCH("Pharmaceutical and Medicinal Product Manufacturing",CK6)),"","184") | KU6: =if(ISERROR(SEARCH("Other Basic Chemical Product Manufacturing",CK6)),"","189") | KV6: =if(ISERROR(SEARCH("Beverage Manufacturing",CR6)),"","121") | KW6: =if(ISERROR(SEARCH("Cigarette and Tobacco Product Manufacturing",CR6)),"","122") | KX6: =if(ISERROR(SEARCH("Iron and Steel Forging",CT6)),"","221") | KY6: =if(ISERROR(SEARCH("Metal Container Manufacturing",CT6)),"","223") | KZ6: =if(ISERROR(SEARCH("Sheet Metal Product Manufacturing (except Metal Structural and Container Products)",CT6)),"","224") | LA6: =if(ISERROR(SEARCH("Structural Metal Product Manufacturing",CT6)),"","222") | LB6: =if(ISERROR(SEARCH("Other Fabricated Metal Product Manufacturing",CT6)),"","229") | LC6: =if(ISERROR(SEARCH("Bakery Product Manufacturing",CX6)),"","117") | LD6: =if(ISERROR(SEARCH("Dairy Product Manufacturing",CX6)),"","113") | LE6: =if(ISERROR(SEARCH("Fruit and Vegetable Processing",CX6)),"","114") | LF6: =if(ISERROR(SEARCH("Grain Mill and Cereal Product Manufacturing",CX6)),"","116") | LG6: =if(ISERROR(SEARCH("Meat and Meat Product Manufacturing",CX6)),"","111") | LH6: =if(ISERROR(SEARCH("Oil and Fat Manufacturing",CX6)),"","115") | LI6: =if(ISERROR(SEARCH("Seafood Processing",CX6)),"","112") | LJ6: =if(ISERROR(SEARCH("Sugar and Confectionery Manufacturing",CX6)),"","118") | LK6: =if(ISERROR(SEARCH("Other Food Product Manufacturing",CX6)),"","119") | LL6: =if(ISERROR(SEARCH("Furniture Manufacturing",DE6)),"","251") | LM6: =if(ISERROR(SEARCH("Other Manufacturing",DE6)),"","259") | LN6: =if(ISERROR(SEARCH("Computer and Electronic Equipment Manufacturing",DH6)),"","242") | LO6: =if(ISERROR(SEARCH("Domestic Appliance Manufacturing",DH6)),"","244") | LP6: =if(ISERROR(SEARCH("Electrical Equipment Manufacturing",DH6)),"","243") | LQ6: =if(ISERROR(SEARCH("Professional and Scientific Equipment Manufacturing",DH6)),"","241") | LR6: =if(ISERROR(SEARCH("Pump, Compressor, Heating and Ventilation Equipment Manufacturing",DH6)),"","245") | LS6: =if(ISERROR(SEARCH("Specialised Machinery and Equipment Manufacturing",DH6)),"","246") | LT6: =if(ISERROR(SEARCH("Other Machinery and Equipment Manufacturing",DH6)),"","249") | LU6: =if(ISERROR(SEARCH("Cement, Lime, Plaster and Concrete Product Manufacturing",DP6)),"","203") | LV6: =if(ISERROR(SEARCH("Ceramic Product Manufacturing",DP6)),"","202") | LW6: =if(ISERROR(SEARCH("Glass and Glass Product Manufacturing",DP6)),"","201") | LX6: =if(ISERROR(SEARCH("Other Non-Metallic Mineral Product Manufacturing",DP6)),"","209") | LY6: =if(ISERROR(SEARCH("Petroleum Refining and Petroleum Fuel Manufacturing",DS6)),"","170") | LZ6: =if(ISERROR(SEARCH("Other Petroleum and Coal Product Manufacturing",DS6)),"","170") | MA6: =if(ISERROR(SEARCH("Natural Rubber Product Manufacturing",DT6)),"","192") | MB6: =if(ISERROR(SEARCH("Polymer Product Manufacturing",DT6)),"","191") | MC6: =if(ISERROR(SEARCH("Basic Ferrous Metal Manufacturing",DV6)),"","211") | MD6: =if(ISERROR(SEARCH("Basic Ferrous Metal Product Manufacturing",DV6)),"","212") | ME6: =if(ISERROR(SEARCH("Basic Non-Ferrous Metal Manufacturing",DV6)),"","213") | MF6: =if(ISERROR(SEARCH("Basic Non-Ferrous Metal Product Manufacturing",DV6)),"","214") | MG6: =if(ISERROR(SEARCH("Printing and Printing Support Services",EA6)),"","161") | MH6: =if(ISERROR(SEARCH("Reproduction of Recorded Media",EA6)),"","162") | MI6: =if(ISERROR(SEARCH("Converted Paper Product Manufacturing",EC6)),"","152") | MJ6: =if(ISERROR(SEARCH("Pulp, Paper and Paperboard Manufacturing",EC6)),"","151") | MK6: =if(ISERROR(SEARCH("Clothing and Footwear Manufacturing",EE6)),"","135") | ML6: =if(ISERROR(SEARCH("Knitted Product Manufacturing",EE6)),"","134") | MM6: =if(ISERROR(SEARCH("Leather Tanning, Fur Dressing and Leather Product Manufacturing",EE6)),"","132") | MN6: =if(ISERROR(SEARCH("Textile Manufacturing",EE6)),"","131") | MO6: =if(ISERROR(SEARCH("Textile Product Manufacturing",EE6)),"","133") | MP6: =if(ISERROR(SEARCH("Motor Vehicle and Motor Vehicle Part Manufacturing",EI6)),"","231") | MQ6: =if(ISERROR(SEARCH("Other Transport Equipment Manufacturing",EI6)),"","239") | MR6: =if(ISERROR(SEARCH("Log Sawmilling and Timber Dressing",EL6)),"","141") | MS6: =if(ISERROR(SEARCH("Other Wood Product Manufacturing",EL6)),"","149") | MT6: =if(ISERROR(SEARCH("Coal Mining",EO6)),"","060") | MU6: =if(ISERROR(SEARCH("Exploration",EP6)),"","101") | MV6: =if(ISERROR(SEARCH("Other Mining Support Services",EP6)),"","109") | MW6: =if(ISERROR(SEARCH("Metal Ore Mining",EO6)),"","080") | MX6: =if(ISERROR(SEARCH("Construction Material Mining",ES6)),"","091") | MY6: =if(ISERROR(SEARCH("Oil and Gas Extraction",EO6)),"","070") | MZ6: =if(ISERROR(SEARCH("Other Non-Metallic Mineral Mining and Quarrying",ES6)),"","099") | NA6: =if(ISERROR(SEARCH("Computer System Design and Related Services",EU6)),"","700") | NB6: =if(ISERROR(SEARCH("Advertising Services",EV6)),"","694") | NC6: =if(ISERROR(SEARCH("Architectural, Engineering and Technical Services",EV6)),"","692") | ND6: =if(ISERROR(SEARCH("Legal and Accounting Services",EV6)),"","693") | NE6: =if(ISERROR(SEARCH("Management and Related Consulting Services",EV6)),"","696") | NF6: =if(ISERROR(SEARCH("Market Research and Statistical Services",EV6)),"","695") | NG6: =if(ISERROR(SEARCH("Scientific Research Services",EV6)),"","691") | NH6: =if(ISERROR(SEARCH("Veterinary Services",EV6)),"","697") | NI6: =if(ISERROR(SEARCH("Other Professional, Scientific and Technical Services",EV6)),"","699") | NJ6: =if(ISERROR(SEARCH("Central Government Administration",FB6)),"","751") | NK6: =if(ISERROR(SEARCH("State Government Administration",FB6)),"","752") | NL6: =if(ISERROR(SEARCH("Local Government Administration",FB6)),"","753") | NM6: =if(ISERROR(SEARCH("Justice",FB6)),"","754") | NN6: =if(ISERROR(SEARCH("Government Representation",FB6)),"","755") | NO6: =if(ISERROR(SEARCH("Defence",FA6)),"","760") | NP6: =if(ISERROR(SEARCH("Public Order and Safety Services",FD6)),"","771") | NQ6: =if(ISERROR(SEARCH("Regulatory Services",FD6)),"","772") | NR6: =if(ISERROR(SEARCH("Property Operators",FG6)),"","671") | NS6: =if(ISERROR(SEARCH("Real Estate Services",FG6)),"","672") | NT6: =if(ISERROR(SEARCH("Farm Animal and Bloodstock Leasing",FI6)),"","662") | NU6: =if(ISERROR(SEARCH("Motor Vehicle and Transport Equipment Rental and Hiring",FI6)),"","661") | NV6: =if(ISERROR(SEARCH("Non-Financial Intangible Assets (Except Copyrights) Leasing",FI6)),"","664") | NW6: =if(ISERROR(SEARCH("Other Goods and Equipment Rental and Hiring",FI6)),"","663") | NX6: =if(ISERROR(SEARCH("Supermarket and Grocery Stores",FM6)),"","411") | NY6: =if(ISERROR(SEARCH("Specialised Food Retailing",FM6)),"","412") | NZ6: =if(ISERROR(SEARCH("Fuel Retailing",FL6)),"","400") | OA6: =if(ISERROR(SEARCH("Motor Vehicle Parts and Tyre Retailing",FO6)),"","392") | OB6: =if(ISERROR(SEARCH("Motor Vehicle Retailing",FO6)),"","391") | OC6: =if(ISERROR(SEARCH("Non-Store Retailing",FR6)),"","431") | OD6: =if(ISERROR(SEARCH("Retail Commission-Based Buying and/or Selling",FR6)),"","432") | OE6: =if(ISERROR(SEARCH("Clothing, Footwear and Personal Accessory Retailing",FS6)),"","425") | OF6: =if(ISERROR(SEARCH("Department Stores",FS6)),"","426") | OG6: =if(ISERROR(SEARCH("Electrical and Electronic Goods Retailing",FS6)),"","422") | OH6: =if(ISERROR(SEARCH("Furniture, Floor Coverings, Houseware and Textile Goods Retailing",FS6)),"","421") | OI6: =if(ISERROR(SEARCH("Hardware, Building and Garden Supplies Retailing",FS6)),"","423") | OJ6: =if(ISERROR(SEARCH("Pharmaceutical and Other Store-Based Retailing",FS6)),"","427") | OK6: =if(ISERROR(SEARCH("Recreational Goods Retailing",FS6)),"","424") | OL6: =if(ISERROR(SEARCH("Air and Space Transport",FZ6)),"","490") | OM6: =if(ISERROR(SEARCH("Postal and Courier Pick-up and Delivery Services",FZ6)),"","510") | ON6: =if(ISERROR(SEARCH("Rail Freight Transport",GB6)),"","471") | OO6: =if(ISERROR(SEARCH("Rail Passenger Transport",GB6)),"","472") | OP6: =if(ISERROR(SEARCH("Road Freight Transport",GC6)),"","461") | OQ6: =if(ISERROR(SEARCH("Road Passenger Transport",GC6)),"","462") | OR6: =if(ISERROR(SEARCH("Airport Operations and Other Air Transport Support Services",GE6)),"","522") | OS6: =if(ISERROR(SEARCH("Water Transport Support Services",GE6)),"","521") | OT6: =if(ISERROR(SEARCH("Other Transport Support Services",GE6)),"","529") | OU6: =if(ISERROR(SEARCH("Warehousing and Storage Services",FZ6)),"","530") | OV6: =if(ISERROR(SEARCH("Water Freight Transport",GI6)),"","481") | OW6: =if(ISERROR(SEARCH("Water Freight Transport",GI6)),"","482") | OX6: =if(ISERROR(SEARCH("Pipeline and Other Transport",GJ6)),"","502") | OY6: =if(ISERROR(SEARCH("Scenic and Sightseeing Transport",GJ6)),"","501") | OZ6: =if(ISERROR(SEARCH("Agricultural Product Wholesaling",GM6)),"","331") | PA6: =if(ISERROR(SEARCH("Mineral, Metal and Chemical Wholesaling",GM6)),"","332") | PB6: =if(ISERROR(SEARCH("Timber and Hardware Goods Wholesaling",GM6)),"","333") | PC6: =if(ISERROR(SEARCH("Commission-Based Wholesaling",GL6)),"","380") | PD6: =if(ISERROR(SEARCH("Grocery, Liquor and Tobacco Product Wholesaling",GL6)),"","360") | PE6: =if(ISERROR(SEARCH("Specialised Industrial Machinery and Equipment Wholesaling",GR6)),"","341") | PF6: =if(ISERROR(SEARCH("Other Machinery and Equipment Wholesaling",GR6)),"","349") | PG6: =if(ISERROR(SEARCH("Motor Vehicle and Motor Vehicle Parts Wholesaling",GL6)),"","350") | PH6: =if(ISERROR(SEARCH("Textile, Clothing and Footwear Wholesaling",GV6)),"","371") | PI6: =if(ISERROR(SEARCH("Furniture, Floor Covering and Other Goods Wholesaling",GV6)),"","373") | PJ6: =if(ISERROR(SEARCH("Pharmaceutical and Toiletry Goods Wholesaling",GV6)),"","372") | PK6: =if(ISERROR(SEARCH("Civic, Professional and Other Interest Group Services",GZ6)),"","955") | PL6: =if(ISERROR(SEARCH("Funeral, Crematorium and Cemetery Services",GZ6)),"","952") | PM6: =if(ISERROR(SEARCH("Personal Care Services",GZ6)),"","951") | PN6: =if(ISERROR(SEARCH("Religious Services",GZ6)),"","954") | PO6: =if(ISERROR(SEARCH("Other Personal Services",GZ6)),"","953") | PP6: =if(ISERROR(SEARCH("Private Households Employing Staff and Undifferentiated Goods- and Service-Producing Activities of Households for Own Use",GY6)),"","960") | PQ6: =if(ISERROR(SEARCH("Automotive Repair and Maintenance",HE6)),"","941") | PR6: =if(ISERROR(SEARCH("Machinery and Equipment Repair and Maintenance",HE6)),"","942") | PS6: =if(ISERROR(SEARCH("Other Repair and Maintenance",HE6)),"","949")
HI7: =if(ISERROR(SEARCH("Accommodation",F7)),"","440") | HJ7: =if(ISERROR(SEARCH("Cafes, Restaurants and Takeaway Food Services",G7)),"","450") | HK7: =if(ISERROR(SEARCH("Clubs (Hospitality)",G7)),"","453") | HL7: =if(ISERROR(SEARCH("Pubs, Taverns and Bars",G7)),"","452") | HM7: =if(ISERROR(SEARCH("Employment Services",J7)),"","721") | HN7: =if(ISERROR(SEARCH("Travel Agency and Tour Arrangement Services",J7)),"","722") | HO7: =if(ISERROR(SEARCH("Other Administrative Services",J7)),"","729") | HP7: =if(ISERROR(SEARCH("Building Cleaning, Pest Control and Gardening Servicess",M7)),"","731") | HQ7: =if(ISERROR(SEARCH("Packaging Services",M7)),"","732") | HR7: =if(ISERROR(SEARCH("Dairy Cattle Farming",P7)),"","016") | HS7: =if(ISERROR(SEARCH("Deer Farming",P7)),"","018") | HT7: =if(ISERROR(SEARCH("Fruit and Tree Nut Growing",P7)),"","013") | HU7: =if(ISERROR(SEARCH("Mushroom and Vegetable Growing",P7)),"","012") | HV7: =if(ISERROR(SEARCH("Nursery and Floriculture Production",P7)),"","011") | HW7: =if(ISERROR(SEARCH("Poultry Farming",P7)),"","017") | HX7: =if(ISERROR(SEARCH("Sheep, Beef Cattle and Grain Farming",P7)),"","014") | HY7: =if(ISERROR(SEARCH("Other Crop Growing",P7)),"","015") | HZ7: =if(ISERROR(SEARCH("Other Livestock Farming",P7)),"","019") | IA7: =if(ISERROR(SEARCH("Agriculture and Fishing Support Services",X7)),"","052") | IB7: =if(ISERROR(SEARCH("Forestry Support Services",X7)),"","051") | IC7: =if(ISERROR(SEARCH("Aquaculture",Z7)),"","020") | ID7: =if(ISERROR(SEARCH("Fishing",AA7)),"","041") | IE7: =if(ISERROR(SEARCH("Hunting and Trapping",AA7)),"","042") | IF7: =if(ISERROR(SEARCH("Forestry and Logging",AB7)),"","030") | IG7: =if(ISERROR(SEARCH("Creative and Performing Arts Activities",AD7)),"","900") | IH7: =if(ISERROR(SEARCH("Gambling Activities",AD7)),"","920") | II7: =if(ISERROR(SEARCH("Museum Operation",AG7)),"","891") | IJ7: =if(ISERROR(SEARCH("Parks and Gardens Operations",AG7)),"","892") | IK7: =if(ISERROR(SEARCH("Amusement and Other Recreation Activities",AI7)),"","913") | IL7: =if(ISERROR(SEARCH("Horse and Dog Racing Activities",AI7)),"","912") | IM7: =if(ISERROR(SEARCH("Sports and Physical Recreation Activities",AI7)),"","911") | IN7: =if(ISERROR(SEARCH("Residential Building Construction",AN7)),"","301") | IO7: =if(ISERROR(SEARCH("Non-Residential Building Construction",AN7)),"","302") | IP7: =if(ISERROR(SEARCH("Building Completion Services",AP7)),"","324") | IQ7: =if(ISERROR(SEARCH("Building Installation Servicess",AP7)),"","323") | IR7: =if(ISERROR(SEARCH("Building Structure Services",AP7)),"","322") | IS7: =if(ISERROR(SEARCH("Land Development and Site Preparation Services",AP7)),"","321") | IT7: =if(ISERROR(SEARCH("Other Construction Services",AP7)),"","329") | IU7: =if(ISERROR(SEARCH("Road and Bridge Construction",AV7)),"","310") | IV7: =if(ISERROR(SEARCH("Other Heavy and Civil Engineering Construction",AV7)),"","310") | IW7: =if(ISERROR(SEARCH("Adult, Community and Other Education",AX7)),"","821") | IX7: =if(ISERROR(SEARCH("Educational Support Services",AX7)),"","822") | IY7: =if(ISERROR(SEARCH("Preschool Education",AZ7)),"","801") | IZ7: =if(ISERROR(SEARCH("School Education",AZ7)),"","802") | JA7: =if(ISERROR(SEARCH("Higher Education",BB7)),"","810") | JB7: =if(ISERROR(SEARCH("Higher Education",BC7)),"","810") | JC7: =if(ISERROR(SEARCH("Electricity Distribution",BC7)),"","263") | JD7: =if(ISERROR(SEARCH("Electricity Generation",BC7)),"","261") | JE7: =if(ISERROR(SEARCH("Electricity Transmission",BC7)),"","262") | JF7: =if(ISERROR(SEARCH("On Selling Electricity and Electricity Market Operation",BC7)),"","264") | JG7: =if(ISERROR(SEARCH("Gas Supply",BC7)),"","270") | JH7: =if(ISERROR(SEARCH("Waste Collection Services",BF7)),"","291") | JI7: =if(ISERROR(SEARCH("Waste Treatment, Disposal and Remediation Services",BF7)),"","292") | JJ7: =if(ISERROR(SEARCH("Sewerage and Drainage Services",BI7)),"","281") | JK7: =if(ISERROR(SEARCH("Water Supply",BI7)),"","281") | JL7: =if(ISERROR(SEARCH("Auxiliary Finance and Investment Services",BK7)),"","641") | JM7: =if(ISERROR(SEARCH("Auxiliary Insurance Services",BK7)),"","642") | JN7: =if(ISERROR(SEARCH("Central Banking",BM7)),"","621") | JO7: =if(ISERROR(SEARCH("Depository Financial Intermediation",BM7)),"","622") | JP7: =if(ISERROR(SEARCH("Financial Asset Investing",BM7)),"","624") | JQ7: =if(ISERROR(SEARCH("Non-Depository Financing",BM7)),"","623") | JR7: =if(ISERROR(SEARCH("Health and General Insurance",BO7)),"","632") | JS7: =if(ISERROR(SEARCH("Life Insurance",BO7)),"","631") | JT7: =if(ISERROR(SEARCH("Superannuation Funds",BO7)),"","633") | JU7: =if(ISERROR(SEARCH("Hospitals",BQ7)),"","840") | JV7: =if(ISERROR(SEARCH("Medical Services",BS7)),"","851") | JW7: =if(ISERROR(SEARCH("Pathology and Diagnostic Imaging Services",BS7)),"","852") | JX7: =if(ISERROR(SEARCH("Allied Health Services",BS7)),"","853") | JY7: =if(ISERROR(SEARCH("Other Health Care Services",BS7)),"","859") | JZ7: =if(ISERROR(SEARCH("Aged Care Residential Services",BW7)),"","860") | KA7: =if(ISERROR(SEARCH("Other Residential Care Services",BW7)),"","860") | KB7: =if(ISERROR(SEARCH("Child Care Services",BX7)),"","871") | KC7: =if(ISERROR(SEARCH("Other Social Assistance Services",BX7)),"","879") | KD7: =if(ISERROR(SEARCH("Radio Broadcasting",BZ7)),"","561") | KE7: =if(ISERROR(SEARCH("Television Broadcasting",BZ7)),"","562") | KF7: =if(ISERROR(SEARCH("Internet Publishing and Broadcasting",BY7)),"","570") | KG7: =if(ISERROR(SEARCH("Data Processing, Web Hosting and Electronic Information Storage Services",CB7)),"","592") | KH7: =if(ISERROR(SEARCH("Internet Service Providers and Web Search Portals",CB7)),"","591") | KI7: =if(ISERROR(SEARCH("Libraries and Archives",CD7)),"","601") | KJ7: =if(ISERROR(SEARCH("Other Information Services",CD7)),"","602") | KK7: =if(ISERROR(SEARCH("Motion Picture and Video Activities",CE7)),"","551") | KL7: =if(ISERROR(SEARCH("Sound Recording and Music Publishing",CE7)),"","552") | KM7: =if(ISERROR(SEARCH("Newspaper, Periodical, Book and Directory Publishing",CH7)),"","541") | KN7: =if(ISERROR(SEARCH("Software Publishing",CH7)),"","542") | KO7: =if(ISERROR(SEARCH("Telecommunications Services",BY7)),"","580") | KP7: =if(ISERROR(SEARCH("Basic Chemical Manufacturing",CK7)),"","181") | KQ7: =if(ISERROR(SEARCH("Basic Polymer Manufacturing",CK7)),"","182") | KR7: =if(ISERROR(SEARCH("Cleaning Compound and Toiletry Preparation Manufacturing",CK7)),"","185") | KS7: =if(ISERROR(SEARCH("Fertiliser and Pesticide Manufacturing",CK7)),"","183") | KT7: =if(ISERROR(SEARCH("Pharmaceutical and Medicinal Product Manufacturing",CK7)),"","184") | KU7: =if(ISERROR(SEARCH("Other Basic Chemical Product Manufacturing",CK7)),"","189") | KV7: =if(ISERROR(SEARCH("Beverage Manufacturing",CR7)),"","121") | KW7: =if(ISERROR(SEARCH("Cigarette and Tobacco Product Manufacturing",CR7)),"","122") | KX7: =if(ISERROR(SEARCH("Iron and Steel Forging",CT7)),"","221") | KY7: =if(ISERROR(SEARCH("Metal Container Manufacturing",CT7)),"","223") | KZ7: =if(ISERROR(SEARCH("Sheet Metal Product Manufacturing (except Metal Structural and Container Products)",CT7)),"","224") | LA7: =if(ISERROR(SEARCH("Structural Metal Product Manufacturing",CT7)),"","222") | LB7: =if(ISERROR(SEARCH("Other Fabricated Metal Product Manufacturing",CT7)),"","229") | LC7: =if(ISERROR(SEARCH("Bakery Product Manufacturing",CX7)),"","117") | LD7: =if(ISERROR(SEARCH("Dairy Product Manufacturing",CX7)),"","113") | LE7: =if(ISERROR(SEARCH("Fruit and Vegetable Processing",CX7)),"","114") | LF7: =if(ISERROR(SEARCH("Grain Mill and Cereal Product Manufacturing",CX7)),"","116") | LG7: =if(ISERROR(SEARCH("Meat and Meat Product Manufacturing",CX7)),"","111") | LH7: =if(ISERROR(SEARCH("Oil and Fat Manufacturing",CX7)),"","115") | LI7: =if(ISERROR(SEARCH("Seafood Processing",CX7)),"","112") | LJ7: =if(ISERROR(SEARCH("Sugar and Confectionery Manufacturing",CX7)),"","118") | LK7: =if(ISERROR(SEARCH("Other Food Product Manufacturing",CX7)),"","119") | LL7: =if(ISERROR(SEARCH("Furniture Manufacturing",DE7)),"","251") | LM7: =if(ISERROR(SEARCH("Other Manufacturing",DE7)),"","259") | LN7: =if(ISERROR(SEARCH("Computer and Electronic Equipment Manufacturing",DH7)),"","242") | LO7: =if(ISERROR(SEARCH("Domestic Appliance Manufacturing",DH7)),"","244") | LP7: =if(ISERROR(SEARCH("Electrical Equipment Manufacturing",DH7)),"","243") | LQ7: =if(ISERROR(SEARCH("Professional and Scientific Equipment Manufacturing",DH7)),"","241") | LR7: =if(ISERROR(SEARCH("Pump, Compressor, Heating and Ventilation Equipment Manufacturing",DH7)),"","245") | LS7: =if(ISERROR(SEARCH("Specialised Machinery and Equipment Manufacturing",DH7)),"","246") | LT7: =if(ISERROR(SEARCH("Other Machinery and Equipment Manufacturing",DH7)),"","249") | LU7: =if(ISERROR(SEARCH("Cement, Lime, Plaster and Concrete Product Manufacturing",DP7)),"","203") | LV7: =if(ISERROR(SEARCH("Ceramic Product Manufacturing",DP7)),"","202") | LW7: =if(ISERROR(SEARCH("Glass and Glass Product Manufacturing",DP7)),"","201") | LX7: =if(ISERROR(SEARCH("Other Non-Metallic Mineral Product Manufacturing",DP7)),"","209") | LY7: =if(ISERROR(SEARCH("Petroleum Refining and Petroleum Fuel Manufacturing",DS7)),"","170") | LZ7: =if(ISERROR(SEARCH("Other Petroleum and Coal Product Manufacturing",DS7)),"","170") | MA7: =if(ISERROR(SEARCH("Natural Rubber Product Manufacturing",DT7)),"","192") | MB7: =if(ISERROR(SEARCH("Polymer Product Manufacturing",DT7)),"","191") | MC7: =if(ISERROR(SEARCH("Basic Ferrous Metal Manufacturing",DV7)),"","211") | MD7: =if(ISERROR(SEARCH("Basic Ferrous Metal Product Manufacturing",DV7)),"","212") | ME7: =if(ISERROR(SEARCH("Basic Non-Ferrous Metal Manufacturing",DV7)),"","213") | MF7: =if(ISERROR(SEARCH("Basic Non-Ferrous Metal Product Manufacturing",DV7)),"","214") | MG7: =if(ISERROR(SEARCH("Printing and Printing Support Services",EA7)),"","161") | MH7: =if(ISERROR(SEARCH("Reproduction of Recorded Media",EA7)),"","162") | MI7: =if(ISERROR(SEARCH("Converted Paper Product Manufacturing",EC7)),"","152") | MJ7: =if(ISERROR(SEARCH("Pulp, Paper and Paperboard Manufacturing",EC7)),"","151") | MK7: =if(ISERROR(SEARCH("Clothing and Footwear Manufacturing",EE7)),"","135") | ML7: =if(ISERROR(SEARCH("Knitted Product Manufacturing",EE7)),"","134") | MM7: =if(ISERROR(SEARCH("Leather Tanning, Fur Dressing and Leather Product Manufacturing",EE7)),"","132") | MN7: =if(ISERROR(SEARCH("Textile Manufacturing",EE7)),"","131") | MO7: =if(ISERROR(SEARCH("Textile Product Manufacturing",EE7)),"","133") | MP7: =if(ISERROR(SEARCH("Motor Vehicle and Motor Vehicle Part Manufacturing",EI7)),"","231") | MQ7: =if(ISERROR(SEARCH("Other Transport Equipment Manufacturing",EI7)),"","239") | MR7: =if(ISERROR(SEARCH("Log Sawmilling and Timber Dressing",EL7)),"","141") | MS7: =if(ISERROR(SEARCH("Other Wood Product Manufacturing",EL7)),"","149") | MT7: =if(ISERROR(SEARCH("Coal Mining",EO7)),"","060") | MU7: =if(ISERROR(SEARCH("Exploration",EP7)),"","101") | MV7: =if(ISERROR(SEARCH("Other Mining Support Services",EP7)),"","109") | MW7: =if(ISERROR(SEARCH("Metal Ore Mining",EO7)),"","080") | MX7: =if(ISERROR(SEARCH("Construction Material Mining",ES7)),"","091") | MY7: =if(ISERROR(SEARCH("Oil and Gas Extraction",EO7)),"","070") | MZ7: =if(ISERROR(SEARCH("Other Non-Metallic Mineral Mining and Quarrying",ES7)),"","099") | NA7: =if(ISERROR(SEARCH("Computer System Design and Related Services",EU7)),"","700") | NB7: =if(ISERROR(SEARCH("Advertising Services",EV7)),"","694") | NC7: =if(ISERROR(SEARCH("Architectural, Engineering and Technical Services",EV7)),"","692") | ND7: =if(ISERROR(SEARCH("Legal and Accounting Services",EV7)),"","693") | NE7: =if(ISERROR(SEARCH("Management and Related Consulting Services",EV7)),"","696") | NF7: =if(ISERROR(SEARCH("Market Research and Statistical Services",EV7)),"","695") | NG7: =if(ISERROR(SEARCH("Scientific Research Services",EV7)),"","691") | NH7: =if(ISERROR(SEARCH("Veterinary Services",EV7)),"","697") | NI7: =if(ISERROR(SEARCH("Other Professional, Scientific and Technical Services",EV7)),"","699") | NJ7: =if(ISERROR(SEARCH("Central Government Administration",FB7)),"","751") | NK7: =if(ISERROR(SEARCH("State Government Administration",FB7)),"","752") | NL7: =if(ISERROR(SEARCH("Local Government Administration",FB7)),"","753") | NM7: =if(ISERROR(SEARCH("Justice",FB7)),"","754") | NN7: =if(ISERROR(SEARCH("Government Representation",FB7)),"","755") | NO7: =if(ISERROR(SEARCH("Defence",FA7)),"","760") | NP7: =if(ISERROR(SEARCH("Public Order and Safety Services",FD7)),"","771") | NQ7: =if(ISERROR(SEARCH("Regulatory Services",FD7)),"","772") | NR7: =if(ISERROR(SEARCH("Property Operators",FG7)),"","671") | NS7: =if(ISERROR(SEARCH("Real Estate Services",FG7)),"","672") | NT7: =if(ISERROR(SEARCH("Farm Animal and Bloodstock Leasing",FI7)),"","662") | NU7: =if(ISERROR(SEARCH("Motor Vehicle and Transport Equipment Rental and Hiring",FI7)),"","661") | NV7: =if(ISERROR(SEARCH("Non-Financial Intangible Assets (Except Copyrights) Leasing",FI7)),"","664") | NW7: =if(ISERROR(SEARCH("Other Goods and Equipment Rental and Hiring",FI7)),"","663") | NX7: =if(ISERROR(SEARCH("Supermarket and Grocery Stores",FM7)),"","411") | NY7: =if(ISERROR(SEARCH("Specialised Food Retailing",FM7)),"","412") | NZ7: =if(ISERROR(SEARCH("Fuel Retailing",FL7)),"","400") | OA7: =if(ISERROR(SEARCH("Motor Vehicle Parts and Tyre Retailing",FO7)),"","392") | OB7: =if(ISERROR(SEARCH("Motor Vehicle Retailing",FO7)),"","391") | OC7: =if(ISERROR(SEARCH("Non-Store Retailing",FR7)),"","431") | OD7: =if(ISERROR(SEARCH("Retail Commission-Based Buying and/or Selling",FR7)),"","432") | OE7: =if(ISERROR(SEARCH("Clothing, Footwear and Personal Accessory Retailing",FS7)),"","425") | OF7: =if(ISERROR(SEARCH("Department Stores",FS7)),"","426") | OG7: =if(ISERROR(SEARCH("Electrical and Electronic Goods Retailing",FS7)),"","422") | OH7: =if(ISERROR(SEARCH("Furniture, Floor Coverings, Houseware and Textile Goods Retailing",FS7)),"","421") | OI7: =if(ISERROR(SEARCH("Hardware, Building and Garden Supplies Retailing",FS7)),"","423") | OJ7: =if(ISERROR(SEARCH("Pharmaceutical and Other Store-Based Retailing",FS7)),"","427") | OK7: =if(ISERROR(SEARCH("Recreational Goods Retailing",FS7)),"","424") | OL7: =if(ISERROR(SEARCH("Air and Space Transport",FZ7)),"","490") | OM7: =if(ISERROR(SEARCH("Postal and Courier Pick-up and Delivery Services",FZ7)),"","510") | ON7: =if(ISERROR(SEARCH("Rail Freight Transport",GB7)),"","471") | OO7: =if(ISERROR(SEARCH("Rail Passenger Transport",GB7)),"","472") | OP7: =if(ISERROR(SEARCH("Road Freight Transport",GC7)),"","461") | OQ7: =if(ISERROR(SEARCH("Road Passenger Transport",GC7)),"","462") | OR7: =if(ISERROR(SEARCH("Airport Operations and Other Air Transport Support Services",GE7)),"","522") | OS7: =if(ISERROR(SEARCH("Water Transport Support Services",GE7)),"","521") | OT7: =if(ISERROR(SEARCH("Other Transport Support Services",GE7)),"","529") | OU7: =if(ISERROR(SEARCH("Warehousing and Storage Services",FZ7)),"","530") | OV7: =if(ISERROR(SEARCH("Water Freight Transport",GI7)),"","481") | OW7: =if(ISERROR(SEARCH("Water Freight Transport",GI7)),"","482") | OX7: =if(ISERROR(SEARCH("Pipeline and Other Transport",GJ7)),"","502") | OY7: =if(ISERROR(SEARCH("Scenic and Sightseeing Transport",GJ7)),"","501") | OZ7: =if(ISERROR(SEARCH("Agricultural Product Wholesaling",GM7)),"","331") | PA7: =if(ISERROR(SEARCH("Mineral, Metal and Chemical Wholesaling",GM7)),"","332") | PB7: =if(ISERROR(SEARCH("Timber and Hardware Goods Wholesaling",GM7)),"","333") | PC7: =if(ISERROR(SEARCH("Commission-Based Wholesaling",GL7)),"","380") | PD7: =if(ISERROR(SEARCH("Grocery, Liquor and Tobacco Product Wholesaling",GL7)),"","360") | PE7: =if(ISERROR(SEARCH("Specialised Industrial Machinery and Equipment Wholesaling",GR7)),"","341") | PF7: =if(ISERROR(SEARCH("Other Machinery and Equipment Wholesaling",GR7)),"","349") | PG7: =if(ISERROR(SEARCH("Motor Vehicle and Motor Vehicle Parts Wholesaling",GL7)),"","350") | PH7: =if(ISERROR(SEARCH("Textile, Clothing and Footwear Wholesaling",GV7)),"","371") | PI7: =if(ISERROR(SEARCH("Furniture, Floor Covering and Other Goods Wholesaling",GV7)),"","373") | PJ7: =if(ISERROR(SEARCH("Pharmaceutical and Toiletry Goods Wholesaling",GV7)),"","372") | PK7: =if(ISERROR(SEARCH("Civic, Professional and Other Interest Group Services",GZ7)),"","955") | PL7: =if(ISERROR(SEARCH("Funeral, Crematorium and Cemetery Services",GZ7)),"","952") | PM7: =if(ISERROR(SEARCH("Personal Care Services",GZ7)),"","951") | PN7: =if(ISERROR(SEARCH("Religious Services",GZ7)),"","954") | PO7: =if(ISERROR(SEARCH("Other Personal Services",GZ7)),"","953") | PP7: =if(ISERROR(SEARCH("Private Households Employing Staff and Undifferentiated Goods- and Service-Producing Activities of Households for Own Use",GY7)),"","960") | PQ7: =if(ISERROR(SEARCH("Automotive Repair and Maintenance",HE7)),"","941") | PR7: =if(ISERROR(SEARCH("Machinery and Equipment Repair and Maintenance",HE7)),"","942") | PS7: =if(ISERROR(SEARCH("Other Repair and Maintenance",HE7)),"","949")
HI8: =if(ISERROR(SEARCH("Accommodation",F8)),"","440") | HJ8: =if(ISERROR(SEARCH("Cafes, Restaurants and Takeaway Food Services",G8)),"","450") | HK8: =if(ISERROR(SEARCH("Clubs (Hospitality)",G8)),"","453") | HL8: =if(ISERROR(SEARCH("Pubs, Taverns and Bars",G8)),"","452") | HM8: =if(ISERROR(SEARCH("Employment Services",J8)),"","721") | HN8: =if(ISERROR(SEARCH("Travel Agency and Tour Arrangement Services",J8)),"","722") | HO8: =if(ISERROR(SEARCH("Other Administrative Services",J8)),"","729") | HP8: =if(ISERROR(SEARCH("Building Cleaning, Pest Control and Gardening Servicess",M8)),"","731") | HQ8: =if(ISERROR(SEARCH("Packaging Services",M8)),"","732") | HR8: =if(ISERROR(SEARCH("Dairy Cattle Farming",P8)),"","016") | HS8: =if(ISERROR(SEARCH("Deer Farming",P8)),"","018") | HT8: =if(ISERROR(SEARCH("Fruit and Tree Nut Growing",P8)),"","013") | HU8: =if(ISERROR(SEARCH("Mushroom and Vegetable Growing",P8)),"","012") | HV8: =if(ISERROR(SEARCH("Nursery and Floriculture Production",P8)),"","011") | HW8: =if(ISERROR(SEARCH("Poultry Farming",P8)),"","017") | HX8: =if(ISERROR(SEARCH("Sheep, Beef Cattle and Grain Farming",P8)),"","014") | HY8: =if(ISERROR(SEARCH("Other Crop Growing",P8)),"","015") | HZ8: =if(ISERROR(SEARCH("Other Livestock Farming",P8)),"","019") | IA8: =if(ISERROR(SEARCH("Agriculture and Fishing Support Services",X8)),"","052") | IB8: =if(ISERROR(SEARCH("Forestry Support Services",X8)),"","051") | IC8: =if(ISERROR(SEARCH("Aquaculture",Z8)),"","020") | ID8: =if(ISERROR(SEARCH("Fishing",AA8)),"","041") | IE8: =if(ISERROR(SEARCH("Hunting and Trapping",AA8)),"","042") | IF8: =if(ISERROR(SEARCH("Forestry and Logging",AB8)),"","030") | IG8: =if(ISERROR(SEARCH("Creative and Performing Arts Activities",AD8)),"","900") | IH8: =if(ISERROR(SEARCH("Gambling Activities",AD8)),"","920") | II8: =if(ISERROR(SEARCH("Museum Operation",AG8)),"","891") | IJ8: =if(ISERROR(SEARCH("Parks and Gardens Operations",AG8)),"","892") | IK8: =if(ISERROR(SEARCH("Amusement and Other Recreation Activities",AI8)),"","913") | IL8: =if(ISERROR(SEARCH("Horse and Dog Racing Activities",AI8)),"","912") | IM8: =if(ISERROR(SEARCH("Sports and Physical Recreation Activities",AI8)),"","911") | IN8: =if(ISERROR(SEARCH("Residential Building Construction",AN8)),"","301") | IO8: =if(ISERROR(SEARCH("Non-Residential Building Construction",AN8)),"","302") | IP8: =if(ISERROR(SEARCH("Building Completion Services",AP8)),"","324") | IQ8: =if(ISERROR(SEARCH("Building Installation Servicess",AP8)),"","323") | IR8: =if(ISERROR(SEARCH("Building Structure Services",AP8)),"","322") | IS8: =if(ISERROR(SEARCH("Land Development and Site Preparation Services",AP8)),"","321") | IT8: =if(ISERROR(SEARCH("Other Construction Services",AP8)),"","329") | IU8: =if(ISERROR(SEARCH("Road and Bridge Construction",AV8)),"","310") | IV8: =if(ISERROR(SEARCH("Other Heavy and Civil Engineering Construction",AV8)),"","310") | IW8: =if(ISERROR(SEARCH("Adult, Community and Other Education",AX8)),"","821") | IX8: =if(ISERROR(SEARCH("Educational Support Services",AX8)),"","822") | IY8: =if(ISERROR(SEARCH("Preschool Education",AZ8)),"","801") | IZ8: =if(ISERROR(SEARCH("School Education",AZ8)),"","802") | JA8: =if(ISERROR(SEARCH("Higher Education",BB8)),"","810") | JB8: =if(ISERROR(SEARCH("Higher Education",BC8)),"","810") | JC8: =if(ISERROR(SEARCH("Electricity Distribution",BC8)),"","263") | JD8: =if(ISERROR(SEARCH("Electricity Generation",BC8)),"","261") | JE8: =if(ISERROR(SEARCH("Electricity Transmission",BC8)),"","262") | JF8: =if(ISERROR(SEARCH("On Selling Electricity and Electricity Market Operation",BC8)),"","264") | JG8: =if(ISERROR(SEARCH("Gas Supply",BC8)),"","270") | JH8: =if(ISERROR(SEARCH("Waste Collection Services",BF8)),"","291") | JI8: =if(ISERROR(SEARCH("Waste Treatment, Disposal and Remediation Services",BF8)),"","292") | JJ8: =if(ISERROR(SEARCH("Sewerage and Drainage Services",BI8)),"","281") | JK8: =if(ISERROR(SEARCH("Water Supply",BI8)),"","281") | JL8: =if(ISERROR(SEARCH("Auxiliary Finance and Investment Services",BK8)),"","641") | JM8: =if(ISERROR(SEARCH("Auxiliary Insurance Services",BK8)),"","642") | JN8: =if(ISERROR(SEARCH("Central Banking",BM8)),"","621") | JO8: =if(ISERROR(SEARCH("Depository Financial Intermediation",BM8)),"","622") | JP8: =if(ISERROR(SEARCH("Financial Asset Investing",BM8)),"","624") | JQ8: =if(ISERROR(SEARCH("Non-Depository Financing",BM8)),"","623") | JR8: =if(ISERROR(SEARCH("Health and General Insurance",BO8)),"","632") | JS8: =if(ISERROR(SEARCH("Life Insurance",BO8)),"","631") | JT8: =if(ISERROR(SEARCH("Superannuation Funds",BO8)),"","633") | JU8: =if(ISERROR(SEARCH("Hospitals",BQ8)),"","840") | JV8: =if(ISERROR(SEARCH("Medical Services",BS8)),"","851") | JW8: =if(ISERROR(SEARCH("Pathology and Diagnostic Imaging Services",BS8)),"","852") | JX8: =if(ISERROR(SEARCH("Allied Health Services",BS8)),"","853") | JY8: =if(ISERROR(SEARCH("Other Health Care Services",BS8)),"","859") | JZ8: =if(ISERROR(SEARCH("Aged Care Residential Services",BW8)),"","860") | KA8: =if(ISERROR(SEARCH("Other Residential Care Services",BW8)),"","860") | KB8: =if(ISERROR(SEARCH("Child Care Services",BX8)),"","871") | KC8: =if(ISERROR(SEARCH("Other Social Assistance Services",BX8)),"","879") | KD8: =if(ISERROR(SEARCH("Radio Broadcasting",BZ8)),"","561") | KE8: =if(ISERROR(SEARCH("Television Broadcasting",BZ8)),"","562") | KF8: =if(ISERROR(SEARCH("Internet Publishing and Broadcasting",BY8)),"","570") | KG8: =if(ISERROR(SEARCH("Data Processing, Web Hosting and Electronic Information Storage Services",CB8)),"","592") | KH8: =if(ISERROR(SEARCH("Internet Service Providers and Web Search Portals",CB8)),"","591") | KI8: =if(ISERROR(SEARCH("Libraries and Archives",CD8)),"","601") | KJ8: =if(ISERROR(SEARCH("Other Information Services",CD8)),"","602") | KK8: =if(ISERROR(SEARCH("Motion Picture and Video Activities",CE8)),"","551") | KL8: =if(ISERROR(SEARCH("Sound Recording and Music Publishing",CE8)),"","552") | KM8: =if(ISERROR(SEARCH("Newspaper, Periodical, Book and Directory Publishing",CH8)),"","541") | KN8: =if(ISERROR(SEARCH("Software Publishing",CH8)),"","542") | KO8: =if(ISERROR(SEARCH("Telecommunications Services",BY8)),"","580") | KP8: =if(ISERROR(SEARCH("Basic Chemical Manufacturing",CK8)),"","181") | KQ8: =if(ISERROR(SEARCH("Basic Polymer Manufacturing",CK8)),"","182") | KR8: =if(ISERROR(SEARCH("Cleaning Compound and Toiletry Preparation Manufacturing",CK8)),"","185") | KS8: =if(ISERROR(SEARCH("Fertiliser and Pesticide Manufacturing",CK8)),"","183") | KT8: =if(ISERROR(SEARCH("Pharmaceutical and Medicinal Product Manufacturing",CK8)),"","184") | KU8: =if(ISERROR(SEARCH("Other Basic Chemical Product Manufacturing",CK8)),"","189") | KV8: =if(ISERROR(SEARCH("Beverage Manufacturing",CR8)),"","121") | KW8: =if(ISERROR(SEARCH("Cigarette and Tobacco Product Manufacturing",CR8)),"","122") | KX8: =if(ISERROR(SEARCH("Iron and Steel Forging",CT8)),"","221") | KY8: =if(ISERROR(SEARCH("Metal Container Manufacturing",CT8)),"","223") | KZ8: =if(ISERROR(SEARCH("Sheet Metal Product Manufacturing (except Metal Structural and Container Products)",CT8)),"","224") | LA8: =if(ISERROR(SEARCH("Structural Metal Product Manufacturing",CT8)),"","222") | LB8: =if(ISERROR(SEARCH("Other Fabricated Metal Product Manufacturing",CT8)),"","229") | LC8: =if(ISERROR(SEARCH("Bakery Product Manufacturing",CX8)),"","117") | LD8: =if(ISERROR(SEARCH("Dairy Product Manufacturing",CX8)),"","113") | LE8: =if(ISERROR(SEARCH("Fruit and Vegetable Processing",CX8)),"","114") | LF8: =if(ISERROR(SEARCH("Grain Mill and Cereal Product Manufacturing",CX8)),"","116") | LG8: =if(ISERROR(SEARCH("Meat and Meat Product Manufacturing",CX8)),"","111") | LH8: =if(ISERROR(SEARCH("Oil and Fat Manufacturing",CX8)),"","115") | LI8: =if(ISERROR(SEARCH("Seafood Processing",CX8)),"","112") | LJ8: =if(ISERROR(SEARCH("Sugar and Confectionery Manufacturing",CX8)),"","118") | LK8: =if(ISERROR(SEARCH("Other Food Product Manufacturing",CX8)),"","119") | LL8: =if(ISERROR(SEARCH("Furniture Manufacturing",DE8)),"","251") | LM8: =if(ISERROR(SEARCH("Other Manufacturing",DE8)),"","259") | LN8: =if(ISERROR(SEARCH("Computer and Electronic Equipment Manufacturing",DH8)),"","242") | LO8: =if(ISERROR(SEARCH("Domestic Appliance Manufacturing",DH8)),"","244") | LP8: =if(ISERROR(SEARCH("Electrical Equipment Manufacturing",DH8)),"","243") | LQ8: =if(ISERROR(SEARCH("Professional and Scientific Equipment Manufacturing",DH8)),"","241") | LR8: =if(ISERROR(SEARCH("Pump, Compressor, Heating and Ventilation Equipment Manufacturing",DH8)),"","245") | LS8: =if(ISERROR(SEARCH("Specialised Machinery and Equipment Manufacturing",DH8)),"","246") | LT8: =if(ISERROR(SEARCH("Other Machinery and Equipment Manufacturing",DH8)),"","249") | LU8: =if(ISERROR(SEARCH("Cement, Lime, Plaster and Concrete Product Manufacturing",DP8)),"","203") | LV8: =if(ISERROR(SEARCH("Ceramic Product Manufacturing",DP8)),"","202") | LW8: =if(ISERROR(SEARCH("Glass and Glass Product Manufacturing",DP8)),"","201") | LX8: =if(ISERROR(SEARCH("Other Non-Metallic Mineral Product Manufacturing",DP8)),"","209") | LY8: =if(ISERROR(SEARCH("Petroleum Refining and Petroleum Fuel Manufacturing",DS8)),"","170") | LZ8: =if(ISERROR(SEARCH("Other Petroleum and Coal Product Manufacturing",DS8)),"","170") | MA8: =if(ISERROR(SEARCH("Natural Rubber Product Manufacturing",DT8)),"","192") | MB8: =if(ISERROR(SEARCH("Polymer Product Manufacturing",DT8)),"","191") | MC8: =if(ISERROR(SEARCH("Basic Ferrous Metal Manufacturing",DV8)),"","211") | MD8: =if(ISERROR(SEARCH("Basic Ferrous Metal Product Manufacturing",DV8)),"","212") | ME8: =if(ISERROR(SEARCH("Basic Non-Ferrous Metal Manufacturing",DV8)),"","213") | MF8: =if(ISERROR(SEARCH("Basic Non-Ferrous Metal Product Manufacturing",DV8)),"","214") | MG8: =if(ISERROR(SEARCH("Printing and Printing Support Services",EA8)),"","161") | MH8: =if(ISERROR(SEARCH("Reproduction of Recorded Media",EA8)),"","162") | MI8: =if(ISERROR(SEARCH("Converted Paper Product Manufacturing",EC8)),"","152") | MJ8: =if(ISERROR(SEARCH("Pulp, Paper and Paperboard Manufacturing",EC8)),"","151") | MK8: =if(ISERROR(SEARCH("Clothing and Footwear Manufacturing",EE8)),"","135") | ML8: =if(ISERROR(SEARCH("Knitted Product Manufacturing",EE8)),"","134") | MM8: =if(ISERROR(SEARCH("Leather Tanning, Fur Dressing and Leather Product Manufacturing",EE8)),"","132") | MN8: =if(ISERROR(SEARCH("Textile Manufacturing",EE8)),"","131") | MO8: =if(ISERROR(SEARCH("Textile Product Manufacturing",EE8)),"","133") | MP8: =if(ISERROR(SEARCH("Motor Vehicle and Motor Vehicle Part Manufacturing",EI8)),"","231") | MQ8: =if(ISERROR(SEARCH("Other Transport Equipment Manufacturing",EI8)),"","239") | MR8: =if(ISERROR(SEARCH("Log Sawmilling and Timber Dressing",EL8)),"","141") | MS8: =if(ISERROR(SEARCH("Other Wood Product Manufacturing",EL8)),"","149") | MT8: =if(ISERROR(SEARCH("Coal Mining",EO8)),"","060") | MU8: =if(ISERROR(SEARCH("Exploration",EP8)),"","101") | MV8: =if(ISERROR(SEARCH("Other Mining Support Services",EP8)),"","109") | MW8: =if(ISERROR(SEARCH("Metal Ore Mining",EO8)),"","080") | MX8: =if(ISERROR(SEARCH("Construction Material Mining",ES8)),"","091") | MY8: =if(ISERROR(SEARCH("Oil and Gas Extraction",EO8)),"","070") | MZ8: =if(ISERROR(SEARCH("Other Non-Metallic Mineral Mining and Quarrying",ES8)),"","099") | NA8: =if(ISERROR(SEARCH("Computer System Design and Related Services",EU8)),"","700") | NB8: =if(ISERROR(SEARCH("Advertising Services",EV8)),"","694") | NC8: =if(ISERROR(SEARCH("Architectural, Engineering and Technical Services",EV8)),"","692") | ND8: =if(ISERROR(SEARCH("Legal and Accounting Services",EV8)),"","693") | NE8: =if(ISERROR(SEARCH("Management and Related Consulting Services",EV8)),"","696") | NF8: =if(ISERROR(SEARCH("Market Research and Statistical Services",EV8)),"","695") | NG8: =if(ISERROR(SEARCH("Scientific Research Services",EV8)),"","691") | NH8: =if(ISERROR(SEARCH("Veterinary Services",EV8)),"","697") | NI8: =if(ISERROR(SEARCH("Other Professional, Scientific and Technical Services",EV8)),"","699") | NJ8: =if(ISERROR(SEARCH("Central Government Administration",FB8)),"","751") | NK8: =if(ISERROR(SEARCH("State Government Administration",FB8)),"","752") | NL8: =if(ISERROR(SEARCH("Local Government Administration",FB8)),"","753") | NM8: =if(ISERROR(SEARCH("Justice",FB8)),"","754") | NN8: =if(ISERROR(SEARCH("Government Representation",FB8)),"","755") | NO8: =if(ISERROR(SEARCH("Defence",FA8)),"","760") | NP8: =if(ISERROR(SEARCH("Public Order and Safety Services",FD8)),"","771") | NQ8: =if(ISERROR(SEARCH("Regulatory Services",FD8)),"","772") | NR8: =if(ISERROR(SEARCH("Property Operators",FG8)),"","671") | NS8: =if(ISERROR(SEARCH("Real Estate Services",FG8)),"","672") | NT8: =if(ISERROR(SEARCH("Farm Animal and Bloodstock Leasing",FI8)),"","662") | NU8: =if(ISERROR(SEARCH("Motor Vehicle and Transport Equipment Rental and Hiring",FI8)),"","661") | NV8: =if(ISERROR(SEARCH("Non-Financial Intangible Assets (Except Copyrights) Leasing",FI8)),"","664") | NW8: =if(ISERROR(SEARCH("Other Goods and Equipment Rental and Hiring",FI8)),"","663") | NX8: =if(ISERROR(SEARCH("Supermarket and Grocery Stores",FM8)),"","411") | NY8: =if(ISERROR(SEARCH("Specialised Food Retailing",FM8)),"","412") | NZ8: =if(ISERROR(SEARCH("Fuel Retailing",FL8)),"","400") | OA8: =if(ISERROR(SEARCH("Motor Vehicle Parts and Tyre Retailing",FO8)),"","392") | OB8: =if(ISERROR(SEARCH("Motor Vehicle Retailing",FO8)),"","391") | OC8: =if(ISERROR(SEARCH("Non-Store Retailing",FR8)),"","431") | OD8: =if(ISERROR(SEARCH("Retail Commission-Based Buying and/or Selling",FR8)),"","432") | OE8: =if(ISERROR(SEARCH("Clothing, Footwear and Personal Accessory Retailing",FS8)),"","425") | OF8: =if(ISERROR(SEARCH("Department Stores",FS8)),"","426") | OG8: =if(ISERROR(SEARCH("Electrical and Electronic Goods Retailing",FS8)),"","422") | OH8: =if(ISERROR(SEARCH("Furniture, Floor Coverings, Houseware and Textile Goods Retailing",FS8)),"","421") | OI8: =if(ISERROR(SEARCH("Hardware, Building and Garden Supplies Retailing",FS8)),"","423") | OJ8: =if(ISERROR(SEARCH("Pharmaceutical and Other Store-Based Retailing",FS8)),"","427") | OK8: =if(ISERROR(SEARCH("Recreational Goods Retailing",FS8)),"","424") | OL8: =if(ISERROR(SEARCH("Air and Space Transport",FZ8)),"","490") | OM8: =if(ISERROR(SEARCH("Postal and Courier Pick-up and Delivery Services",FZ8)),"","510") | ON8: =if(ISERROR(SEARCH("Rail Freight Transport",GB8)),"","471") | OO8: =if(ISERROR(SEARCH("Rail Passenger Transport",GB8)),"","472") | OP8: =if(ISERROR(SEARCH("Road Freight Transport",GC8)),"","461") | OQ8: =if(ISERROR(SEARCH("Road Passenger Transport",GC8)),"","462") | OR8: =if(ISERROR(SEARCH("Airport Operations and Other Air Transport Support Services",GE8)),"","522") | OS8: =if(ISERROR(SEARCH("Water Transport Support Services",GE8)),"","521") | OT8: =if(ISERROR(SEARCH("Other Transport Support Services",GE8)),"","529") | OU8: =if(ISERROR(SEARCH("Warehousing and Storage Services",FZ8)),"","530") | OV8: =if(ISERROR(SEARCH("Water Freight Transport",GI8)),"","481") | OW8: =if(ISERROR(SEARCH("Water Freight Transport",GI8)),"","482") | OX8: =if(ISERROR(SEARCH("Pipeline and Other Transport",GJ8)),"","502") | OY8: =if(ISERROR(SEARCH("Scenic and Sightseeing Transport",GJ8)),"","501") | OZ8: =if(ISERROR(SEARCH("Agricultural Product Wholesaling",GM8)),"","331") | PA8: =if(ISERROR(SEARCH("Mineral, Metal and Chemical Wholesaling",GM8)),"","332") | PB8: =if(ISERROR(SEARCH("Timber and Hardware Goods Wholesaling",GM8)),"","333") | PC8: =if(ISERROR(SEARCH("Commission-Based Wholesaling",GL8)),"","380") | PD8: =if(ISERROR(SEARCH("Grocery, Liquor and Tobacco Product Wholesaling",GL8)),"","360") | PE8: =if(ISERROR(SEARCH("Specialised Industrial Machinery and Equipment Wholesaling",GR8)),"","341") | PF8: =if(ISERROR(SEARCH("Other Machinery and Equipment Wholesaling",GR8)),"","349") | PG8: =if(ISERROR(SEARCH("Motor Vehicle and Motor Vehicle Parts Wholesaling",GL8)),"","350") | PH8: =if(ISERROR(SEARCH("Textile, Clothing and Footwear Wholesaling",GV8)),"","371") | PI8: =if(ISERROR(SEARCH("Furniture, Floor Covering and Other Goods Wholesaling",GV8)),"","373") | PJ8: =if(ISERROR(SEARCH("Pharmaceutical and Toiletry Goods Wholesaling",GV8)),"","372") | PK8: =if(ISERROR(SEARCH("Civic, Professional and Other Interest Group Services",GZ8)),"","955") | PL8: =if(ISERROR(SEARCH("Funeral, Crematorium and Cemetery Services",GZ8)),"","952") | PM8: =if(ISERROR(SEARCH("Personal Care Services",GZ8)),"","951") | PN8: =if(ISERROR(SEARCH("Religious Services",GZ8)),"","954") | PO8: =if(ISERROR(SEARCH("Other Personal Services",GZ8)),"","953") | PP8: =if(ISERROR(SEARCH("Private Households Employing Staff and Undifferentiated Goods- and Service-Producing Activities of Households for Own Use",GY8)),"","960") | PQ8: =if(ISERROR(SEARCH("Automotive Repair and Maintenance",HE8)),"","941") | PR8: =if(ISERROR(SEARCH("Machinery and Equipment Repair and Maintenance",HE8)),"","942") | PS8: =if(ISERROR(SEARCH("Other Repair and Maintenance",HE8)),"","949")
HI9: =if(ISERROR(SEARCH("Accommodation",F9)),"","440") | HJ9: =if(ISERROR(SEARCH("Cafes, Restaurants and Takeaway Food Services",G9)),"","450") | HK9: =if(ISERROR(SEARCH("Clubs (Hospitality)",G9)),"","453") | HL9: =if(ISERROR(SEARCH("Pubs, Taverns and Bars",G9)),"","452") | HM9: =if(ISERROR(SEARCH("Employment Services",J9)),"","721") | HN9: =if(ISERROR(SEARCH("Travel Agency and Tour Arrangement Services",J9)),"","722") | HO9: =if(ISERROR(SEARCH("Other Administrative Services",J9)),"","729") | HP9: =if(ISERROR(SEARCH("Building Cleaning, Pest Control and Gardening Servicess",M9)),"","731") | HQ9: =if(ISERROR(SEARCH("Packaging Services",M9)),"","732") | HR9: =if(ISERROR(SEARCH("Dairy Cattle Farming",P9)),"","016") | HS9: =if(ISERROR(SEARCH("Deer Farming",P9)),"","018") | HT9: =if(ISERROR(SEARCH("Fruit and Tree Nut Growing",P9)),"","013") | HU9: =if(ISERROR(SEARCH("Mushroom and Vegetable Growing",P9)),"","012") | HV9: =if(ISERROR(SEARCH("Nursery and Floriculture Production",P9)),"","011") | HW9: =if(ISERROR(SEARCH("Poultry Farming",P9)),"","017") | HX9: =if(ISERROR(SEARCH("Sheep, Beef Cattle and Grain Farming",P9)),"","014") | HY9: =if(ISERROR(SEARCH("Other Crop Growing",P9)),"","015") | HZ9: =if(ISERROR(SEARCH("Other Livestock Farming",P9)),"","019") | IA9: =if(ISERROR(SEARCH("Agriculture and Fishing Support Services",X9)),"","052") | IB9: =if(ISERROR(SEARCH("Forestry Support Services",X9)),"","051") | IC9: =if(ISERROR(SEARCH("Aquaculture",Z9)),"","020") | ID9: =if(ISERROR(SEARCH("Fishing",AA9)),"","041") | IE9: =if(ISERROR(SEARCH("Hunting and Trapping",AA9)),"","042") | IF9: =if(ISERROR(SEARCH("Forestry and Logging",AB9)),"","030") | IG9: =if(ISERROR(SEARCH("Creative and Performing Arts Activities",AD9)),"","900") | IH9: =if(ISERROR(SEARCH("Gambling Activities",AD9)),"","920") | II9: =if(ISERROR(SEARCH("Museum Operation",AG9)),"","891") | IJ9: =if(ISERROR(SEARCH("Parks and Gardens Operations",AG9)),"","892") | IK9: =if(ISERROR(SEARCH("Amusement and Other Recreation Activities",AI9)),"","913") | IL9: =if(ISERROR(SEARCH("Horse and Dog Racing Activities",AI9)),"","912") | IM9: =if(ISERROR(SEARCH("Sports and Physical Recreation Activities",AI9)),"","911") | IN9: =if(ISERROR(SEARCH("Residential Building Construction",AN9)),"","301") | IO9: =if(ISERROR(SEARCH("Non-Residential Building Construction",AN9)),"","302") | IP9: =if(ISERROR(SEARCH("Building Completion Services",AP9)),"","324") | IQ9: =if(ISERROR(SEARCH("Building Installation Servicess",AP9)),"","323") | IR9: =if(ISERROR(SEARCH("Building Structure Services",AP9)),"","322") | IS9: =if(ISERROR(SEARCH("Land Development and Site Preparation Services",AP9)),"","321") | IT9: =if(ISERROR(SEARCH("Other Construction Services",AP9)),"","329") | IU9: =if(ISERROR(SEARCH("Road and Bridge Construction",AV9)),"","310") | IV9: =if(ISERROR(SEARCH("Other Heavy and Civil Engineering Construction",AV9)),"","310") | IW9: =if(ISERROR(SEARCH("Adult, Community and Other Education",AX9)),"","821") | IX9: =if(ISERROR(SEARCH("Educational Support Services",AX9)),"","822") | IY9: =if(ISERROR(SEARCH("Preschool Education",AZ9)),"","801") | IZ9: =if(ISERROR(SEARCH("School Education",AZ9)),"","802") | JA9: =if(ISERROR(SEARCH("Higher Education",BB9)),"","810") | JB9: =if(ISERROR(SEARCH("Higher Education",BC9)),"","810") | JC9: =if(ISERROR(SEARCH("Electricity Distribution",BC9)),"","263") | JD9: =if(ISERROR(SEARCH("Electricity Generation",BC9)),"","261") | JE9: =if(ISERROR(SEARCH("Electricity Transmission",BC9)),"","262") | JF9: =if(ISERROR(SEARCH("On Selling Electricity and Electricity Market Operation",BC9)),"","264") | JG9: =if(ISERROR(SEARCH("Gas Supply",BC9)),"","270") | JH9: =if(ISERROR(SEARCH("Waste Collection Services",BF9)),"","291") | JI9: =if(ISERROR(SEARCH("Waste Treatment, Disposal and Remediation Services",BF9)),"","292") | JJ9: =if(ISERROR(SEARCH("Sewerage and Drainage Services",BI9)),"","281") | JK9: =if(ISERROR(SEARCH("Water Supply",BI9)),"","281") | JL9: =if(ISERROR(SEARCH("Auxiliary Finance and Investment Services",BK9)),"","641") | JM9: =if(ISERROR(SEARCH("Auxiliary Insurance Services",BK9)),"","642") | JN9: =if(ISERROR(SEARCH("Central Banking",BM9)),"","621") | JO9: =if(ISERROR(SEARCH("Depository Financial Intermediation",BM9)),"","622") | JP9: =if(ISERROR(SEARCH("Financial Asset Investing",BM9)),"","624") | JQ9: =if(ISERROR(SEARCH("Non-Depository Financing",BM9)),"","623") | JR9: =if(ISERROR(SEARCH("Health and General Insurance",BO9)),"","632") | JS9: =if(ISERROR(SEARCH("Life Insurance",BO9)),"","631") | JT9: =if(ISERROR(SEARCH("Superannuation Funds",BO9)),"","633") | JU9: =if(ISERROR(SEARCH("Hospitals",BQ9)),"","840") | JV9: =if(ISERROR(SEARCH("Medical Services",BS9)),"","851") | JW9: =if(ISERROR(SEARCH("Pathology and Diagnostic Imaging Services",BS9)),"","852") | JX9: =if(ISERROR(SEARCH("Allied Health Services",BS9)),"","853") | JY9: =if(ISERROR(SEARCH("Other Health Care Services",BS9)),"","859") | JZ9: =if(ISERROR(SEARCH("Aged Care Residential Services",BW9)),"","860") | KA9: =if(ISERROR(SEARCH("Other Residential Care Services",BW9)),"","860") | KB9: =if(ISERROR(SEARCH("Child Care Services",BX9)),"","871") | KC9: =if(ISERROR(SEARCH("Other Social Assistance Services",BX9)),"","879") | KD9: =if(ISERROR(SEARCH("Radio Broadcasting",BZ9)),"","561") | KE9: =if(ISERROR(SEARCH("Television Broadcasting",BZ9)),"","562") | KF9: =if(ISERROR(SEARCH("Internet Publishing and Broadcasting",BY9)),"","570") | KG9: =if(ISERROR(SEARCH("Data Processing, Web Hosting and Electronic Information Storage Services",CB9)),"","592") | KH9: =if(ISERROR(SEARCH("Internet Service Providers and Web Search Portals",CB9)),"","591") | KI9: =if(ISERROR(SEARCH("Libraries and Archives",CD9)),"","601") | KJ9: =if(ISERROR(SEARCH("Other Information Services",CD9)),"","602") | KK9: =if(ISERROR(SEARCH("Motion Picture and Video Activities",CE9)),"","551") | KL9: =if(ISERROR(SEARCH("Sound Recording and Music Publishing",CE9)),"","552") | KM9: =if(ISERROR(SEARCH("Newspaper, Periodical, Book and Directory Publishing",CH9)),"","541") | KN9: =if(ISERROR(SEARCH("Software Publishing",CH9)),"","542") | KO9: =if(ISERROR(SEARCH("Telecommunications Services",BY9)),"","580") | KP9: =if(ISERROR(SEARCH("Basic Chemical Manufacturing",CK9)),"","181") | KQ9: =if(ISERROR(SEARCH("Basic Polymer Manufacturing",CK9)),"","182") | KR9: =if(ISERROR(SEARCH("Cleaning Compound and Toiletry Preparation Manufacturing",CK9)),"","185") | KS9: =if(ISERROR(SEARCH("Fertiliser and Pesticide Manufacturing",CK9)),"","183") | KT9: =if(ISERROR(SEARCH("Pharmaceutical and Medicinal Product Manufacturing",CK9)),"","184") | KU9: =if(ISERROR(SEARCH("Other Basic Chemical Product Manufacturing",CK9)),"","189") | KV9: =if(ISERROR(SEARCH("Beverage Manufacturing",CR9)),"","121") | KW9: =if(ISERROR(SEARCH("Cigarette and Tobacco Product Manufacturing",CR9)),"","122") | KX9: =if(ISERROR(SEARCH("Iron and Steel Forging",CT9)),"","221") | KY9: =if(ISERROR(SEARCH("Metal Container Manufacturing",CT9)),"","223") | KZ9: =if(ISERROR(SEARCH("Sheet Metal Product Manufacturing (except Metal Structural and Container Products)",CT9)),"","224") | LA9: =if(ISERROR(SEARCH("Structural Metal Product Manufacturing",CT9)),"","222") | LB9: =if(ISERROR(SEARCH("Other Fabricated Metal Product Manufacturing",CT9)),"","229") | LC9: =if(ISERROR(SEARCH("Bakery Product Manufacturing",CX9)),"","117") | LD9: =if(ISERROR(SEARCH("Dairy Product Manufacturing",CX9)),"","113") | LE9: =if(ISERROR(SEARCH("Fruit and Vegetable Processing",CX9)),"","114") | LF9: =if(ISERROR(SEARCH("Grain Mill and Cereal Product Manufacturing",CX9)),"","116") | LG9: =if(ISERROR(SEARCH("Meat and Meat Product Manufacturing",CX9)),"","111") | LH9: =if(ISERROR(SEARCH("Oil and Fat Manufacturing",CX9)),"","115") | LI9: =if(ISERROR(SEARCH("Seafood Processing",CX9)),"","112") | LJ9: =if(ISERROR(SEARCH("Sugar and Confectionery Manufacturing",CX9)),"","118") | LK9: =if(ISERROR(SEARCH("Other Food Product Manufacturing",CX9)),"","119") | LL9: =if(ISERROR(SEARCH("Furniture Manufacturing",DE9)),"","251") | LM9: =if(ISERROR(SEARCH("Other Manufacturing",DE9)),"","259") | LN9: =if(ISERROR(SEARCH("Computer and Electronic Equipment Manufacturing",DH9)),"","242") | LO9: =if(ISERROR(SEARCH("Domestic Appliance Manufacturing",DH9)),"","244") | LP9: =if(ISERROR(SEARCH("Electrical Equipment Manufacturing",DH9)),"","243") | LQ9: =if(ISERROR(SEARCH("Professional and Scientific Equipment Manufacturing",DH9)),"","241") | LR9: =if(ISERROR(SEARCH("Pump, Compressor, Heating and Ventilation Equipment Manufacturing",DH9)),"","245") | LS9: =if(ISERROR(SEARCH("Specialised Machinery and Equipment Manufacturing",DH9)),"","246") | LT9: =if(ISERROR(SEARCH("Other Machinery and Equipment Manufacturing",DH9)),"","249") | LU9: =if(ISERROR(SEARCH("Cement, Lime, Plaster and Concrete Product Manufacturing",DP9)),"","203") | LV9: =if(ISERROR(SEARCH("Ceramic Product Manufacturing",DP9)),"","202") | LW9: =if(ISERROR(SEARCH("Glass and Glass Product Manufacturing",DP9)),"","201") | LX9: =if(ISERROR(SEARCH("Other Non-Metallic Mineral Product Manufacturing",DP9)),"","209") | LY9: =if(ISERROR(SEARCH("Petroleum Refining and Petroleum Fuel Manufacturing",DS9)),"","170") | LZ9: =if(ISERROR(SEARCH("Other Petroleum and Coal Product Manufacturing",DS9)),"","170") | MA9: =if(ISERROR(SEARCH("Natural Rubber Product Manufacturing",DT9)),"","192") | MB9: =if(ISERROR(SEARCH("Polymer Product Manufacturing",DT9)),"","191") | MC9: =if(ISERROR(SEARCH("Basic Ferrous Metal Manufacturing",DV9)),"","211") | MD9: =if(ISERROR(SEARCH("Basic Ferrous Metal Product Manufacturing",DV9)),"","212") | ME9: =if(ISERROR(SEARCH("Basic Non-Ferrous Metal Manufacturing",DV9)),"","213") | MF9: =if(ISERROR(SEARCH("Basic Non-Ferrous Metal Product Manufacturing",DV9)),"","214") | MG9: =if(ISERROR(SEARCH("Printing and Printing Support Services",EA9)),"","161") | MH9: =if(ISERROR(SEARCH("Reproduction of Recorded Media",EA9)),"","162") | MI9: =if(ISERROR(SEARCH("Converted Paper Product Manufacturing",EC9)),"","152") | MJ9: =if(ISERROR(SEARCH("Pulp, Paper and Paperboard Manufacturing",EC9)),"","151") | MK9: =if(ISERROR(SEARCH("Clothing and Footwear Manufacturing",EE9)),"","135") | ML9: =if(ISERROR(SEARCH("Knitted Product Manufacturing",EE9)),"","134") | MM9: =if(ISERROR(SEARCH("Leather Tanning, Fur Dressing and Leather Product Manufacturing",EE9)),"","132") | MN9: =if(ISERROR(SEARCH("Textile Manufacturing",EE9)),"","131") | MO9: =if(ISERROR(SEARCH("Textile Product Manufacturing",EE9)),"","133") | MP9: =if(ISERROR(SEARCH("Motor Vehicle and Motor Vehicle Part Manufacturing",EI9)),"","231") | MQ9: =if(ISERROR(SEARCH("Other Transport Equipment Manufacturing",EI9)),"","239") | MR9: =if(ISERROR(SEARCH("Log Sawmilling and Timber Dressing",EL9)),"","141") | MS9: =if(ISERROR(SEARCH("Other Wood Product Manufacturing",EL9)),"","149") | MT9: =if(ISERROR(SEARCH("Coal Mining",EO9)),"","060") | MU9: =if(ISERROR(SEARCH("Exploration",EP9)),"","101") | MV9: =if(ISERROR(SEARCH("Other Mining Support Services",EP9)),"","109") | MW9: =if(ISERROR(SEARCH("Metal Ore Mining",EO9)),"","080") | MX9: =if(ISERROR(SEARCH("Construction Material Mining",ES9)),"","091") | MY9: =if(ISERROR(SEARCH("Oil and Gas Extraction",EO9)),"","070") | MZ9: =if(ISERROR(SEARCH("Other Non-Metallic Mineral Mining and Quarrying",ES9)),"","099") | NA9: =if(ISERROR(SEARCH("Computer System Design and Related Services",EU9)),"","700") | NB9: =if(ISERROR(SEARCH("Advertising Services",EV9)),"","694") | NC9: =if(ISERROR(SEARCH("Architectural, Engineering and Technical Services",EV9)),"","692") | ND9: =if(ISERROR(SEARCH("Legal and Accounting Services",EV9)),"","693") | NE9: =if(ISERROR(SEARCH("Management and Related Consulting Services",EV9)),"","696") | NF9: =if(ISERROR(SEARCH("Market Research and Statistical Services",EV9)),"","695") | NG9: =if(ISERROR(SEARCH("Scientific Research Services",EV9)),"","691") | NH9: =if(ISERROR(SEARCH("Veterinary Services",EV9)),"","697") | NI9: =if(ISERROR(SEARCH("Other Professional, Scientific and Technical Services",EV9)),"","699") | NJ9: =if(ISERROR(SEARCH("Central Government Administration",FB9)),"","751") | NK9: =if(ISERROR(SEARCH("State Government Administration",FB9)),"","752") | NL9: =if(ISERROR(SEARCH("Local Government Administration",FB9)),"","753") | NM9: =if(ISERROR(SEARCH("Justice",FB9)),"","754") | NN9: =if(ISERROR(SEARCH("Government Representation",FB9)),"","755") | NO9: =if(ISERROR(SEARCH("Defence",FA9)),"","760") | NP9: =if(ISERROR(SEARCH("Public Order and Safety Services",FD9)),"","771") | NQ9: =if(ISERROR(SEARCH("Regulatory Services",FD9)),"","772") | NR9: =if(ISERROR(SEARCH("Property Operators",FG9)),"","671") | NS9: =if(ISERROR(SEARCH("Real Estate Services",FG9)),"","672") | NT9: =if(ISERROR(SEARCH("Farm Animal and Bloodstock Leasing",FI9)),"","662") | NU9: =if(ISERROR(SEARCH("Motor Vehicle and Transport Equipment Rental and Hiring",FI9)),"","661") | NV9: =if(ISERROR(SEARCH("Non-Financial Intangible Assets (Except Copyrights) Leasing",FI9)),"","664") | NW9: =if(ISERROR(SEARCH("Other Goods and Equipment Rental and Hiring",FI9)),"","663") | NX9: =if(ISERROR(SEARCH("Supermarket and Grocery Stores",FM9)),"","411") | NY9: =if(ISERROR(SEARCH("Specialised Food Retailing",FM9)),"","412") | NZ9: =if(ISERROR(SEARCH("Fuel Retailing",FL9)),"","400") | OA9: =if(ISERROR(SEARCH("Motor Vehicle Parts and Tyre Retailing",FO9)),"","392") | OB9: =if(ISERROR(SEARCH("Motor Vehicle Retailing",FO9)),"","391") | OC9: =if(ISERROR(SEARCH("Non-Store Retailing",FR9)),"","431") | OD9: =if(ISERROR(SEARCH("Retail Commission-Based Buying and/or Selling",FR9)),"","432") | OE9: =if(ISERROR(SEARCH("Clothing, Footwear and Personal Accessory Retailing",FS9)),"","425") | OF9: =if(ISERROR(SEARCH("Department Stores",FS9)),"","426") | OG9: =if(ISERROR(SEARCH("Electrical and Electronic Goods Retailing",FS9)),"","422") | OH9: =if(ISERROR(SEARCH("Furniture, Floor Coverings, Houseware and Textile Goods Retailing",FS9)),"","421") | OI9: =if(ISERROR(SEARCH("Hardware, Building and Garden Supplies Retailing",FS9)),"","423") | OJ9: =if(ISERROR(SEARCH("Pharmaceutical and Other Store-Based Retailing",FS9)),"","427") | OK9: =if(ISERROR(SEARCH("Recreational Goods Retailing",FS9)),"","424") | OL9: =if(ISERROR(SEARCH("Air and Space Transport",FZ9)),"","490") | OM9: =if(ISERROR(SEARCH("Postal and Courier Pick-up and Delivery Services",FZ9)),"","510") | ON9: =if(ISERROR(SEARCH("Rail Freight Transport",GB9)),"","471") | OO9: =if(ISERROR(SEARCH("Rail Passenger Transport",GB9)),"","472") | OP9: =if(ISERROR(SEARCH("Road Freight Transport",GC9)),"","461") | OQ9: =if(ISERROR(SEARCH("Road Passenger Transport",GC9)),"","462") | OR9: =if(ISERROR(SEARCH("Airport Operations and Other Air Transport Support Services",GE9)),"","522") | OS9: =if(ISERROR(SEARCH("Water Transport Support Services",GE9)),"","521") | OT9: =if(ISERROR(SEARCH("Other Transport Support Services",GE9)),"","529") | OU9: =if(ISERROR(SEARCH("Warehousing and Storage Services",FZ9)),"","530") | OV9: =if(ISERROR(SEARCH("Water Freight Transport",GI9)),"","481") | OW9: =if(ISERROR(SEARCH("Water Freight Transport",GI9)),"","482") | OX9: =if(ISERROR(SEARCH("Pipeline and Other Transport",GJ9)),"","502") | OY9: =if(ISERROR(SEARCH("Scenic and Sightseeing Transport",GJ9)),"","501") | OZ9: =if(ISERROR(SEARCH("Agricultural Product Wholesaling",GM9)),"","331") | PA9: =if(ISERROR(SEARCH("Mineral, Metal and Chemical Wholesaling",GM9)),"","332") | PB9: =if(ISERROR(SEARCH("Timber and Hardware Goods Wholesaling",GM9)),"","333") | PC9: =if(ISERROR(SEARCH("Commission-Based Wholesaling",GL9)),"","380") | PD9: =if(ISERROR(SEARCH("Grocery, Liquor and Tobacco Product Wholesaling",GL9)),"","360") | PE9: =if(ISERROR(SEARCH("Specialised Industrial Machinery and Equipment Wholesaling",GR9)),"","341") | PF9: =if(ISERROR(SEARCH("Other Machinery and Equipment Wholesaling",GR9)),"","349") | PG9: =if(ISERROR(SEARCH("Motor Vehicle and Motor Vehicle Parts Wholesaling",GL9)),"","350") | PH9: =if(ISERROR(SEARCH("Textile, Clothing and Footwear Wholesaling",GV9)),"","371") | PI9: =if(ISERROR(SEARCH("Furniture, Floor Covering and Other Goods Wholesaling",GV9)),"","373") | PJ9: =if(ISERROR(SEARCH("Pharmaceutical and Toiletry Goods Wholesaling",GV9)),"","372") | PK9: =if(ISERROR(SEARCH("Civic, Professional and Other Interest Group Services",GZ9)),"","955") | PL9: =if(ISERROR(SEARCH("Funeral, Crematorium and Cemetery Services",GZ9)),"","952") | PM9: =if(ISERROR(SEARCH("Personal Care Services",GZ9)),"","951") | PN9: =if(ISERROR(SEARCH("Religious Services",GZ9)),"","954") | PO9: =if(ISERROR(SEARCH("Other Personal Services",GZ9)),"","953") | PP9: =if(ISERROR(SEARCH("Private Households Employing Staff and Undifferentiated Goods- and Service-Producing Activities of Households for Own Use",GY9)),"","960") | PQ9: =if(ISERROR(SEARCH("Automotive Repair and Maintenance",HE9)),"","941") | PR9: =if(ISERROR(SEARCH("Machinery and Equipment Repair and Maintenance",HE9)),"","942") | PS9: =if(ISERROR(SEARCH("Other Repair and Maintenance",HE9)),"","949")
HI10: =if(ISERROR(SEARCH("Accommodation",F10)),"","440") | HJ10: =if(ISERROR(SEARCH("Cafes, Restaurants and Takeaway Food Services",G10)),"","450") | HK10: =if(ISERROR(SEARCH("Clubs (Hospitality)",G10)),"","453") | HL10: =if(ISERROR(SEARCH("Pubs, Taverns and Bars",G10)),"","452") | HM10: =if(ISERROR(SEARCH("Employment Services",J10)),"","721") | HN10: =if(ISERROR(SEARCH("Travel Agency and Tour Arrangement Services",J10)),"","722") | HO10: =if(ISERROR(SEARCH("Other Administrative Services",J10)),"","729") | HP10: =if(ISERROR(SEARCH("Building Cleaning, Pest Control and Gardening Servicess",M10)),"","731") | HQ10: =if(ISERROR(SEARCH("Packaging Services",M10)),"","732") | HR10: =if(ISERROR(SEARCH("Dairy Cattle Farming",P10)),"","016") | HS10: =if(ISERROR(SEARCH("Deer Farming",P10)),"","018") | HT10: =if(ISERROR(SEARCH("Fruit and Tree Nut Growing",P10)),"","013") | HU10: =if(ISERROR(SEARCH("Mushroom and Vegetable Growing",P10)),"","012") | HV10: =if(ISERROR(SEARCH("Nursery and Floriculture Production",P10)),"","011") | HW10: =if(ISERROR(SEARCH("Poultry Farming",P10)),"","017") | HX10: =if(ISERROR(SEARCH("Sheep, Beef Cattle and Grain Farming",P10)),"","014") | HY10: =if(ISERROR(SEARCH("Other Crop Growing",P10)),"","015") | HZ10: =if(ISERROR(SEARCH("Other Livestock Farming",P10)),"","019") | IA10: =if(ISERROR(SEARCH("Agriculture and Fishing Support Services",X10)),"","052") | IB10: =if(ISERROR(SEARCH("Forestry Support Services",X10)),"","051") | IC10: =if(ISERROR(SEARCH("Aquaculture",Z10)),"","020") | ID10: =if(ISERROR(SEARCH("Fishing",AA10)),"","041") | IE10: =if(ISERROR(SEARCH("Hunting and Trapping",AA10)),"","042") | IF10: =if(ISERROR(SEARCH("Forestry and Logging",AB10)),"","030") | IG10: =if(ISERROR(SEARCH("Creative and Performing Arts Activities",AD10)),"","900") | IH10: =if(ISERROR(SEARCH("Gambling Activities",AD10)),"","920") | II10: =if(ISERROR(SEARCH("Museum Operation",AG10)),"","891") | IJ10: =if(ISERROR(SEARCH("Parks and Gardens Operations",AG10)),"","892") | IK10: =if(ISERROR(SEARCH("Amusement and Other Recreation Activities",AI10)),"","913") | IL10: =if(ISERROR(SEARCH("Horse and Dog Racing Activities",AI10)),"","912") | IM10: =if(ISERROR(SEARCH("Sports and Physical Recreation Activities",AI10)),"","911") | IN10: =if(ISERROR(SEARCH("Residential Building Construction",AN10)),"","301") | IO10: =if(ISERROR(SEARCH("Non-Residential Building Construction",AN10)),"","302") | IP10: =if(ISERROR(SEARCH("Building Completion Services",AP10)),"","324") | IQ10: =if(ISERROR(SEARCH("Building Installation Servicess",AP10)),"","323") | IR10: =if(ISERROR(SEARCH("Building Structure Services",AP10)),"","322") | IS10: =if(ISERROR(SEARCH("Land Development and Site Preparation Services",AP10)),"","321") | IT10: =if(ISERROR(SEARCH("Other Construction Services",AP10)),"","329") | IU10: =if(ISERROR(SEARCH("Road and Bridge Construction",AV10)),"","310") | IV10: =if(ISERROR(SEARCH("Other Heavy and Civil Engineering Construction",AV10)),"","310") | IW10: =if(ISERROR(SEARCH("Adult, Community and Other Education",AX10)),"","821") | IX10: =if(ISERROR(SEARCH("Educational Support Services",AX10)),"","822") | IY10: =if(ISERROR(SEARCH("Preschool Education",AZ10)),"","801") | IZ10: =if(ISERROR(SEARCH("School Education",AZ10)),"","802") | JA10: =if(ISERROR(SEARCH("Higher Education",BB10)),"","810") | JB10: =if(ISERROR(SEARCH("Higher Education",BC10)),"","810") | JC10: =if(ISERROR(SEARCH("Electricity Distribution",BC10)),"","263") | JD10: =if(ISERROR(SEARCH("Electricity Generation",BC10)),"","261") | JE10: =if(ISERROR(SEARCH("Electricity Transmission",BC10)),"","262") | JF10: =if(ISERROR(SEARCH("On Selling Electricity and Electricity Market Operation",BC10)),"","264") | JG10: =if(ISERROR(SEARCH("Gas Supply",BC10)),"","270") | JH10: =if(ISERROR(SEARCH("Waste Collection Services",BF10)),"","291") | JI10: =if(ISERROR(SEARCH("Waste Treatment, Disposal and Remediation Services",BF10)),"","292") | JJ10: =if(ISERROR(SEARCH("Sewerage and Drainage Services",BI10)),"","281") | JK10: =if(ISERROR(SEARCH("Water Supply",BI10)),"","281") | JL10: =if(ISERROR(SEARCH("Auxiliary Finance and Investment Services",BK10)),"","641") | JM10: =if(ISERROR(SEARCH("Auxiliary Insurance Services",BK10)),"","642") | JN10: =if(ISERROR(SEARCH("Central Banking",BM10)),"","621") | JO10: =if(ISERROR(SEARCH("Depository Financial Intermediation",BM10)),"","622") | JP10: =if(ISERROR(SEARCH("Financial Asset Investing",BM10)),"","624") | JQ10: =if(ISERROR(SEARCH("Non-Depository Financing",BM10)),"","623") | JR10: =if(ISERROR(SEARCH("Health and General Insurance",BO10)),"","632") | JS10: =if(ISERROR(SEARCH("Life Insurance",BO10)),"","631") | JT10: =if(ISERROR(SEARCH("Superannuation Funds",BO10)),"","633") | JU10: =if(ISERROR(SEARCH("Hospitals",BQ10)),"","840") | JV10: =if(ISERROR(SEARCH("Medical Services",BS10)),"","851") | JW10: =if(ISERROR(SEARCH("Pathology and Diagnostic Imaging Services",BS10)),"","852") | JX10: =if(ISERROR(SEARCH("Allied Health Services",BS10)),"","853") | JY10: =if(ISERROR(SEARCH("Other Health Care Services",BS10)),"","859") | JZ10: =if(ISERROR(SEARCH("Aged Care Residential Services",BW10)),"","860") | KA10: =if(ISERROR(SEARCH("Other Residential Care Services",BW10)),"","860") | KB10: =if(ISERROR(SEARCH("Child Care Services",BX10)),"","871") | KC10: =if(ISERROR(SEARCH("Other Social Assistance Services",BX10)),"","879") | KD10: =if(ISERROR(SEARCH("Radio Broadcasting",BZ10)),"","561") | KE10: =if(ISERROR(SEARCH("Television Broadcasting",BZ10)),"","562") | KF10: =if(ISERROR(SEARCH("Internet Publishing and Broadcasting",BY10)),"","570") | KG10: =if(ISERROR(SEARCH("Data Processing, Web Hosting and Electronic Information Storage Services",CB10)),"","592") | KH10: =if(ISERROR(SEARCH("Internet Service Providers and Web Search Portals",CB10)),"","591") | KI10: =if(ISERROR(SEARCH("Libraries and Archives",CD10)),"","601") | KJ10: =if(ISERROR(SEARCH("Other Information Services",CD10)),"","602") | KK10: =if(ISERROR(SEARCH("Motion Picture and Video Activities",CE10)),"","551") | KL10: =if(ISERROR(SEARCH("Sound Recording and Music Publishing",CE10)),"","552") | KM10: =if(ISERROR(SEARCH("Newspaper, Periodical, Book and Directory Publishing",CH10)),"","541") | KN10: =if(ISERROR(SEARCH("Software Publishing",CH10)),"","542") | KO10: =if(ISERROR(SEARCH("Telecommunications Services",BY10)),"","580") | KP10: =if(ISERROR(SEARCH("Basic Chemical Manufacturing",CK10)),"","181") | KQ10: =if(ISERROR(SEARCH("Basic Polymer Manufacturing",CK10)),"","182") | KR10: =if(ISERROR(SEARCH("Cleaning Compound and Toiletry Preparation Manufacturing",CK10)),"","185") | KS10: =if(ISERROR(SEARCH("Fertiliser and Pesticide Manufacturing",CK10)),"","183") | KT10: =if(ISERROR(SEARCH("Pharmaceutical and Medicinal Product Manufacturing",CK10)),"","184") | KU10: =if(ISERROR(SEARCH("Other Basic Chemical Product Manufacturing",CK10)),"","189") | KV10: =if(ISERROR(SEARCH("Beverage Manufacturing",CR10)),"","121") | KW10: =if(ISERROR(SEARCH("Cigarette and Tobacco Product Manufacturing",CR10)),"","122") | KX10: =if(ISERROR(SEARCH("Iron and Steel Forging",CT10)),"","221") | KY10: =if(ISERROR(SEARCH("Metal Container Manufacturing",CT10)),"","223") | KZ10: =if(ISERROR(SEARCH("Sheet Metal Product Manufacturing (except Metal Structural and Container Products)",CT10)),"","224") | LA10: =if(ISERROR(SEARCH("Structural Metal Product Manufacturing",CT10)),"","222") | LB10: =if(ISERROR(SEARCH("Other Fabricated Metal Product Manufacturing",CT10)),"","229") | LC10: =if(ISERROR(SEARCH("Bakery Product Manufacturing",CX10)),"","117") | LD10: =if(ISERROR(SEARCH("Dairy Product Manufacturing",CX10)),"","113") | LE10: =if(ISERROR(SEARCH("Fruit and Vegetable Processing",CX10)),"","114") | LF10: =if(ISERROR(SEARCH("Grain Mill and Cereal Product Manufacturing",CX10)),"","116") | LG10: =if(ISERROR(SEARCH("Meat and Meat Product Manufacturing",CX10)),"","111") | LH10: =if(ISERROR(SEARCH("Oil and Fat Manufacturing",CX10)),"","115") | LI10: =if(ISERROR(SEARCH("Seafood Processing",CX10)),"","112") | LJ10: =if(ISERROR(SEARCH("Sugar and Confectionery Manufacturing",CX10)),"","118") | LK10: =if(ISERROR(SEARCH("Other Food Product Manufacturing",CX10)),"","119") | LL10: =if(ISERROR(SEARCH("Furniture Manufacturing",DE10)),"","251") | LM10: =if(ISERROR(SEARCH("Other Manufacturing",DE10)),"","259") | LN10: =if(ISERROR(SEARCH("Computer and Electronic Equipment Manufacturing",DH10)),"","242") | LO10: =if(ISERROR(SEARCH("Domestic Appliance Manufacturing",DH10)),"","244") | LP10: =if(ISERROR(SEARCH("Electrical Equipment Manufacturing",DH10)),"","243") | LQ10: =if(ISERROR(SEARCH("Professional and Scientific Equipment Manufacturing",DH10)),"","241") | LR10: =if(ISERROR(SEARCH("Pump, Compressor, Heating and Ventilation Equipment Manufacturing",DH10)),"","245") | LS10: =if(ISERROR(SEARCH("Specialised Machinery and Equipment Manufacturing",DH10)),"","246") | LT10: =if(ISERROR(SEARCH("Other Machinery and Equipment Manufacturing",DH10)),"","249") | LU10: =if(ISERROR(SEARCH("Cement, Lime, Plaster and Concrete Product Manufacturing",DP10)),"","203") | LV10: =if(ISERROR(SEARCH("Ceramic Product Manufacturing",DP10)),"","202") | LW10: =if(ISERROR(SEARCH("Glass and Glass Product Manufacturing",DP10)),"","201") | LX10: =if(ISERROR(SEARCH("Other Non-Metallic Mineral Product Manufacturing",DP10)),"","209") | LY10: =if(ISERROR(SEARCH("Petroleum Refining and Petroleum Fuel Manufacturing",DS10)),"","170") | LZ10: =if(ISERROR(SEARCH("Other Petroleum and Coal Product Manufacturing",DS10)),"","170") | MA10: =if(ISERROR(SEARCH("Natural Rubber Product Manufacturing",DT10)),"","192") | MB10: =if(ISERROR(SEARCH("Polymer Product Manufacturing",DT10)),"","191") | MC10: =if(ISERROR(SEARCH("Basic Ferrous Metal Manufacturing",DV10)),"","211") | MD10: =if(ISERROR(SEARCH("Basic Ferrous Metal Product Manufacturing",DV10)),"","212") | ME10: =if(ISERROR(SEARCH("Basic Non-Ferrous Metal Manufacturing",DV10)),"","213") | MF10: =if(ISERROR(SEARCH("Basic Non-Ferrous Metal Product Manufacturing",DV10)),"","214") | MG10: =if(ISERROR(SEARCH("Printing and Printing Support Services",EA10)),"","161") | MH10: =if(ISERROR(SEARCH("Reproduction of Recorded Media",EA10)),"","162") | MI10: =if(ISERROR(SEARCH("Converted Paper Product Manufacturing",EC10)),"","152") | MJ10: =if(ISERROR(SEARCH("Pulp, Paper and Paperboard Manufacturing",EC10)),"","151") | MK10: =if(ISERROR(SEARCH("Clothing and Footwear Manufacturing",EE10)),"","135") | ML10: =if(ISERROR(SEARCH("Knitted Product Manufacturing",EE10)),"","134") | MM10: =if(ISERROR(SEARCH("Leather Tanning, Fur Dressing and Leather Product Manufacturing",EE10)),"","132") | MN10: =if(ISERROR(SEARCH("Textile Manufacturing",EE10)),"","131") | MO10: =if(ISERROR(SEARCH("Textile Product Manufacturing",EE10)),"","133") | MP10: =if(ISERROR(SEARCH("Motor Vehicle and Motor Vehicle Part Manufacturing",EI10)),"","231") | MQ10: =if(ISERROR(SEARCH("Other Transport Equipment Manufacturing",EI10)),"","239") | MR10: =if(ISERROR(SEARCH("Log Sawmilling and Timber Dressing",EL10)),"","141") | MS10: =if(ISERROR(SEARCH("Other Wood Product Manufacturing",EL10)),"","149") | MT10: =if(ISERROR(SEARCH("Coal Mining",EO10)),"","060") | MU10: =if(ISERROR(SEARCH("Exploration",EP10)),"","101") | MV10: =if(ISERROR(SEARCH("Other Mining Support Services",EP10)),"","109") | MW10: =if(ISERROR(SEARCH("Metal Ore Mining",EO10)),"","080") | MX10: =if(ISERROR(SEARCH("Construction Material Mining",ES10)),"","091") | MY10: =if(ISERROR(SEARCH("Oil and Gas Extraction",EO10)),"","070") | MZ10: =if(ISERROR(SEARCH("Other Non-Metallic Mineral Mining and Quarrying",ES10)),"","099") | NA10: =if(ISERROR(SEARCH("Computer System Design and Related Services",EU10)),"","700") | NB10: =if(ISERROR(SEARCH("Advertising Services",EV10)),"","694") | NC10: =if(ISERROR(SEARCH("Architectural, Engineering and Technical Services",EV10)),"","692") | ND10: =if(ISERROR(SEARCH("Legal and Accounting Services",EV10)),"","693") | NE10: =if(ISERROR(SEARCH("Management and Related Consulting Services",EV10)),"","696") | NF10: =if(ISERROR(SEARCH("Market Research and Statistical Services",EV10)),"","695") | NG10: =if(ISERROR(SEARCH("Scientific Research Services",EV10)),"","691") | NH10: =if(ISERROR(SEARCH("Veterinary Services",EV10)),"","697") | NI10: =if(ISERROR(SEARCH("Other Professional, Scientific and Technical Services",EV10)),"","699") | NJ10: =if(ISERROR(SEARCH("Central Government Administration",FB10)),"","751") | NK10: =if(ISERROR(SEARCH("State Government Administration",FB10)),"","752") | NL10: =if(ISERROR(SEARCH("Local Government Administration",FB10)),"","753") | NM10: =if(ISERROR(SEARCH("Justice",FB10)),"","754") | NN10: =if(ISERROR(SEARCH("Government Representation",FB10)),"","755") | NO10: =if(ISERROR(SEARCH("Defence",FA10)),"","760") | NP10: =if(ISERROR(SEARCH("Public Order and Safety Services",FD10)),"","771") | NQ10: =if(ISERROR(SEARCH("Regulatory Services",FD10)),"","772") | NR10: =if(ISERROR(SEARCH("Property Operators",FG10)),"","671") | NS10: =if(ISERROR(SEARCH("Real Estate Services",FG10)),"","672") | NT10: =if(ISERROR(SEARCH("Farm Animal and Bloodstock Leasing",FI10)),"","662") | NU10: =if(ISERROR(SEARCH("Motor Vehicle and Transport Equipment Rental and Hiring",FI10)),"","661") | NV10: =if(ISERROR(SEARCH("Non-Financial Intangible Assets (Except Copyrights) Leasing",FI10)),"","664") | NW10: =if(ISERROR(SEARCH("Other Goods and Equipment Rental and Hiring",FI10)),"","663") | NX10: =if(ISERROR(SEARCH("Supermarket and Grocery Stores",FM10)),"","411") | NY10: =if(ISERROR(SEARCH("Specialised Food Retailing",FM10)),"","412") | NZ10: =if(ISERROR(SEARCH("Fuel Retailing",FL10)),"","400") | OA10: =if(ISERROR(SEARCH("Motor Vehicle Parts and Tyre Retailing",FO10)),"","392") | OB10: =if(ISERROR(SEARCH("Motor Vehicle Retailing",FO10)),"","391") | OC10: =if(ISERROR(SEARCH("Non-Store Retailing",FR10)),"","431") | OD10: =if(ISERROR(SEARCH("Retail Commission-Based Buying and/or Selling",FR10)),"","432") | OE10: =if(ISERROR(SEARCH("Clothing, Footwear and Personal Accessory Retailing",FS10)),"","425") | OF10: =if(ISERROR(SEARCH("Department Stores",FS10)),"","426") | OG10: =if(ISERROR(SEARCH("Electrical and Electronic Goods Retailing",FS10)),"","422") | OH10: =if(ISERROR(SEARCH("Furniture, Floor Coverings, Houseware and Textile Goods Retailing",FS10)),"","421") | OI10: =if(ISERROR(SEARCH("Hardware, Building and Garden Supplies Retailing",FS10)),"","423") | OJ10: =if(ISERROR(SEARCH("Pharmaceutical and Other Store-Based Retailing",FS10)),"","427") | OK10: =if(ISERROR(SEARCH("Recreational Goods Retailing",FS10)),"","424") | OL10: =if(ISERROR(SEARCH("Air and Space Transport",FZ10)),"","490") | OM10: =if(ISERROR(SEARCH("Postal and Courier Pick-up and Delivery Services",FZ10)),"","510") | ON10: =if(ISERROR(SEARCH("Rail Freight Transport",GB10)),"","471") | OO10: =if(ISERROR(SEARCH("Rail Passenger Transport",GB10)),"","472") | OP10: =if(ISERROR(SEARCH("Road Freight Transport",GC10)),"","461") | OQ10: =if(ISERROR(SEARCH("Road Passenger Transport",GC10)),"","462") | OR10: =if(ISERROR(SEARCH("Airport Operations and Other Air Transport Support Services",GE10)),"","522") | OS10: =if(ISERROR(SEARCH("Water Transport Support Services",GE10)),"","521") | OT10: =if(ISERROR(SEARCH("Other Transport Support Services",GE10)),"","529") | OU10: =if(ISERROR(SEARCH("Warehousing and Storage Services",FZ10)),"","530") | OV10: =if(ISERROR(SEARCH("Water Freight Transport",GI10)),"","481") | OW10: =if(ISERROR(SEARCH("Water Freight Transport",GI10)),"","482") | OX10: =if(ISERROR(SEARCH("Pipeline and Other Transport",GJ10)),"","502") | OY10: =if(ISERROR(SEARCH("Scenic and Sightseeing Transport",GJ10)),"","501") | OZ10: =if(ISERROR(SEARCH("Agricultural Product Wholesaling",GM10)),"","331") | PA10: =if(ISERROR(SEARCH("Mineral, Metal and Chemical Wholesaling",GM10)),"","332") | PB10: =if(ISERROR(SEARCH("Timber and Hardware Goods Wholesaling",GM10)),"","333") | PC10: =if(ISERROR(SEARCH("Commission-Based Wholesaling",GL10)),"","380") | PD10: =if(ISERROR(SEARCH("Grocery, Liquor and Tobacco Product Wholesaling",GL10)),"","360") | PE10: =if(ISERROR(SEARCH("Specialised Industrial Machinery and Equipment Wholesaling",GR10)),"","341") | PF10: =if(ISERROR(SEARCH("Other Machinery and Equipment Wholesaling",GR10)),"","349") | PG10: =if(ISERROR(SEARCH("Motor Vehicle and Motor Vehicle Parts Wholesaling",GL10)),"","350") | PH10: =if(ISERROR(SEARCH("Textile, Clothing and Footwear Wholesaling",GV10)),"","371") | PI10: =if(ISERROR(SEARCH("Furniture, Floor Covering and Other Goods Wholesaling",GV10)),"","373") | PJ10: =if(ISERROR(SEARCH("Pharmaceutical and Toiletry Goods Wholesaling",GV10)),"","372") | PK10: =if(ISERROR(SEARCH("Civic, Professional and Other Interest Group Services",GZ10)),"","955") | PL10: =if(ISERROR(SEARCH("Funeral, Crematorium and Cemetery Services",GZ10)),"","952") | PM10: =if(ISERROR(SEARCH("Personal Care Services",GZ10)),"","951") | PN10: =if(ISERROR(SEARCH("Religious Services",GZ10)),"","954") | PO10: =if(ISERROR(SEARCH("Other Personal Services",GZ10)),"","953") | PP10: =if(ISERROR(SEARCH("Private Households Employing Staff and Undifferentiated Goods- and Service-Producing Activities of Households for Own Use",GY10)),"","960") | PQ10: =if(ISERROR(SEARCH("Automotive Repair and Maintenance",HE10)),"","941") | PR10: =if(ISERROR(SEARCH("Machinery and Equipment Repair and Maintenance",HE10)),"","942") | PS10: =if(ISERROR(SEARCH("Other Repair and Maintenance",HE10)),"","949")
HI11: =if(ISERROR(SEARCH("Accommodation",F11)),"","440") | HJ11: =if(ISERROR(SEARCH("Cafes, Restaurants and Takeaway Food Services",G11)),"","450") | HK11: =if(ISERROR(SEARCH("Clubs (Hospitality)",G11)),"","453") | HL11: =if(ISERROR(SEARCH("Pubs, Taverns and Bars",G11)),"","452") | HM11: =if(ISERROR(SEARCH("Employment Services",J11)),"","721") | HN11: =if(ISERROR(SEARCH("Travel Agency and Tour Arrangement Services",J11)),"","722") | HO11: =if(ISERROR(SEARCH("Other Administrative Services",J11)),"","729") | HP11: =if(ISERROR(SEARCH("Building Cleaning, Pest Control and Gardening Servicess",M11)),"","731") | HQ11: =if(ISERROR(SEARCH("Packaging Services",M11)),"","732") | HR11: =if(ISERROR(SEARCH("Dairy Cattle Farming",P11)),"","016") | HS11: =if(ISERROR(SEARCH("Deer Farming",P11)),"","018") | HT11: =if(ISERROR(SEARCH("Fruit and Tree Nut Growing",P11)),"","013") | HU11: =if(ISERROR(SEARCH("Mushroom and Vegetable Growing",P11)),"","012") | HV11: =if(ISERROR(SEARCH("Nursery and Floriculture Production",P11)),"","011") | HW11: =if(ISERROR(SEARCH("Poultry Farming",P11)),"","017") | HX11: =if(ISERROR(SEARCH("Sheep, Beef Cattle and Grain Farming",P11)),"","014") | HY11: =if(ISERROR(SEARCH("Other Crop Growing",P11)),"","015") | HZ11: =if(ISERROR(SEARCH("Other Livestock Farming",P11)),"","019") | IA11: =if(ISERROR(SEARCH("Agriculture and Fishing Support Services",X11)),"","052") | IB11: =if(ISERROR(SEARCH("Forestry Support Services",X11)),"","051") | IC11: =if(ISERROR(SEARCH("Aquaculture",Z11)),"","020") | ID11: =if(ISERROR(SEARCH("Fishing",AA11)),"","041") | IE11: =if(ISERROR(SEARCH("Hunting and Trapping",AA11)),"","042") | IF11: =if(ISERROR(SEARCH("Forestry and Logging",AB11)),"","030") | IG11: =if(ISERROR(SEARCH("Creative and Performing Arts Activities",AD11)),"","900") | IH11: =if(ISERROR(SEARCH("Gambling Activities",AD11)),"","920") | II11: =if(ISERROR(SEARCH("Museum Operation",AG11)),"","891") | IJ11: =if(ISERROR(SEARCH("Parks and Gardens Operations",AG11)),"","892") | IK11: =if(ISERROR(SEARCH("Amusement and Other Recreation Activities",AI11)),"","913") | IL11: =if(ISERROR(SEARCH("Horse and Dog Racing Activities",AI11)),"","912") | IM11: =if(ISERROR(SEARCH("Sports and Physical Recreation Activities",AI11)),"","911") | IN11: =if(ISERROR(SEARCH("Residential Building Construction",AN11)),"","301") | IO11: =if(ISERROR(SEARCH("Non-Residential Building Construction",AN11)),"","302") | IP11: =if(ISERROR(SEARCH("Building Completion Services",AP11)),"","324") | IQ11: =if(ISERROR(SEARCH("Building Installation Servicess",AP11)),"","323") | IR11: =if(ISERROR(SEARCH("Building Structure Services",AP11)),"","322") | IS11: =if(ISERROR(SEARCH("Land Development and Site Preparation Services",AP11)),"","321") | IT11: =if(ISERROR(SEARCH("Other Construction Services",AP11)),"","329") | IU11: =if(ISERROR(SEARCH("Road and Bridge Construction",AV11)),"","310") | IV11: =if(ISERROR(SEARCH("Other Heavy and Civil Engineering Construction",AV11)),"","310") | IW11: =if(ISERROR(SEARCH("Adult, Community and Other Education",AX11)),"","821") | IX11: =if(ISERROR(SEARCH("Educational Support Services",AX11)),"","822") | IY11: =if(ISERROR(SEARCH("Preschool Education",AZ11)),"","801") | IZ11: =if(ISERROR(SEARCH("School Education",AZ11)),"","802") | JA11: =if(ISERROR(SEARCH("Higher Education",BB11)),"","810") | JB11: =if(ISERROR(SEARCH("Higher Education",BC11)),"","810") | JC11: =if(ISERROR(SEARCH("Electricity Distribution",BC11)),"","263") | JD11: =if(ISERROR(SEARCH("Electricity Generation",BC11)),"","261") | JE11: =if(ISERROR(SEARCH("Electricity Transmission",BC11)),"","262") | JF11: =if(ISERROR(SEARCH("On Selling Electricity and Electricity Market Operation",BC11)),"","264") | JG11: =if(ISERROR(SEARCH("Gas Supply",BC11)),"","270") | JH11: =if(ISERROR(SEARCH("Waste Collection Services",BF11)),"","291") | JI11: =if(ISERROR(SEARCH("Waste Treatment, Disposal and Remediation Services",BF11)),"","292") | JJ11: =if(ISERROR(SEARCH("Sewerage and Drainage Services",BI11)),"","281") | JK11: =if(ISERROR(SEARCH("Water Supply",BI11)),"","281") | JL11: =if(ISERROR(SEARCH("Auxiliary Finance and Investment Services",BK11)),"","641") | JM11: =if(ISERROR(SEARCH("Auxiliary Insurance Services",BK11)),"","642") | JN11: =if(ISERROR(SEARCH("Central Banking",BM11)),"","621") | JO11: =if(ISERROR(SEARCH("Depository Financial Intermediation",BM11)),"","622") | JP11: =if(ISERROR(SEARCH("Financial Asset Investing",BM11)),"","624") | JQ11: =if(ISERROR(SEARCH("Non-Depository Financing",BM11)),"","623") | JR11: =if(ISERROR(SEARCH("Health and General Insurance",BO11)),"","632") | JS11: =if(ISERROR(SEARCH("Life Insurance",BO11)),"","631") | JT11: =if(ISERROR(SEARCH("Superannuation Funds",BO11)),"","633") | JU11: =if(ISERROR(SEARCH("Hospitals",BQ11)),"","840") | JV11: =if(ISERROR(SEARCH("Medical Services",BS11)),"","851") | JW11: =if(ISERROR(SEARCH("Pathology and Diagnostic Imaging Services",BS11)),"","852") | JX11: =if(ISERROR(SEARCH("Allied Health Services",BS11)),"","853") | JY11: =if(ISERROR(SEARCH("Other Health Care Services",BS11)),"","859") | JZ11: =if(ISERROR(SEARCH("Aged Care Residential Services",BW11)),"","860") | KA11: =if(ISERROR(SEARCH("Other Residential Care Services",BW11)),"","860") | KB11: =if(ISERROR(SEARCH("Child Care Services",BX11)),"","871") | KC11: =if(ISERROR(SEARCH("Other Social Assistance Services",BX11)),"","879") | KD11: =if(ISERROR(SEARCH("Radio Broadcasting",BZ11)),"","561") | KE11: =if(ISERROR(SEARCH("Television Broadcasting",BZ11)),"","562") | KF11: =if(ISERROR(SEARCH("Internet Publishing and Broadcasting",BY11)),"","570") | KG11: =if(ISERROR(SEARCH("Data Processing, Web Hosting and Electronic Information Storage Services",CB11)),"","592") | KH11: =if(ISERROR(SEARCH("Internet Service Providers and Web Search Portals",CB11)),"","591") | KI11: =if(ISERROR(SEARCH("Libraries and Archives",CD11)),"","601") | KJ11: =if(ISERROR(SEARCH("Other Information Services",CD11)),"","602") | KK11: =if(ISERROR(SEARCH("Motion Picture and Video Activities",CE11)),"","551") | KL11: =if(ISERROR(SEARCH("Sound Recording and Music Publishing",CE11)),"","552") | KM11: =if(ISERROR(SEARCH("Newspaper, Periodical, Book and Directory Publishing",CH11)),"","541") | KN11: =if(ISERROR(SEARCH("Software Publishing",CH11)),"","542") | KO11: =if(ISERROR(SEARCH("Telecommunications Services",BY11)),"","580") | KP11: =if(ISERROR(SEARCH("Basic Chemical Manufacturing",CK11)),"","181") | KQ11: =if(ISERROR(SEARCH("Basic Polymer Manufacturing",CK11)),"","182") | KR11: =if(ISERROR(SEARCH("Cleaning Compound and Toiletry Preparation Manufacturing",CK11)),"","185") | KS11: =if(ISERROR(SEARCH("Fertiliser and Pesticide Manufacturing",CK11)),"","183") | KT11: =if(ISERROR(SEARCH("Pharmaceutical and Medicinal Product Manufacturing",CK11)),"","184") | KU11: =if(ISERROR(SEARCH("Other Basic Chemical Product Manufacturing",CK11)),"","189") | KV11: =if(ISERROR(SEARCH("Beverage Manufacturing",CR11)),"","121") | KW11: =if(ISERROR(SEARCH("Cigarette and Tobacco Product Manufacturing",CR11)),"","122") | KX11: =if(ISERROR(SEARCH("Iron and Steel Forging",CT11)),"","221") | KY11: =if(ISERROR(SEARCH("Metal Container Manufacturing",CT11)),"","223") | KZ11: =if(ISERROR(SEARCH("Sheet Metal Product Manufacturing (except Metal Structural and Container Products)",CT11)),"","224") | LA11: =if(ISERROR(SEARCH("Structural Metal Product Manufacturing",CT11)),"","222") | LB11: =if(ISERROR(SEARCH("Other Fabricated Metal Product Manufacturing",CT11)),"","229") | LC11: =if(ISERROR(SEARCH("Bakery Product Manufacturing",CX11)),"","117") | LD11: =if(ISERROR(SEARCH("Dairy Product Manufacturing",CX11)),"","113") | LE11: =if(ISERROR(SEARCH("Fruit and Vegetable Processing",CX11)),"","114") | LF11: =if(ISERROR(SEARCH("Grain Mill and Cereal Product Manufacturing",CX11)),"","116") | LG11: =if(ISERROR(SEARCH("Meat and Meat Product Manufacturing",CX11)),"","111") | LH11: =if(ISERROR(SEARCH("Oil and Fat Manufacturing",CX11)),"","115") | LI11: =if(ISERROR(SEARCH("Seafood Processing",CX11)),"","112") | LJ11: =if(ISERROR(SEARCH("Sugar and Confectionery Manufacturing",CX11)),"","118") | LK11: =if(ISERROR(SEARCH("Other Food Product Manufacturing",CX11)),"","119") | LL11: =if(ISERROR(SEARCH("Furniture Manufacturing",DE11)),"","251") | LM11: =if(ISERROR(SEARCH("Other Manufacturing",DE11)),"","259") | LN11: =if(ISERROR(SEARCH("Computer and Electronic Equipment Manufacturing",DH11)),"","242") | LO11: =if(ISERROR(SEARCH("Domestic Appliance Manufacturing",DH11)),"","244") | LP11: =if(ISERROR(SEARCH("Electrical Equipment Manufacturing",DH11)),"","243") | LQ11: =if(ISERROR(SEARCH("Professional and Scientific Equipment Manufacturing",DH11)),"","241") | LR11: =if(ISERROR(SEARCH("Pump, Compressor, Heating and Ventilation Equipment Manufacturing",DH11)),"","245") | LS11: =if(ISERROR(SEARCH("Specialised Machinery and Equipment Manufacturing",DH11)),"","246") | LT11: =if(ISERROR(SEARCH("Other Machinery and Equipment Manufacturing",DH11)),"","249") | LU11: =if(ISERROR(SEARCH("Cement, Lime, Plaster and Concrete Product Manufacturing",DP11)),"","203") | LV11: =if(ISERROR(SEARCH("Ceramic Product Manufacturing",DP11)),"","202") | LW11: =if(ISERROR(SEARCH("Glass and Glass Product Manufacturing",DP11)),"","201") | LX11: =if(ISERROR(SEARCH("Other Non-Metallic Mineral Product Manufacturing",DP11)),"","209") | LY11: =if(ISERROR(SEARCH("Petroleum Refining and Petroleum Fuel Manufacturing",DS11)),"","170") | LZ11: =if(ISERROR(SEARCH("Other Petroleum and Coal Product Manufacturing",DS11)),"","170") | MA11: =if(ISERROR(SEARCH("Natural Rubber Product Manufacturing",DT11)),"","192") | MB11: =if(ISERROR(SEARCH("Polymer Product Manufacturing",DT11)),"","191") | MC11: =if(ISERROR(SEARCH("Basic Ferrous Metal Manufacturing",DV11)),"","211") | MD11: =if(ISERROR(SEARCH("Basic Ferrous Metal Product Manufacturing",DV11)),"","212") | ME11: =if(ISERROR(SEARCH("Basic Non-Ferrous Metal Manufacturing",DV11)),"","213") | MF11: =if(ISERROR(SEARCH("Basic Non-Ferrous Metal Product Manufacturing",DV11)),"","214") | MG11: =if(ISERROR(SEARCH("Printing and Printing Support Services",EA11)),"","161") | MH11: =if(ISERROR(SEARCH("Reproduction of Recorded Media",EA11)),"","162") | MI11: =if(ISERROR(SEARCH("Converted Paper Product Manufacturing",EC11)),"","152") | MJ11: =if(ISERROR(SEARCH("Pulp, Paper and Paperboard Manufacturing",EC11)),"","151") | MK11: =if(ISERROR(SEARCH("Clothing and Footwear Manufacturing",EE11)),"","135") | ML11: =if(ISERROR(SEARCH("Knitted Product Manufacturing",EE11)),"","134") | MM11: =if(ISERROR(SEARCH("Leather Tanning, Fur Dressing and Leather Product Manufacturing",EE11)),"","132") | MN11: =if(ISERROR(SEARCH("Textile Manufacturing",EE11)),"","131") | MO11: =if(ISERROR(SEARCH("Textile Product Manufacturing",EE11)),"","133") | MP11: =if(ISERROR(SEARCH("Motor Vehicle and Motor Vehicle Part Manufacturing",EI11)),"","231") | MQ11: =if(ISERROR(SEARCH("Other Transport Equipment Manufacturing",EI11)),"","239") | MR11: =if(ISERROR(SEARCH("Log Sawmilling and Timber Dressing",EL11)),"","141") | MS11: =if(ISERROR(SEARCH("Other Wood Product Manufacturing",EL11)),"","149") | MT11: =if(ISERROR(SEARCH("Coal Mining",EO11)),"","060") | MU11: =if(ISERROR(SEARCH("Exploration",EP11)),"","101") | MV11: =if(ISERROR(SEARCH("Other Mining Support Services",EP11)),"","109") | MW11: =if(ISERROR(SEARCH("Metal Ore Mining",EO11)),"","080") | MX11: =if(ISERROR(SEARCH("Construction Material Mining",ES11)),"","091") | MY11: =if(ISERROR(SEARCH("Oil and Gas Extraction",EO11)),"","070") | MZ11: =if(ISERROR(SEARCH("Other Non-Metallic Mineral Mining and Quarrying",ES11)),"","099") | NA11: =if(ISERROR(SEARCH("Computer System Design and Related Services",EU11)),"","700") | NB11: =if(ISERROR(SEARCH("Advertising Services",EV11)),"","694") | NC11: =if(ISERROR(SEARCH("Architectural, Engineering and Technical Services",EV11)),"","692") | ND11: =if(ISERROR(SEARCH("Legal and Accounting Services",EV11)),"","693") | NE11: =if(ISERROR(SEARCH("Management and Related Consulting Services",EV11)),"","696") | NF11: =if(ISERROR(SEARCH("Market Research and Statistical Services",EV11)),"","695") | NG11: =if(ISERROR(SEARCH("Scientific Research Services",EV11)),"","691") | NH11: =if(ISERROR(SEARCH("Veterinary Services",EV11)),"","697") | NI11: =if(ISERROR(SEARCH("Other Professional, Scientific and Technical Services",EV11)),"","699") | NJ11: =if(ISERROR(SEARCH("Central Government Administration",FB11)),"","751") | NK11: =if(ISERROR(SEARCH("State Government Administration",FB11)),"","752") | NL11: =if(ISERROR(SEARCH("Local Government Administration",FB11)),"","753") | NM11: =if(ISERROR(SEARCH("Justice",FB11)),"","754") | NN11: =if(ISERROR(SEARCH("Government Representation",FB11)),"","755") | NO11: =if(ISERROR(SEARCH("Defence",FA11)),"","760") | NP11: =if(ISERROR(SEARCH("Public Order and Safety Services",FD11)),"","771") | NQ11: =if(ISERROR(SEARCH("Regulatory Services",FD11)),"","772") | NR11: =if(ISERROR(SEARCH("Property Operators",FG11)),"","671") | NS11: =if(ISERROR(SEARCH("Real Estate Services",FG11)),"","672") | NT11: =if(ISERROR(SEARCH("Farm Animal and Bloodstock Leasing",FI11)),"","662") | NU11: =if(ISERROR(SEARCH("Motor Vehicle and Transport Equipment Rental and Hiring",FI11)),"","661") | NV11: =if(ISERROR(SEARCH("Non-Financial Intangible Assets (Except Copyrights) Leasing",FI11)),"","664") | NW11: =if(ISERROR(SEARCH("Other Goods and Equipment Rental and Hiring",FI11)),"","663") | NX11: =if(ISERROR(SEARCH("Supermarket and Grocery Stores",FM11)),"","411") | NY11: =if(ISERROR(SEARCH("Specialised Food Retailing",FM11)),"","412") | NZ11: =if(ISERROR(SEARCH("Fuel Retailing",FL11)),"","400") | OA11: =if(ISERROR(SEARCH("Motor Vehicle Parts and Tyre Retailing",FO11)),"","392") | OB11: =if(ISERROR(SEARCH("Motor Vehicle Retailing",FO11)),"","391") | OC11: =if(ISERROR(SEARCH("Non-Store Retailing",FR11)),"","431") | OD11: =if(ISERROR(SEARCH("Retail Commission-Based Buying and/or Selling",FR11)),"","432") | OE11: =if(ISERROR(SEARCH("Clothing, Footwear and Personal Accessory Retailing",FS11)),"","425") | OF11: =if(ISERROR(SEARCH("Department Stores",FS11)),"","426") | OG11: =if(ISERROR(SEARCH("Electrical and Electronic Goods Retailing",FS11)),"","422") | OH11: =if(ISERROR(SEARCH("Furniture, Floor Coverings, Houseware and Textile Goods Retailing",FS11)),"","421") | OI11: =if(ISERROR(SEARCH("Hardware, Building and Garden Supplies Retailing",FS11)),"","423") | OJ11: =if(ISERROR(SEARCH("Pharmaceutical and Other Store-Based Retailing",FS11)),"","427") | OK11: =if(ISERROR(SEARCH("Recreational Goods Retailing",FS11)),"","424") | OL11: =if(ISERROR(SEARCH("Air and Space Transport",FZ11)),"","490") | OM11: =if(ISERROR(SEARCH("Postal and Courier Pick-up and Delivery Services",FZ11)),"","510") | ON11: =if(ISERROR(SEARCH("Rail Freight Transport",GB11)),"","471") | OO11: =if(ISERROR(SEARCH("Rail Passenger Transport",GB11)),"","472") | OP11: =if(ISERROR(SEARCH("Road Freight Transport",GC11)),"","461") | OQ11: =if(ISERROR(SEARCH("Road Passenger Transport",GC11)),"","462") | OR11: =if(ISERROR(SEARCH("Airport Operations and Other Air Transport Support Services",GE11)),"","522") | OS11: =if(ISERROR(SEARCH("Water Transport Support Services",GE11)),"","521") | OT11: =if(ISERROR(SEARCH("Other Transport Support Services",GE11)),"","529") | OU11: =if(ISERROR(SEARCH("Warehousing and Storage Services",FZ11)),"","530") | OV11: =if(ISERROR(SEARCH("Water Freight Transport",GI11)),"","481") | OW11: =if(ISERROR(SEARCH("Water Freight Transport",GI11)),"","482") | OX11: =if(ISERROR(SEARCH("Pipeline and Other Transport",GJ11)),"","502") | OY11: =if(ISERROR(SEARCH("Scenic and Sightseeing Transport",GJ11)),"","501") | OZ11: =if(ISERROR(SEARCH("Agricultural Product Wholesaling",GM11)),"","331") | PA11: =if(ISERROR(SEARCH("Mineral, Metal and Chemical Wholesaling",GM11)),"","332") | PB11: =if(ISERROR(SEARCH("Timber and Hardware Goods Wholesaling",GM11)),"","333") | PC11: =if(ISERROR(SEARCH("Commission-Based Wholesaling",GL11)),"","380") | PD11: =if(ISERROR(SEARCH("Grocery, Liquor and Tobacco Product Wholesaling",GL11)),"","360") | PE11: =if(ISERROR(SEARCH("Specialised Industrial Machinery and Equipment Wholesaling",GR11)),"","341") | PF11: =if(ISERROR(SEARCH("Other Machinery and Equipment Wholesaling",GR11)),"","349") | PG11: =if(ISERROR(SEARCH("Motor Vehicle and Motor Vehicle Parts Wholesaling",GL11)),"","350") | PH11: =if(ISERROR(SEARCH("Textile, Clothing and Footwear Wholesaling",GV11)),"","371") | PI11: =if(ISERROR(SEARCH("Furniture, Floor Covering and Other Goods Wholesaling",GV11)),"","373") | PJ11: =if(ISERROR(SEARCH("Pharmaceutical and Toiletry Goods Wholesaling",GV11)),"","372") | PK11: =if(ISERROR(SEARCH("Civic, Professional and Other Interest Group Services",GZ11)),"","955") | PL11: =if(ISERROR(SEARCH("Funeral, Crematorium and Cemetery Services",GZ11)),"","952") | PM11: =if(ISERROR(SEARCH("Personal Care Services",GZ11)),"","951") | PN11: =if(ISERROR(SEARCH("Religious Services",GZ11)),"","954") | PO11: =if(ISERROR(SEARCH("Other Personal Services",GZ11)),"","953") | PP11: =if(ISERROR(SEARCH("Private Households Employing Staff and Undifferentiated Goods- and Service-Producing Activities of Households for Own Use",GY11)),"","960") | PQ11: =if(ISERROR(SEARCH("Automotive Repair and Maintenance",HE11)),"","941") | PR11: =if(ISERROR(SEARCH("Machinery and Equipment Repair and Maintenance",HE11)),"","942") | PS11: =if(ISERROR(SEARCH("Other Repair and Maintenance",HE11)),"","949")
